Workbook
Name ABEILLE: 'CT à Transf'!$AA$16:$BI$16
Name AFER: 'CT à Transf'!$AA$17:$BI$17
Name AG2R_LA_MONDIALE: 'CT à Transf'!$AA$18:$BI$18
Name AGEAS: 'CT à Transf'!$AA$19:$BI$19
Name AGIPI: 'CT à Transf'!$AA$20:$BI$20
Name ALLIANZ: 'CT à Transf'!$AA$21:$BI$21
Name ALPTIS: 'CT à Transf'!$AA$22:$BI$22
Name APICIL: 'CT à Transf'!$AA$23:$BI$23
Name APRIL: 'CT à Transf'!$AA$24:$BI$24
Name AREAS: 'CT à Transf'!$AA$25:$BI$25
Name AXA: 'CT à Transf'!$AA$26:$BI$26
Name BANQUE_POPULAIRE: 'CT à Transf'!$AA$27:$BI$27
Name BNP: 'CT à Transf'!$AA$28:$BI$28
Name CAISSE_D_EPARGNE: 'CT à Transf'!$AA$29:$BI$29
Name CARDIF: 'CT à Transf'!$AA$30:$BI$30
Name Celibataire_Veuf_Divorce: MEPPER2!$E$32
Name Compagnies: 'CT à Transf'!$Z$16:$Z$68
Name CREDIT_AGRICOLE: 'CT à Transf'!$AA$31:$BI$31
Name CREDIT_DU_NORD: 'CT à Transf'!$AA$32:$BI$32
Name CREDIT_MUTUEL: 'CT à Transf'!$AA$33:$BI$33
Name EPSENS: 'CT à Transf'!$AA$34:$BI$34
Name EPSOR: 'CT à Transf'!$AA$35:$BI$35
Name ERES: 'CT à Transf'!$AA$36:$BI$36
Name GAN: 'CT à Transf'!$AA$37:$BI$37
Name GARANCE: 'CT à Transf'!$AA$38:$BI$38
Name GENERALI: 'CT à Transf'!$AA$39:$BI$39
Name GO_EPARGNE: 'CT à Transf'!$AA$40:$BI$40
Name GROUPAMA: 'CT à Transf'!$AA$41:$BI$41
Name HARMONIE_MUTUELLE: 'CT à Transf'!$AA$42:$BI$42
Name HSBC: 'CT à Transf'!$AA$43:$BI$43
Name LA_BANQUE_POSTALE: 'CT à Transf'!$AA$44:$BI$44
Name LA_MEDICALE: 'CT à Transf'!$AA$45:$BI$45
Name LCL: 'CT à Transf'!$AA$46:$BI$46
Name LPA: 'CT à Transf'!$AA$47:$BI$47
Name MAAF: 'CT à Transf'!$AA$48:$BI$48
Name MACIF: 'CT à Transf'!$AA$49:$BI$49
Name MACSF: 'CT à Transf'!$AA$50:$BI$50
Name MAIF: 'CT à Transf'!$AA$51:$BI$51
Name MALAKOFF_HUMANIS: 'CT à Transf'!$AA$52:$BI$52
Name MAPA: 'CT à Transf'!$AA$53:$BI$53
Name Marie_Pacse: MEPPER2!$E$31:$F$31
Name MATMUT: 'CT à Transf'!$AA$54:$BI$54
Name MEDICIS: 'CT à Transf'!$AA$55:$BI$55
Name MMA: 'CT à Transf'!$AA$56:$BI$56
Name MNRA: 'CT à Transf'!$AA$57:$BI$57
Name NORTIA: 'CT à Transf'!$AA$58:$BI$58
Name OK: TRUE
Name ORADEA: 'CT à Transf'!$AA$59:$BI$59
Name PREFON: 'CT à Transf'!$AA$60:$BI$60
Name PREVOIR: 'CT à Transf'!$AA$61:$BI$61
Name PRIMONIAL: 'CT à Transf'!$AA$62:$BI$62
Name PRO_BTP: 'CT à Transf'!$AA$63:$BI$63
Name Situation: MEPPER2!$D$31:$D$32
Name SMA: 'CT à Transf'!$AA$64:$BI$64
Name SOCIETE_GENERALE: 'CT à Transf'!$AA$65:$BI$65
Name SWISSLIFE: 'CT à Transf'!$AA$66:$BI$66
Name UFF: 'CT à Transf'!$AA$67:$BI$67
Name UMR: 'CT à Transf'!$AA$68:$BI$68

Sheet Login
S1: 122

Sheet Home
B5: =TODAY() -> 46023

Sheet Données
E4: Barème | F4: =YEAR(TODAY()) -> 2026 | Q4: Zoom écran : | R4: 95
B5: =TODAY() -> 46023 | E5: Sur revenus | F5: =F4-1 -> 2025 | Q5: Fin de validité : | R5: 46023
Q6: Date du jour : | R6: =TODAY() -> 46023
F12: Taux | G12: Retraitement | N12: Seuil | P12: Seul | Q12: Couple
D13: 0 | E13: 11498 | F13: 0 | K13: Abattement 1 | L13: 152500 | N13: 250000 | P13: 0 | Q13: 0
D14: =E13+1 -> 11499 | E14: 29315 | F14: 0.11 | G14: =E13*F14 -> 1264.78 | K14: Abattement 2 | L14: 30500 | N14: 500000 | P14: 0.03 | Q14: 0
D15: =E14+1 -> 29316 | E15: 83823 | F15: 0.3 | G15: =(E13-D13)*F15+(E14-E13)*(F15-F14) -> 6834.63 | K15: Fisca > 8 ans | L15: 0.075 | N15: 1000000 | P15: 0.04 | Q15: 0.03
D16: =E15+1 -> 83824 | E16: 180294 | F16: 0.41 | G16: =(E13-D13)*F16+(E14-E13)*(F16-F14)+(E15-E14)*(F16-F15) -> 16055.16 | K16: 152500 | L16: 0.2 | N16: Plus | P16: 0.04 | Q16: 0.04
D17: =E16 -> 180294 | F17: 0.45 | G17: =(E13-D13)*F17+(E14-E13)*(F17-F14)+(E15-E14)*(F17-F15)+(E16-E15)*(F17-F16) -> 23266.92 | K17: 700000 | L17: 0.3125
D18: Plafond du quotient familial | F18: 1791 | G18: 4224 | H18: parents isolés (deux 1ere parts)
D19: Décote (Célib/couple) | E19: Déclenchement | F19: 1964 | G19: 3248
E20: Montant | F20: 889 | G20: 1470
E21: Taux | F21: 0.4525
D22: Exemple Calcul de décote 2023 pour un célibataire : 833 – 45.25 % de l’impôt
F23: =F4 -> 2026 | H23: =F5 -> 2025
D24: Plafond abattement 10% | F24: 14426 | G24: 504 | H24: 14171 | I24: 495 | K24: IS | L24: 0.25
D25: Plafond abt 10% retraités | F25: 4399 | G25: 450 | H25: 4321 | I25: 442 | K25: IS réduit | L25: 0.15
K26: Seuil IS réduit | L26: 42500 | N26: Seuil sortie capital (PERP, Madelin, Art83) (rente mensuelle) | S26: 110
N27: PFL pour capital PERP | S27: 0.075
D28: PFU | F28: 0.128
F35: PS | G35: Deductible
D36: PS (patrimoine et capital) | F36: 0.172 | G36: 0.068
D37: PS sur retraite | E37: Revenu fiscal de ref | G37: ="+/0,25 parts" -> +/0,25 parts | H37: CSG | I37: CRDS | J37: CASA | K37: Maladie | L37: Total | M37: CSG déd
D38: 1 part | E38: 0 | F38: 11432 | G38: 1526 | H38: exo | I38: exo | J38: exo | K38: exo | L38: =0 -> 0 | M38: 0
E39: =F38+1 -> 11433 | F39: 14944 | G39: 1995 | H39: 0.038 | I39: 0.005 | J39: exo | K39: exo | L39: =H39+I39 -> 0.043 | M39: 0.038
E40: =F39+1 -> 14945 | F40: 23193 | G40: 3095.5 | H40: 0.066 | I40: 0.005 | J40: 0.003 | K40: 0.01 | L40: =H40+I40+J40+K40 -> 0.084 | M40: 0.042
E41: =F40 -> 23193 | H41: 0.083 | I41: 0.005 | J41: 0.003 | K41: 0.01 | L41: =H41+I41+J41+K41 -> 0.101 | M41: 0.059
D49: Historique plafonds sécurité sociale | H49: Type de produit | L49: Divers
D50: 2019 | E50: 40524 | F50: Ne pas étendre cette liste, remplacer du plus ancien au plus récent | H50: Madelin (154 bis CGI) | L50: Marié/pacsé | M50: Situation familiale
D51: 2020 | E51: 41136 | H51: Art 83 CGI | L51: Célibataire/veuf/divorcé
D52: 2021 | E52: 41136 | H52: PERin (154 bis CGI) | L52: Rente Réversible | M52: Type de rente
D53: 2022 | E53: 41136 | H53: PERin (163 Quater CGI) | L53: Rente Non réversible
D54: 2023 | E54: 43992 | H54: PERin non déduit | L54: selon les hypothèses des contrats | M54: Type projection rente
D55: 2024 | E55: 46368 | H55: PERob (Art83 CGI) | L55: sur mesure
D56: 2025 | E56: 47100 | H56: PERP et assimilés
H57: PERCO/PEReco
H58: Assurance vie

Sheet Placement
B5: =TODAY() -> 46023
E12: Placement 1 | F12: Placement 2 | G12: Placement 3 | H12: Assurance vie | J12: Compte titre
H13: SCPI | I13: Produit strucutré distri
D14: Rendement Net de FG | E14: 0.05 | F14: 0.05 | G14: 0.04 | H14: 0.035 | I14: 0.04 | J14: 0.05
D16: Placement Initial | E16: 563750 | F16: 570000 | G16: 100000 | H16: 97000 | I16: 100000 | J16: 100000
D17: Frais d'entrée | G17: 0.03 | H17: 0.085 | I17: 0
D18: Année 1 | E18: =(PRODUCT((E16-(E16*E17)),(POWER($E$14,1))))+(E16-(E16*E17)) -> 591937.5 | F18: =(PRODUCT((F16-(F16*F17)),(POWER($F$14,1))))+(F16-(F16*F17)) -> 598500 | G18: =(PRODUCT((G16-(G16*G17)),(POWER(G14,1))))+(G16-(G16*G17)) -> 100880 | H18: =(PRODUCT(H16,(POWER(H14,1))))+(H16-(H16*H17)) -> 92150 | I18: =(I16-(I16*I17))+(I14*(I16-(I16*I17))) -> 104000 | J18: =(J16-(J16*J17))+(J14*(J16-(J16*J17))) -> 105000
D19: Année 2 | E19: =(PRODUCT(E18,(POWER($E$14,1))))+E18 -> 621534.38 | F19: =(PRODUCT(F18,(POWER($F$14,1))))+F18 -> 628425 | G19: =(PRODUCT(G18,(POWER($G$14,1))))+G18 -> 104915.2 | H19: =(PRODUCT($H$16,(POWER($H$14,1))))+H18 -> 95545 | I19: =(I16-(I16*I17))+((I16-(I16*I17))*$I$14*2) -> 108000 | J19: =(J16-(J16*J17))+((J16-(J16*J17))*J14*2) -> 110000
D20: Année 3 | E20: =(PRODUCT(E19,(POWER($E$14,1))))+E19 -> 652611.09 | F20: =(PRODUCT(F19,(POWER($F$14,1))))+F19 -> 659846.25 | G20: =(PRODUCT(G19,(POWER($G$14,1))))+G19 -> 109111.81 | H20: =(PRODUCT($H$16,(POWER($H$14,1))))+H19 -> 98940 | I20: =(I16-(I16*I17))+((I16-(I16*I17))*I14*3) -> 112000 | J20: =(J16-(J16*J17))+((J16-(J16*J17))*J14*3) -> 115000
D21: Année 4 | E21: =(PRODUCT(E20,(POWER($E$14,1))))+E20 -> 685241.65 | F21: =(PRODUCT(F20,(POWER($F$14,1))))+F20 -> 692838.56 | G21: =(PRODUCT(G20,(POWER($G$14,1))))+G20 -> 113476.28 | H21: =(PRODUCT($H$16,(POWER($H$14,1))))+H20 -> 102335 | I21: =(I16-(I16*I17))+((I16-(I16*I17))*I14*4) -> 116000 | J21: =(J16-(J16*J17))+((J16-(J16*J17))*J14*4) -> 120000
D22: Année 5 | E22: =(PRODUCT(E21,(POWER($E$14,1))))+E21 -> 719503.73 | F22: =(PRODUCT(F21,(POWER($F$14,1))))+F21 -> 727480.49 | G22: =(PRODUCT(G21,(POWER($G$14,1))))+G21 -> 118015.33 | H22: =(PRODUCT($H$16,(POWER($H$14,1))))+H21 -> 105730 | I22: =(I16-(I16*I17))+((I16-(I16*I17))*I14*5) -> 120000 | J22: =(J16-(J16*J17))+((J16-(J16*J17))*J14*5) -> 125000
D23: Année 6 | E23: =(PRODUCT(E22,(POWER($E$14,1))))+E22 -> 755478.92 | F23: =(PRODUCT(F22,(POWER($F$14,1))))+F22 -> 763854.52 | G23: =(PRODUCT(G22,(POWER($G$14,1))))+G22 -> 122735.94 | H23: =(PRODUCT($H$16,(POWER($H$14,1))))+H22 -> 109125 | I23: =(I16-(I16*I17))+((I16-(I16*I17))*I14*6) -> 124000 | J23: =(J16-(J16*J17))+((J16-(J16*J17))*J14*6) -> 130000
D24: Année 7 | E24: =(PRODUCT(E23,(POWER($E$14,1))))+E23 -> 793252.86 | F24: =(PRODUCT(F23,(POWER($F$14,1))))+F23 -> 802047.24 | G24: =(PRODUCT(G23,(POWER($G$14,1))))+G23 -> 127645.38 | H24: =(PRODUCT($H$16,(POWER($H$14,1))))+H23 -> 112520 | I24: =(I16-(I16*I17))+((I16-(I16*I17))*I14*7) -> 128000 | J24: =(J16-(J16*J17))+((J16-(J16*J17))*J14*7) -> 135000
D25: Année 8 | E25: =(PRODUCT(E24,(POWER($E$14,1))))+E24 -> 832915.51 | F25: =(PRODUCT(F24,(POWER($F$14,1))))+F24 -> 842149.6 | G25: =(PRODUCT(G24,(POWER($G$14,1))))+G24 -> 132751.2 | H25: =(PRODUCT(H16,(POWER(H14,1))))+H24 -> 115915 | I25: =(I16-(I16*I17))+((I16-(I16*I17))*I14*8) -> 132000 | J25: =(J16-(J16*J17))+((J16-(J16*J17))*J14*8) -> 140000
D26: Année 9 | E26: =(PRODUCT(E25,(POWER($E$14,1))))+E25 -> 874561.28 | F26: =(PRODUCT(F25,(POWER($F$14,1))))+F25 -> 884257.08 | G26: =(PRODUCT(G25,(POWER($G$14,1))))+G25 -> 138061.25 | H26: =(PRODUCT($H$16,(POWER($H$14,1))))+H25 -> 119310 | I26: =(I16-(I16*I17))+((I16-(I16*I17))*I14*9) -> 136000 | J26: =(J16-(J16*J17))+((J16-(J16*J17))*J14*9) -> 145000
D27: Année 10 | E27: =(PRODUCT(E26,(POWER($E$14,1))))+E26 -> 918289.35 | F27: =(PRODUCT(F26,(POWER($F$14,1))))+F26 -> 928469.94 | G27: =(PRODUCT(G26,(POWER($G$14,1))))+G26 -> 143583.7 | H27: =(PRODUCT($H$16,(POWER($H$14,1))))+H26 -> 122705 | I27: =(I16-(I16*I17))+((I16-(I16*I17))*I14*10) -> 140000 | J27: =(J16-(J16*J17))+((J16-(J16*J17))*J14*10) -> 150000
D28: Année 11 | E28: =(PRODUCT(E27,(POWER($E$14,1))))+E27 -> 964203.81 | F28: =(PRODUCT(F27,(POWER($F$14,1))))+F27 -> 974893.43 | G28: =(PRODUCT(G27,(POWER($G$14,1))))+G27 -> 149327.04 | H28: =(PRODUCT($H$16,(POWER($H$14,1))))+H27 -> 126100
D29: Année 12 | E29: =(PRODUCT(E28,(POWER($E$14,1))))+E28 -> 1012414 | F29: =(PRODUCT(F28,(POWER($F$14,1))))+F28 -> 1023638.1 | G29: =(PRODUCT(G28,(POWER($G$14,1))))+G28 -> 155300.13 | H29: =(PRODUCT($H$16,(POWER($H$14,1))))+H28 -> 129495
D30: Année 13 | E30: =(PRODUCT(E29,(POWER($E$14,1))))+E29 -> 1063034.7 | F30: =(PRODUCT(F29,(POWER($F$14,1))))+F29 -> 1074820 | G30: =(PRODUCT(G29,(POWER($G$14,1))))+G29 -> 161512.13 | H30: =(PRODUCT($H$16,(POWER($H$14,1))))+H29 -> 132890
D31: Année 14 | E31: =(PRODUCT(E30,(POWER($E$14,1))))+E30 -> 1116186.4 | F31: =(PRODUCT(F30,(POWER($F$14,1))))+F30 -> 1128561 | G31: =(PRODUCT(G30,(POWER($G$14,1))))+G30 -> 167972.62 | H31: =(PRODUCT($H$16,(POWER($H$14,1))))+H30 -> 136285
D32: Année 15 | E32: =(PRODUCT(E31,(POWER(E14,1))))+E31 -> 1171995.8 | F32: =(PRODUCT(F31,(POWER($F$14,1))))+F31 -> 1184989.1 | G32: =(PRODUCT(G31,(POWER($G$14,1))))+G31 -> 174691.52 | H32: =(PRODUCT(H16,(POWER(H14,1))))+H31 -> 139680
D33: Année 16 | E33: =(PRODUCT(E32,(POWER(E14,1))))+E32 -> 1230595.5 | F33: =(PRODUCT(F32,(POWER($F$14,1))))+F32 -> 1244238.5 | G33: =(PRODUCT(G32,(POWER($G$14,1))))+G32 -> 181679.18 | H33: =(PRODUCT(H16,(POWER(H14,1))))+H32 -> 143075
D34: Durée "sur mesure" du placement 1
D35: 20 | E35: =(E16*(1-E17))*(1+E14)^D35 -> 1495796.6

Sheet Crédit
B5: =TODAY() -> 46023
E13: Somme empruntée | G13: 447072 | I13: Mensualité | K13: =-PMT(G14/12,G15,G13) -> 4399.998
E14: Taux d'intérêt de l'emprunt | G14: 0.034 | I14: Soit annuellement | K14: =K13*12 -> 52799.976
E15: Durée de l'emprunt en mois | G15: 120 | I15: Mensualité avec assurance | K15: =K13+(G13*(G16/12)) -> 4399.998
E16: Taux de l'assurance (Ci) | I16: Soit annuellement | K16: =K15*12 -> 52799.976
E17: Date début emprunt | G17: 45658 | I17: Coût total du crédit | K17: =SUM(G21:G381) -> 80927.757
I18: Coût assurance | K18: =SUM(K21:K381) -> 0
E20: Année | F20: Mois | G20: Intérets | H20: Amortissement | I20: CRD en fin de période | K20: Assurance
E21: =IF(F21<>0,G17,0) -> 45658 | F21: =IF(G15>=1,1,"") -> 1 | G21: =IFERROR(IF(F21<>"",-IPMT($G$14/12,F21,$G$15,$G$13),""),0) -> 1266.704 | H21: =IFERROR(IF(F21<>"",-PPMT($G$14/12,F21,$G$15,$G$13),""),0) -> 3133.294 | I21: =IF(F21<>"",G13-H21,"") -> 443938.71 | K21: =IF(F21<>"",$G$13*($G$16/12),"") -> 0
E22: =IFERROR(IF($G$15<=F21,"",DATE(YEAR(E21),MONTH(E21)+1,DAY(E21))),"") -> 45689 | F22: =IF(OR(F21="",F21=$G$15),"",IF(F21<$G$15,F21+1,0)) -> 2 | G22: =IFERROR(IF(F22<>"",-IPMT($G$14/12,F22,$G$15,$G$13),""),0) -> 1257.8263 | H22: =IFERROR(IF(F22<>"",-PPMT($G$14/12,F22,$G$15,$G$13),""),0) -> 3142.1716 | I22: =IF(F22<>"",I21-H22,"") -> 440796.53 | K22: =IF(F22<>"",$G$13*($G$16/12),"") -> 0
E23: =IFERROR(IF($G$15<=F22,"",DATE(YEAR(E22),MONTH(E22)+1,DAY(E22))),"") -> 45717 | F23: =IF(OR(F22="",F22=$G$15),"",IF(F22<$G$15,F22+1,0)) -> 3 | G23: =IFERROR(IF(F23<>"",-IPMT($G$14/12,F23,$G$15,$G$13),""),0) -> 1248.9235 | H23: =IFERROR(IF(F23<>"",-PPMT($G$14/12,F23,$G$15,$G$13),""),0) -> 3151.0745 | I23: =IF(F23<>"",I22-H23,"") -> 437645.46 | K23: =IF(F23<>"",$G$13*($G$16/12),"") -> 0
E24: =IFERROR(IF($G$15<=F23,"",DATE(YEAR(E23),MONTH(E23)+1,DAY(E23))),"") -> 45748 | F24: =IF(OR(F23="",F23=$G$15),"",IF(F23<$G$15,F23+1,0)) -> 4 | G24: =IFERROR(IF(F24<>"",-IPMT($G$14/12,F24,$G$15,$G$13),""),0) -> 1239.9955 | H24: =IFERROR(IF(F24<>"",-PPMT($G$14/12,F24,$G$15,$G$13),""),0) -> 3160.0025 | I24: =IF(F24<>"",I23-H24,"") -> 434485.46 | K24: =IF(F24<>"",$G$13*($G$16/12),"") -> 0
E25: =IFERROR(IF($G$15<=F24,"",DATE(YEAR(E24),MONTH(E24)+1,DAY(E24))),"") -> 45778 | F25: =IF(OR(F24="",F24=$G$15),"",IF(F24<$G$15,F24+1,0)) -> 5 | G25: =IFERROR(IF(F25<>"",-IPMT($G$14/12,F25,$G$15,$G$13),""),0) -> 1231.0421 | H25: =IFERROR(IF(F25<>"",-PPMT($G$14/12,F25,$G$15,$G$13),""),0) -> 3168.9558 | I25: =IF(F25<>"",I24-H25,"") -> 431316.5 | K25: =IF(F25<>"",$G$13*($G$16/12),"") -> 0
E26: =IFERROR(IF($G$15<=F25,"",DATE(YEAR(E25),MONTH(E25)+1,DAY(E25))),"") -> 45809 | F26: =IF(OR(F25="",F25=$G$15),"",IF(F25<$G$15,F25+1,0)) -> 6 | G26: =IFERROR(IF(F26<>"",-IPMT($G$14/12,F26,$G$15,$G$13),""),0) -> 1222.0634 | H26: =IFERROR(IF(F26<>"",-PPMT($G$14/12,F26,$G$15,$G$13),""),0) -> 3177.9346 | I26: =IF(F26<>"",I25-H26,"") -> 428138.57 | K26: =IF(F26<>"",$G$13*($G$16/12),"") -> 0
E27: =IFERROR(IF($G$15<=F26,"",DATE(YEAR(E26),MONTH(E26)+1,DAY(E26))),"") -> 45839 | F27: =IF(OR(F26="",F26=$G$15),"",IF(F26<$G$15,F26+1,0)) -> 7 | G27: =IFERROR(IF(F27<>"",-IPMT($G$14/12,F27,$G$15,$G$13),""),0) -> 1213.0593 | H27: =IFERROR(IF(F27<>"",-PPMT($G$14/12,F27,$G$15,$G$13),""),0) -> 3186.9387 | I27: =IF(F27<>"",I26-H27,"") -> 424951.63 | K27: =IF(F27<>"",$G$13*($G$16/12),"") -> 0
E28: =IFERROR(IF($G$15<=F27,"",DATE(YEAR(E27),MONTH(E27)+1,DAY(E27))),"") -> 45870 | F28: =IF(OR(F27="",F27=$G$15),"",IF(F27<$G$15,F27+1,0)) -> 8 | G28: =IFERROR(IF(F28<>"",-IPMT($G$14/12,F28,$G$15,$G$13),""),0) -> 1204.0296 | H28: =IFERROR(IF(F28<>"",-PPMT($G$14/12,F28,$G$15,$G$13),""),0) -> 3195.9684 | I28: =IF(F28<>"",I27-H28,"") -> 421755.66 | K28: =IF(F28<>"",$G$13*($G$16/12),"") -> 0
E29: =IFERROR(IF($G$15<=F28,"",DATE(YEAR(E28),MONTH(E28)+1,DAY(E28))),"") -> 45901 | F29: =IF(OR(F28="",F28=$G$15),"",IF(F28<$G$15,F28+1,0)) -> 9 | G29: =IFERROR(IF(F29<>"",-IPMT($G$14/12,F29,$G$15,$G$13),""),0) -> 1194.9744 | H29: =IFERROR(IF(F29<>"",-PPMT($G$14/12,F29,$G$15,$G$13),""),0) -> 3205.0236 | I29: =IF(F29<>"",I28-H29,"") -> 418550.64 | K29: =IF(F29<>"",$G$13*($G$16/12),"") -> 0
E30: =IFERROR(IF($G$15<=F29,"",DATE(YEAR(E29),MONTH(E29)+1,DAY(E29))),"") -> 45931 | F30: =IF(OR(F29="",F29=$G$15),"",IF(F29<$G$15,F29+1,0)) -> 10 | G30: =IFERROR(IF(F30<>"",-IPMT($G$14/12,F30,$G$15,$G$13),""),0) -> 1185.8935 | H30: =IFERROR(IF(F30<>"",-PPMT($G$14/12,F30,$G$15,$G$13),""),0) -> 3214.1045 | I30: =IF(F30<>"",I29-H30,"") -> 415336.53 | K30: =IF(F30<>"",$G$13*($G$16/12),"") -> 0
E31: =IFERROR(IF($G$15<=F30,"",DATE(YEAR(E30),MONTH(E30)+1,DAY(E30))),"") -> 45962 | F31: =IF(OR(F30="",F30=$G$15),"",IF(F30<$G$15,F30+1,0)) -> 11 | G31: =IFERROR(IF(F31<>"",-IPMT($G$14/12,F31,$G$15,$G$13),""),0) -> 1176.7868 | H31: =IFERROR(IF(F31<>"",-PPMT($G$14/12,F31,$G$15,$G$13),""),0) -> 3223.2111 | I31: =IF(F31<>"",I30-H31,"") -> 412113.32 | K31: =IF(F31<>"",$G$13*($G$16/12),"") -> 0
E32: =IFERROR(IF($G$15<=F31,"",DATE(YEAR(E31),MONTH(E31)+1,DAY(E31))),"") -> 45992 | F32: =IF(OR(F31="",F31=$G$15),"",IF(F31<$G$15,F31+1,0)) -> 12 | G32: =IFERROR(IF(F32<>"",-IPMT($G$14/12,F32,$G$15,$G$13),""),0) -> 1167.6544 | H32: =IFERROR(IF(F32<>"",-PPMT($G$14/12,F32,$G$15,$G$13),""),0) -> 3232.3436 | I32: =IF(F32<>"",I31-H32,"") -> 408880.98 | K32: =IF(F32<>"",$G$13*($G$16/12),"") -> 0
E33: =IFERROR(IF($G$15<=F32,"",DATE(YEAR(E32),MONTH(E32)+1,DAY(E32))),"") -> 46023 | F33: =IF(OR(F32="",F32=$G$15),"",IF(F32<$G$15,F32+1,0)) -> 13 | G33: =IFERROR(IF(F33<>"",-IPMT($G$14/12,F33,$G$15,$G$13),""),0) -> 1158.4961 | H33: =IFERROR(IF(F33<>"",-PPMT($G$14/12,F33,$G$15,$G$13),""),0) -> 3241.5019 | I33: =IF(F33<>"",I32-H33,"") -> 405639.48 | K33: =IF(F33<>"",$G$13*($G$16/12),"") -> 0
... E381: =IFERROR(IF($G$15<=F380,"",DATE(YEAR(E380),MONTH(E380)+1,DAY(E380))),"") | F381: =IF(OR(F380="",F380=$G$15),"",IF(F380<$G$15,F380+1,0)) | G381: =IFERROR(IF(F381<>"",-IPMT($G$14/12,F381,$G$15,$G$13),""),0) | H381: =IFERROR(IF(F381<>"",-PPMT($G$14/12,F381,$G$15,$G$13),""),0) | I381: =IF(F381<>"",I380-H381,"") | K381: =IF(F381<>"",$G$13*($G$16/12),"")

Sheet IR
B5: =TODAY() -> 46023
A7: Barème | B7: =Données!F4 -> 2026
A8: sur revenus | B8: =B7-1 -> 2025
D13: Situation familiale | G13: Marié/pacsé | J13: Estimation IR
J14: TMI… | K14: =U25 -> 0 | L14: =U26 -> 0.11 | M14: =U27 -> 0.3 | N14: =U28 -> 0.41 | O14: =U29 -> 0.45
D15: Nombre de parts | G15: =IF(G13="",0,IF(G13="Célibataire/veuf/divorcé",1,2)+(I15*0.25)) -> 2 | I15: 0 | J15: IR… | K15: =S34 -> 8830.74
D16: Isolé | J16: Montant des revenus dans cette TMI : | N16: =IF(W34<0,0,W34) -> 16370
J17: ="+CEHR" -> +CEHR | N17: =IF(IR!G13=Données!L51,IF(IR!R22<Données!N13,0,IF(IR!R22<Données!N14,(IR!R22-Données!N13)*Données!P14,((IR!R22-Données!N14)*Données!P15)+((Données!N14-Données!N13)*Données!P14))),IF(IR!R22<Données!N14,0,IF(IR!R22<Données!N15,(IR!R22-Données!N14)*Données!Q15,((IR!R22-Données!N15)*Données!Q16+((Données!N15-Données!N14)*Données!Q15))))) -> 0
H21: Déclarant 1 | K21: Déclarant 2 | T21: Estimation IR | U21: =B7 -> 2026
Q22: Revenu | R22: =IF(G13=Données!L51,IR!H35,H35+K35) -> 75000 | S22: =G15 -> 2 | T22: Situation (marié, ...) | W22: Plafond quotient
D23: Traitement et salaires | H23: 50000 | R23: =IFERROR(R22/S22,0) -> 37500 | S23: =R22/IF(T23=Données!$L$51,1,2) -> 37500 | T23: =G13 -> Marié/pacsé | W23: =IF(OR(G16="Non",G16=""),(S22-(IF(T23="Célibataire/veuf/divorcé",1,2)))*(Données!$F$18*2),IF(T23="Célibataire/veuf/divorcé",IF(S22<=2,(S22-1)*Données!$G$18,Données!$G$18+((S22-2)*Données!$F$18*2)),(S22-(IF(T23="Célibataire/veuf/divorcé",1,2)))*(Données!$F$18*2))) -> 0
D24: Revenus des associés et gérants (article 62 CGI) | R24: 1er T | S24: 2ème T | T24: Tranches | U24: TMI | V24: Retraitement | W24: IR (nb parts) | X24: IR (plaf quotient)
D25: Frais réels | H25: Non | K25: Non | R25: =IF(R23<=T25,R23,0) -> 0 | S25: =IF(S23<=T25,S23,0) -> 0 | T25: =Données!$E$13 -> 11498 | U25: =Données!$F$13 -> 0
D26: Abattement | H26: =IF(H25="Oui",I25,IF((H23+H24)<Données!$G$24,(H23+H24),IF(((H23+H24)*10%)<Données!$G$24,Données!$G$24,IF(((H23+H24)*10%)<Données!$F$24,(H23+H24)*10%,Données!$F$24)))) -> 5000 | K26: =IF(K25="Oui",L25,IF((K23+K24)<Données!$G$24,(K23+K24),IF(((K23+K24)*10%)<Données!$G$24,Données!$G$24,IF(((K23+K24)*10%)<Données!$F$24,(K23+K24)*10%,Données!$F$24)))) -> 0 | R26: =IF(AND(R23<=T26,R23>T25),R23,0) -> 0 | S26: =IF(AND(S23<=T26,S23>T25),S23,0) -> 0 | T26: =Données!$E$14 -> 29315 | U26: =Données!$F$14 -> 0.11 | V26: =T25*U26 -> 1264.78 | W26: =IF(R26>0,(R22*U26)-(V26*S22),0) -> 0 | X26: =IF(S26>0,(R22*U26)-(V26*(IF(T23="Célibataire/veuf/divorcé",1,2)))-W23,0) -> 0
D27: Pensions, retraites et rentes | K27: 20000 | R27: =IF(AND(R23<=T27,R23>T26),R23,0) -> 37500 | S27: =IF(AND(S23<=T27,S23>T26),S23,0) -> 37500 | T27: =Données!$E$15 -> 83823 | U27: =Données!$F$15 -> 0.3 | V27: =(T25-S25)*U27+(T26-T25)*(U27-U26) -> 6834.63 | W27: =IF(R27>0,(R22*U27)-(V27*S22),0) -> 8830.74 | X27: =IF(S27>0,(R22*U27)-(V27*(IF(T23="Célibataire/veuf/divorcé",1,2)))-W23,0) -> 8830.74
D28: Abattement spécial | H28: =IF((H27+K27)<Données!$G$25,(H27+K27),IF(((H27+K27)*10%)<Données!$G$25,Données!$G$25,IF(((H27+K27)*10%)<Données!$F$25,(H27+K27)*10%,Données!$F$25))) -> 2000 | R28: =IF(AND(R23<=T28,R23>T27),R23,0) -> 0 | S28: =IF(AND(S23<=T28,S23>T27),S23,0) -> 0 | T28: =Données!$E$16 -> 180294 | U28: =Données!$F$16 -> 0.41 | V28: =(T25-S25)*U28+(T26-T25)*(U28-U26)+(T27-T26)*(U28-U27) -> 16055.16 | W28: =IF(R28>0,(R22*U28)-(V28*S22),0) -> 0 | X28: =IF(S28>0,(R22*U28)-(V28*(IF(T23="Célibataire/veuf/divorcé",1,2)))-W23,0) -> 0
D29: BIC-BNC-BA imposables | R29: =IF(R23>T28,R23,0) -> 0 | S29: =IF(S23>T28,S23,0) -> 0 | T29: =Données!$E$17 -> 0 | U29: =Données!$F$17 -> 0.45 | V29: =(T25-S25)*U29+(T26-T25)*(U29-U26)+(T27-T26)*(U29-U27)+(T28-T27)*(U29-U28) -> 23266.92 | W29: =IF(R29>0,(R22*U29)-(V29*S22),0) -> 0 | X29: =IF(S29>0,(R22*U29)-(V29*(IF(T23="Célibataire/veuf/divorcé",1,2)))-W23,0) -> 0
D30: Revenus fonciers nets | H30: 12000 | W30: =SUM(W26:W29) -> 8830.74 | X30: =SUM(X26:X29) -> 8830.74
D31: Autres revenus imposables | Q31: IR avant décote | S31: =IF(W30<=X30,X30,W30) -> 8830.74 | V31: TMI | W31: =IF(W30<=X30,IF(X26>0,U26,IF(X27>0,U27,IF(X28>0,U28,IF(X29>0,U29,0)))),IF(W26>0,U26,IF(W27>0,U27,IF(W28>0,U28,IF(W29>0,U29,0))))) -> 0.3
D32: Déductions d'impôt | Q32: Décote | S32: =IF(S31=0,0,IF(AND(S31<Données!$F$19,T23="Célibataire/veuf/divorcé"),Données!$F$20-(S31*Données!$F$21),IF(AND(S31<Données!$G$19,T23="Marié/pacsé"),Données!$G$20-(S31*Données!$F$21),0))) -> 0 | U32: Reste T1 | V32: Reste T2 | W32: Seuil plaf Q | X32: Seuil décote
D33: Crédits, réductions d'impôt | Q33: IR | S33: =IF(S31-S32<0,0,S31-S32) -> 8830.74 | U33: =IF(W26>0,($R$23-$T$25)*$S$22,IF(W27>0,($R$23-T26)*$S$22,IF(W28>0,($R$23-T27)*$S$22,($R$23-T28)*$S$22))) -> 16370 | V33: =IF(X26>0,R22-(T25*IF($T$23=Données!$L$50,2,1)),IF(X27>0,R22-(T26*IF($T$23=Données!$L$50,2,1)),IF(X28>0,R22-(T27*IF($T$23=Données!$L$50,2,1)),R22-(T28*IF($T$23=Données!$L$50,2,1))))) -> 16370 | W33: =(-(V26*S22)/(U27-U26))+((W23+(IF($T$23="Célibataire/veuf/divorcé",1,2)*V27))/(U27-U26)) -> 58630 | X33: =(IF(T23=Données!$L$51,Données!$F$20,Données!$G$20)/(1+Données!$F$21)+(V26*S22))/U26 -> 32196.438
Q34: IR après réductions | S34: =S33-H33-K33 -> 8830.74 | U34: Reste dans la TMI => | W34: =IF(W31=U26,R22-X33,IF(W30>X30,U33,IF(W31=U27,R22-W33,V33))) -> 16370
D35: Revenus imposables | H35: =H23+H24-H26+H27-H28+H29+H30+H31-H32 -> 55000 | K35: =K23+K24-K26+K27+K29+K30+K31-K32 -> 20000

Sheet Impr (1)
A1: Edition étude Page 1 | W1: Titre des diapos
V2: Slide 2 | W2: OBJECTIFS & CONTEXTE | Z2: Vous souhaitez estimer le montant de votre impôt sur le revenu.
V3: Slide 3 | W3: ESTIMATION DE LA SITUATION FISCALE
C31: Etude Impôt sur le revenu
E32: Madame et Monsieur …..............
G34: =TODAY() -> 46023
C36: Prénom CGP NOM CGP
C37: Conseiller en gestion de patrimoine
A41: Edition étude Page 2
B78: =(TODAY()) -> 46023 | E78: Document non contractuel établi en fonction des dispositions fiscales ou sociales en vigueur à la date des présentes | O78: 2
A81: Edition étude Page 3
B101: Estimation de vos revenus | F101: Estimation du revenu imposable | J101: Nombre de parts fiscales | N101: TMI
B103: Déclarant 1 | C103: =IR!H23+IR!H24+IR!H27+IR!H29 -> 50000 | F103: =IR!R22 -> 75000 | J103: =IR!S22 -> 2 | N103: =IR!W31 -> 0.3
B104: Déclarant 2 | C104: =IR!K23+IR!K24+IR!K27+IR!K29 -> 20000
B110: 0 | C110: 0.11 | E110: 0.3 | H110: 0.41 | L110: 0.45
C113: =IF(N103=11%,IR!N16,"") | E113: =IF(N103=30%,IR!N16,"") -> 16370 | H113: =IF(N103=41%,IR!N16,"") | L113: =IF(N103=45%,IR!N16,"")
D116: Estimation du montant de votre impôt sur le revenu : | I116: =IR!K15 -> 8830.74
G117: + | H117: CEHR | I117: =IF(IR!G13=Données!L51,IF(IR!R22<Données!N13,0,IF(IR!R22<Données!N14,(IR!R22-Données!N13)*Données!P14,((IR!R22-Données!N14)*Données!P15)+((Données!N14-Données!N13)*Données!P14))),IF(IR!R22<Données!N14,0,IF(IR!R22<Données!N15,(IR!R22-Données!N14)*Données!Q15,((IR!R22-Données!N15)*Données!Q16+((Données!N15-Données!N14)*Données!Q15))))) -> 0
A121: Edition étude Page 4
A161: Edition étude Page suivante

Sheet Pot ER Mode
B5: =TODAY() -> 46023
D13: Vous souhaitez | J13: =IF(G13="","Faux",IF(AND(G13="Réaliser un versement N (et vérifier si le potentiel le permet)",G15=""),"Faux",IF(AND(G15="Avis IR délivré en",H15=""),"Faux","OK"))) -> Faux
D15: Documents disponibles

Sheet Avis IR N-2
B5: =TODAY() -> 46023
D12: Avis IR | L12: =IF('Pot ER Mode'!G13="Réaliser un versement N (et vérifier si le potentiel le permet)",IF('Pot ER Mode'!G15="Dernière déclaration de revenus",Données!F5,'Pot ER Mode'!H15),Données!F5) -> 2025 | M12: Sur les revenus | N12: =L12-1 -> 2024
D16: PLAFOND EPARGNE RETRAITE
D17: Le plafond disponible pour la déduction des
D18: cotisations verées en | G18: =L12 -> 2025 | H18: , pour la | S18: DIRECTION GENERALE DES FINANCES PUBLIQUES
D19: déclaration des revenus à souscrire en | I19: =G18+1 -> 2026 | J19: est de : | S19: Impôt sur les revenus de | U19: =L12-1 -> 2024
L20: Déclar. 1 | M20: Déclar. 2 | S20: Avis d'impôt établi en | U20: =L12 -> 2025
D21: Plafond total de | F21: =G18-2 -> 2023 | G21: …................................................
D23: Plafond non utilisé pour les revenus de | I23: =F21-1 -> 2022 | J23: …............
D24: Plafond non utilisé pour les revenus de | I24: =I23+1 -> 2023 | J24: …............ | K24: ="+" -> +
D25: Plafond non utilisé pour les revenus de | I25: =I24+1 -> 2024 | J25: …............ | K25: ="+" -> +
D26: Plafond calculé sur les revenus de | I26: =I25 -> 2024 | J26: …............ | K26: ="+" -> +
D28: Plafond pour les cotisations versées en | I28: =I25+1 -> 2025 | J28: …............ | K28: ="=" -> = | L28: =SUM(L23:L27) -> 0 | M28: =SUM(M23:M27) -> 0

Sheet Décla N-1
Z4: Barème | AA4: =Données!F4 -> 2026
B5: =TODAY() -> 46023 | X5: sur revenus | AA5: =AA4-1 -> 2025
Q10: Versements épargne retraite
U11: Déclarant 1 | X11: Déclarant 2
D13: Situation familiale | J13: Estimation IR | Q13: Cotisations PER 163 Quatervicies CGI
J14: TMI… | K14: =U26 -> 0 | L14: =U27 -> 0.11 | M14: =U28 -> 0.3 | N14: =U29 -> 0.41 | O14: =U30 -> 0.45 | Q14: Cotisations PERP et assimilées
D15: Nombre de parts | G15: =IF(G13="",0,IF(G13="Célibataire/veuf/divorcé",1,2)+(I15*0.25)) -> 0 | J15: IR… | K15: =S35 -> 0 | Q15: Cotisations art83 (employeur et salarié sur fiche de paie)
D16: Isolé | J16: Montant des revenus dans cette TMI : | N16: =IF(W35<0,0,W35) -> 0 | Q16: Abondement brut versé par l'employeur PERCO
J17: ="+CEHR" -> +CEHR | N17: =IF('Décla N-1'!G13=Données!L51,IF('Décla N-1'!R23<Données!N13,0,IF('Décla N-1'!R23<Données!N14,('Décla N-1'!R23-Données!N13)*Données!P14,(('Décla N-1'!R23-Données!N14)*Données!P15)+((Données!N14-Données!N13)*Données!P14))),IF('Décla N-1'!R23<Données!N14,0,IF('Décla N-1'!R23<Données!N15,('Décla N-1'!R23-Données!N14)*Données!Q15,(('Décla N-1'!R23-Données!N15)*Données!Q16+((Données!N15-Données!N14)*Données!Q15))))) -> 0 | Q17: Cotisations PER 154 bis CGI
Q18: Cotisations Madelin retraite
Q19: Cotisations prévoyance et santé Madelin (part Madelin)
U20: =IF(U19>0,"",IF(H24+H29>0,"Attention, la cotisation prévoyance entre dans le calcul du potentiel","")) | X20: =IF(G13=Données!L51,"",IF(X19>0,"",IF(K24+K29>0,"Attention, la cotisation prévoyance entre dans le calcul du potentiel","")))
H21: Déclarant 1 | K21: Déclarant 2
T22: Estimation IR | U22: =AA4 -> 2026
D23: Traitement et salaires | Q23: Revenu | R23: =IF(G13=Données!L51,'Décla N-1'!H35,H35+K35) -> 0 | S23: =G15 -> 0 | T23: Situation (marié, ...) | W23: Plafond quotient
D24: Revenus des associés et gérants (article 62 CGI) | R24: =IFERROR(R23/S23,0) -> 0 | S24: =R23/IF(T24=Données!$L$51,1,2) -> 0 | T24: =G13 -> 0 | W24: =IF(OR(G16="Non",G16=""),(S23-(IF(T24="Célibataire/veuf/divorcé",1,2)))*(Données!F18*2),IF(T24="Célibataire/veuf/divorcé",IF(S23<=2,(S23-1)*Données!G18,Données!G18+((S23-2)*Données!F18*2)),(S23-(IF(T24="Célibataire/veuf/divorcé",1,2)))*(Données!F18*2))) -> -7164
D25: Frais réels | H25: Non | K25: Non | R25: 1er T | S25: 2ème T | T25: Tranches | U25: TMI | V25: Retraitement | W25: IR (nb parts) | X25: IR (plaf quotient)
D26: Abattement | H26: =IF(H25="Oui",I25,IF((H23+H24)<Données!$G$24,(H23+H24),IF(((H23+H24)*10%)<Données!$G$24,Données!$G$24,IF(((H23+H24)*10%)<Données!$F$24,(H23+H24)*10%,Données!$F$24)))) -> 0 | K26: =IF(K25="Oui",L25,IF((K23+K24)<Données!$G$24,(K23+K24),IF(((K23+K24)*10%)<Données!$G$24,Données!$G$24,IF(((K23+K24)*10%)<Données!$F$24,(K23+K24)*10%,Données!$F$24)))) -> 0 | R26: =IF(R24<=T26,R24,0) -> 0 | S26: =IF(S24<=T26,S24,0) -> 0 | T26: =Données!E13 -> 11498 | U26: =Données!F13 -> 0
D27: Pensions, retraites et rentes | R27: =IF(AND(R24<=T27,R24>T26),R24,0) -> 0 | S27: =IF(AND(S24<=T27,S24>T26),S24,0) -> 0 | T27: =Données!E14 -> 29315 | U27: =Données!F14 -> 0.11 | V27: =T26*U27 -> 1264.78 | W27: =IF(R27>0,(R23*U27)-(V27*S23),0) -> 0 | X27: =IF(S27>0,(R23*U27)-(V27*(IF(T24="Célibataire/veuf/divorcé",1,2)))-W24,0) -> 0
D28: Abattement spécial | H28: =IF((H27+K27)<Données!$G$25,(H27+K27),IF(((H27+K27)*10%)<Données!$G$25,Données!$G$25,IF(((H27+K27)*10%)<Données!$F$25,(H27+K27)*10%,Données!$F$25))) -> 0 | R28: =IF(AND(R24<=T28,R24>T27),R24,0) -> 0 | S28: =IF(AND(S24<=T28,S24>T27),S24,0) -> 0 | T28: =Données!E15 -> 83823 | U28: =Données!F15 -> 0.3 | V28: =(T26-S26)*U28+(T27-T26)*(U28-U27) -> 6834.63 | W28: =IF(R28>0,(R23*U28)-(V28*S23),0) -> 0 | X28: =IF(S28>0,(R23*U28)-(V28*(IF(T24="Célibataire/veuf/divorcé",1,2)))-W24,0) -> 0
D29: BIC-BNC-BA imposables | R29: =IF(AND(R24<=T29,R24>T28),R24,0) -> 0 | S29: =IF(AND(S24<=T29,S24>T28),S24,0) -> 0 | T29: =Données!E16 -> 180294 | U29: =Données!F16 -> 0.41 | V29: =(T26-S26)*U29+(T27-T26)*(U29-U27)+(T28-T27)*(U29-U28) -> 16055.16 | W29: =IF(R29>0,(R23*U29)-(V29*S23),0) -> 0 | X29: =IF(S29>0,(R23*U29)-(V29*(IF(T24="Célibataire/veuf/divorcé",1,2)))-W24,0) -> 0
D30: Revenus fonciers nets | R30: =IF(R24>T29,R24,0) -> 0 | S30: =IF(S24>T29,S24,0) -> 0 | T30: =Données!E17 -> 0 | U30: =Données!F17 -> 0.45 | V30: =(T26-S26)*U30+(T27-T26)*(U30-U27)+(T28-T27)*(U30-U28)+(T29-T28)*(U30-U29) -> 23266.92 | W30: =IF(R30>0,(R23*U30)-(V30*S23),0) -> 0 | X30: =IF(S30>0,(R23*U30)-(V30*(IF(T24="Célibataire/veuf/divorcé",1,2)))-W24,0) -> 0
D31: Autres revenus imposables | W31: =SUM(W27:W30) -> 0 | X31: =SUM(X27:X30) -> 0
D32: Déductions d'impôt (autres que PER) | Q32: IR avant décote | S32: =IF(W31<=X31,X31,W31) -> 0 | V32: TMI | W32: =IF(W31<=X31,IF(X27>0,U27,IF(X28>0,U28,IF(X29>0,U29,IF(X30>0,U30,0)))),IF(W27>0,U27,IF(W28>0,U28,IF(W29>0,U29,IF(W30>0,U30,0))))) -> 0
D33: Crédits, réductions d'impôt | Q33: Décote | S33: =IF(S32=0,0,IF(AND(S32<Données!$F$19,T24="Célibataire/veuf/divorcé"),Données!$F$20-(S32*Données!$F$21),IF(AND(S32<Données!$G$19,T24="Marié/pacsé"),Données!$G$20-(S32*Données!$F$21),0))) -> 0 | U33: Reste T1 | V33: Reste T2 | W33: Seuil plaf Q | X33: Seuil décote
Q34: IR | S34: =IF(S32-S33<0,0,S32-S33) -> 0 | U34: =IF(W27>0,($R$24-$T$26)*$S$23,IF(W28>0,($R$24-T27)*$S$23,IF(W29>0,($R$24-T28)*$S$23,($R$24-T29)*$S$23))) -> 0 | V34: =IF(X27>0,R23-(T26*IF($T$24=Données!$L$50,2,1)),IF(X28>0,R23-(T27*IF($T$24=Données!$L$50,2,1)),IF(X29>0,R23-(T28*IF($T$24=Données!$L$50,2,1)),R23-(T29*IF($T$24=Données!$L$50,2,1))))) -> -180294 | W34: =(-(V27*S23)/(U28-U27))+((W24+(IF($T$24="Célibataire/veuf/divorcé",1,2)*V28))/(U28-U27)) -> 34238.211 | X34: =(IF(T24=Données!$L$51,Données!$F$20,Données!$G$20)/(1+Données!$F$21)+(V27*S23))/U27 -> 9200.4381
D35: Revenus imposables | H35: =H23+H24-H26+H27-H28+H29+H30+H31-H32-'Synthèse décla'!I34 -> 0 | K35: =K23+K24-K26+K27+K29+K30+K31-K32-'Synthèse décla'!J34 -> 0 | Q35: IR après réductions | S35: =S34-H33-K33 -> 0 | U35: Reste dans la TMI => | W35: =IF(W32=U27,R23-X34,IF(W31>X31,U34,IF(W32=U28,R23-W34,V34))) -> -180294

Sheet Synthèse décla
Q4: Barème | R4: =Données!F4 -> 2026
B5: =TODAY() -> 46023 | Q5: sur revenus | R5: =R4-1 -> 2025
Q9: PASS | R9: =J13 -> 2025
Q10: =VLOOKUP(J13,Données!$D$50:$E$56,2) -> 47100
D13: Déclatation des revenus | G13: =R4 -> 2026 | H13: Sur les revenus | J13: =G13-1 -> 2025 | N13: Choix pour le report 154 bis (Madelin) : | O13: Interprétation recalcul sur Revenu Brut Global
M14: Mad 15 décla1 | N14: =IF(O14-Q10<=0,0,IF(O14<='Synthèse décla'!$Q$10,0,IF(O14<=8*'Synthèse décla'!$Q$10,(O14-'Synthèse décla'!$Q$10)*0.15,((8*'Synthèse décla'!$Q$10)-'Synthèse décla'!$Q$10)*0.15))) -> 0 | O14: =IF('Décla N-1'!H24-'Décla N-1'!H26+'Décla N-1'!H29<0,0,'Décla N-1'!H24-'Décla N-1'!H26+'Décla N-1'!H29) -> 0 | P14: =IF('Décla N-1'!K24-'Décla N-1'!K26+'Décla N-1'!K29<0,0,'Décla N-1'!K24-'Décla N-1'!K26+'Décla N-1'!K29) -> 0 | Q14: =IF(P14-Q10<=0,0,IF(P14<='Synthèse décla'!$Q$10,0,IF(P14<=8*'Synthèse décla'!$Q$10,(P14-'Synthèse décla'!$Q$10)*0.15,((8*'Synthèse décla'!$Q$10)-'Synthèse décla'!$Q$10)*0.15))) -> 0 | R14: Mad 15 Décla2
D15: Epargne retraite (2042) | H15: Déclarant 1 | J15: Déclarant 2 | M15: Déclarant 1 : Potentiel 154 BIS (Madelin retraite) | P15: Déclarant 2 : Potentiel 154 BIS (Madelin retraite)
D16: Cotisations versées sur les nouveaux plans d'épargne retraite (PER) déduction du revenu global…….............6NS | H16: ='Décla N-1'!U13 -> 0 | I16: 6NT | J16: ='Décla N-1'!X13 -> 0 | M16: Revenu imposable TNS | N16: ='Décla N-1'!H24+'Décla N-1'!H29 -> 0 | P16: Revenu imposable TNS | Q16: ='Décla N-1'!K24+'Décla N-1'!K29 -> 0
D17: Cotisations PERP, Préfon, Corem, CGOS et assimilées…................................................................................6RS | H17: ='Décla N-1'!U14 -> 0 | I17: 6RT | J17: ='Décla N-1'!X14 -> 0 | M17: Assiette Madelin | N17: =N16+N18+N19+'Décla N-1'!U19 -> 0 | P17: Assiette Madelin | Q17: =Q16+Q18+Q19+'Décla N-1'!X19 -> 0
D18: Plafond de déduction…..............................................................................................................................6PS | I18: 6PT | M18: Versement Madelin retraite | N18: ='Décla N-1'!U18 -> 0 | P18: Versement Madelin Retraite | Q18: ='Décla N-1'!$X$18 -> 0
D19: Vous souhaitez bénéficier du plafond de votre conjoint…..................................................................................... | H19: ............................ | I19: .…..................6QR | J19: Non | L19: =IF('Décla N-1'!G13=Données!L51,"",IF(J19="Oui","",IF(OR(J17+J16>J34,H16+H17>I34),"?",""))) | M19: Versement PER 154bis | N19: ='Décla N-1'!U17 -> 0 | P19: Versement PER 154bis | Q19: ='Décla N-1'!$X$17 -> 0
D20: Vous êtes nouvellement domicilié en France en…................................................................................................. | H20: ............................ | I20: ….................6QW | M20: Potentiel Madelin total | N20: =N21+N22 -> 0 | P20: Potentiel Madelin total | Q20: =Q21+Q22 -> 0
D21: Cotisations sur les nouveaux plans d'épargne retraite déduites des BIC, BNC, BA, Rem art62….....................6OS | H21: =IF(O13="Interprétation recalcul sur Revenu Brut Global",MAX(0,IF(IF(N18<N14,0,N18-N14)>0,N19,(N19+N18)-N14)),MAX(0,IF(IF(N18<N21,0,N18-N21)>0,N19,(N19+N18)-N21))) -> 0 | I21: 6OT | J21: =IF(O13="Interprétation recalcul sur Revenu Brut Global",MAX(0,IF(IF(Q18<Q14,0,Q18-Q14)>0,Q19,(Q19+Q18)-Q14)),MAX(0,IF(IF(Q18<Q21,0,Q18-Q21)>0,Q19,(Q19+Q18)-Q21))) -> 0 | M21: Enveloppe 15% | N21: =IF(N17<='Synthèse décla'!$Q$10,0,IF(N17<=8*'Synthèse décla'!$Q$10,(N17-'Synthèse décla'!$Q$10)*0.15,((8*'Synthèse décla'!$Q$10)-'Synthèse décla'!$Q$10)*0.15)) -> 0 | O21: =IF((N18+N19)>=N21,0,N21-(N18+N19)) -> 0 | P21: Enveloppe 15% | Q21: =IF(Q17<='Synthèse décla'!$Q$10,0,IF(Q17<=8*'Synthèse décla'!$Q$10,(Q17-'Synthèse décla'!$Q$10)*0.15,((8*'Synthèse décla'!$Q$10)-'Synthèse décla'!$Q$10)*0.15)) -> 0 | R21: =IF((Q18+Q19)>=Q21,0,Q21-(Q18+Q19)) -> 0
D22: Autres cotisations déduites des BIC, BNC, BA, rémun. art. 62 ou salaires …..................................................6QS | H22: =IF(O13="Interprétation recalcul sur Revenu Brut Global",'Décla N-1'!U16+'Décla N-1'!U15+IF(N18<N14,0,N18-N14),'Décla N-1'!U16+'Décla N-1'!U15+IF(N18<N21,0,N18-N21)) -> 0 | I22: 6QT | J22: =IF(O13="Interprétation recalcul sur Revenu Brut Global",'Décla N-1'!X16+'Décla N-1'!X15+IF(Q18<Q14,0,Q18-Q14),'Décla N-1'!X16+'Décla N-1'!X15+IF(Q18<Q21,0,Q18-Q21)) -> 0 | M22: Enveloppe 10% | N22: =IF(N16=0,0,IF(N17<='Synthèse décla'!$Q$10,0.1*'Synthèse décla'!$Q$10,IF(N17<=8*'Synthèse décla'!$Q$10,N17*0.1,8*'Synthèse décla'!$Q$10*0.1))) -> 0 | O22: =IF(N16=0,0,IF(('Décla N-1'!U15+'Décla N-1'!U16)>=N22,IF((N18+N19)>N21,N22-(MAX(0,IF(IF(N18<N21,0,N18-N21)>0,N19,(N19+N18)-N21)))-('Décla N-1'!U16+'Décla N-1'!U15+IF(N18<N21,0,N18-N21)),0),N22-(MAX(0,IF(IF(N18<N21,0,N18-N21)>0,N19,(N19+N18)-N21)))-('Décla N-1'!U16+'Décla N-1'!U15+IF(N18<N21,0,N18-N21)))) -> 0 | P22: Enveloppe 10% | Q22: =IF(Q16=0,0,IF(Q17<='Synthèse décla'!$Q$10,0.1*'Synthèse décla'!$Q$10,IF(Q17<=8*'Synthèse décla'!$Q$10,Q17*0.1,8*'Synthèse décla'!$Q$10*0.1))) -> 0 | R22: =IF(Q16=0,0,IF(('Décla N-1'!X15+'Décla N-1'!X16)>=Q22,IF((Q18+Q19)>Q21,Q22-(MAX(0,IF(IF(Q18<Q21,0,Q18-Q21)>0,Q19,(Q19+Q18)-Q21)))-('Décla N-1'!X16+'Décla N-1'!X15+IF(Q18<Q21,0,Q18-Q21)),0),Q22-(MAX(0,IF(IF(Q18<Q21,0,Q18-Q21)>0,Q19,(Q19+Q18)-Q21)))-('Décla N-1'!X16+'Décla N-1'!X15+IF(Q18<Q21,0,Q18-Q21)))) -> 0
M23: Potentiel Madelin restant : | O23: =O21+O22 -> 0 | P23: Potentiel Madelin restant | R23: =R21+R22 -> 0
M24: =IF(O23<0,"Réintégration fiscale à opérer","") | P24: =IF('Décla N-1'!G13=Données!L51,"",IF(R23<0,"Réintégration fiscale à opérer",""))
D25: Simulation de l'AVIS IR
D27: AVIS D'IMPÔT | F27: =G13 -> 2026
D28: PLAFOND EPARGNE RETRAITE | H28: total cotiz | I28: =H16+H17 -> 0 | J28: =J16+J17 -> 0 | N28: report en avant déclarant 1 | Q28: Données pour calcul 2023
D29: Le plafond disponible pour la déduction des cotisations verées en …........ | G29: =F27 -> 2026 | H29: total plaf | I29: =I32+J32 -> 0 | M29: ='Avis IR N-2'!L23 -> 0 | N29: =IF(N32=0,0,IF(N32<=M29,0,N32-M29)) -> 0 | O29: =M29-N32 -> 0 | Q29: Déclarant 1 | R29: Déclarant 2
D30: pour la déclaration des revenus à souscrire en …...................................... | G30: =G29+1 -> 2027 | I30: =I32-H16-H17 -> 0 | J30: =J32-J16-J17 -> 0 | M30: ='Avis IR N-2'!L24 -> 0 | N30: =IF(N29=0,0,IF(N29<=M30,0,N29-M30)) -> 0 | O30: =M30-N29 -> 0 | Q30: ='Décla N-1'!H23+'Décla N-1'!H24-'Décla N-1'!H26+'Décla N-1'!H29 -> 0 | R30: ='Décla N-1'!K23+'Décla N-1'!K24-'Décla N-1'!K26+'Décla N-1'!K29 -> 0
I31: Déclar. 1 | J31: Déclar. 2 | M31: ='Avis IR N-2'!L25 -> 0 | N31: =IF(N30=0,0,IF(N30<=M31,0,N30-M31)) -> 0 | O31: =M31-N30 -> 0
D32: Plafond total de …...................................................................................... | G32: =G29-2 -> 2024 | I32: ='Avis IR N-2'!L28 -> 0 | J32: =IF('Décla N-1'!G13=Données!L51,0,'Avis IR N-2'!M28) -> 0 | M32: ='Avis IR N-2'!L26 -> 0 | N32: =IF(I34<=M32,IF(OR(J19="Non",J19=""),0,IF(J34>J32,I34+J34-J32-M32,I34-M32)),IF(J19="Non",I34-M32,IF(J34>J32,I34+J34-J32-M32,I34-M32))) -> 0 | O32: =M32-IF(OR(J19="Non",J19=""),I34,J33-J32+I34) -> 0 | Q32: PASS
D33: Plafond après mutualisation…................................................................... | I33: =IF(AND(I28>=I32,J19="Oui",J30>=0),I32+IF(J30>=(I28-I32),I28-I32,J30),IF(J19="Oui",IF(J28>J32,IF(I30+J30>0,I29-J28,I28),I32),"")) | J33: =IF(AND(J28>=J32,J19="Oui",I30>=0),J32+IF(I30>=(J28-J32),J28-J32,I30),IF(J19="Oui",IF(I28>I32,IF(J30+I30>0,I29-I28,J28),J32),"")) | Q33: =Données!D50 -> 2019 | R33: =Données!E50 -> 40524
D34: Cotisations prises en compte pour …......................................................... | G34: =G32+1 -> 2025 | I34: =IF((H16+H17)>I32,IF(J19="Oui",I33,I32),(H16+H17)) -> 0 | J34: =IF('Décla N-1'!G13=Données!L51,0,IF((J16+J17)>J32,IF(J19="Oui",J33,J32),(J16+J17))) -> 0 | N34: report en avant déclarant 2 | Q34: =Données!D51 -> 2020 | R34: =Données!E51 -> 41136
D35: Plafond non utilisé pour les revenus de ….................................................. | G35: =G32-1 -> 2023 | I35: =IF(O30>0,O30,0) -> 0 | J35: =IF('Décla N-1'!G13=Données!L51,0,IF(O36>0,O36,0)) -> 0 | M35: ='Avis IR N-2'!M23 -> 0 | N35: =IF(N38=0,0,IF(N38<=M35,0,N38-M35)) -> 0 | O35: =M35-N38 -> 0 | Q35: =Données!D52 -> 2021 | R35: =Données!E52 -> 41136
D36: Plafond non utilisé pour les revenus de ….................................................. | G36: =G35+1 -> 2024 | H36: ="+" -> + | I36: =IF(O31>0,O31,0) -> 0 | J36: =IF('Décla N-1'!G13=Données!L51,0,IF(O37>0,O37,0)) -> 0 | M36: ='Avis IR N-2'!M24 -> 0 | N36: =IF(N35=0,0,IF(N35<=M36,0,N35-M36)) -> 0 | O36: =M36-N35 -> 0 | Q36: =Données!D53 -> 2022 | R36: =Données!E53 -> 41136
D37: Plafond non utilisé pour les revenus de ….................................................. | G37: =G36+1 -> 2025 | H37: ="+" -> + | I37: =IF(O32>0,O32,0) -> 0 | J37: =IF('Décla N-1'!G13=Données!L51,0,IF(O38>0,O38,0)) -> 0 | M37: ='Avis IR N-2'!M25 -> 0 | N37: =IF(N36=0,0,IF(N36<=M37,0,N36-M37)) -> 0 | O37: =M37-N36 -> 0 | Q37: =Données!D54 -> 2023 | R37: =Données!E54 -> 43992
D38: Plafond calculé sur les revenus de ….......................................................... | G38: =G37 -> 2025 | H38: ="+" -> + | I38: =IF(Q30<=(INDEX($Q$33:$R$39,MATCH($G$38,$Q$33:$Q$39,0),2)),INDEX($Q$33:$R$39,MATCH($G$38,$Q$33:$Q$39,0),2)*10%,IF(Q30>(8*(INDEX($Q$33:$R$39,MATCH($G$38,$Q$33:$Q$39,0),2))),(8*(INDEX($Q$33:$R$39,MATCH($G$38,$Q$33:$Q$39,0),2)))*10%,Q30*10%))-IF(IF(Q30<=(INDEX($Q$33:$R$39,MATCH($G$38,$Q$33:$Q$39,0),2)),INDEX($Q$33:$R$39,MATCH($G$38,$Q$33:$Q$39,0),2)*10%,IF(Q30>(8*(INDEX($Q$33:$R$39,MATCH($G$38,$Q$33:$Q$39,0),2))),(8*(INDEX($Q$33:$R$39,MATCH($G$38,$Q$33:$Q$39,0),2)))*10%,Q30*10%))>(H21+H22),(H21+H22),IF(Q30<=(INDEX($Q$33:$R$39,MATCH($G$38,$Q$33:$Q$39,0),2)),INDEX($Q$33:$R$39,MATCH($G$38,$Q$33:$Q$39,0),2)*10%,IF(Q30>(8*(INDEX($Q$33:$R$39,MATCH($G$38,$Q$33:$Q$39,0),2))),(8*(INDEX($Q$33:$R$39,MATCH($G$38,$Q$33:$Q$39,0),2)))*10%,Q30*10%))) -> 4710 | J38: =IF('Décla N-1'!G13=Données!L51,0,IF(R30<=(INDEX($Q$33:$R$39,MATCH($G$38,$Q$33:$Q$39,0),2)),INDEX($Q$33:$R$39,MATCH($G$38,$Q$33:$Q$39,0),2)*10%,IF(R30>(8*(INDEX($Q$33:$R$39,MATCH($G$38,$Q$33:$Q$39,0),2))),(8*(INDEX($Q$33:$R$39,MATCH($G$38,$Q$33:$Q$39,0),2)))*10%,R30*10%))-IF(IF(R30<=(INDEX($Q$33:$R$39,MATCH($G$38,$Q$33:$Q$39,0),2)),INDEX($Q$33:$R$39,MATCH($G$38,$Q$33:$Q$39,0),2)*10%,IF(R30>(8*(INDEX($Q$33:$R$39,MATCH($G$38,$Q$33:$Q$39,0),2))),(8*(INDEX($Q$33:$R$39,MATCH($G$38,$Q$33:$Q$39,0),2)))*10%,R30*10%))>(J21+J22),(J21+J22),IF(R30<=(INDEX($Q$33:$R$39,MATCH($G$38,$Q$33:$Q$39,0),2)),INDEX($Q$33:$R$39,MATCH($G$38,$Q$33:$Q$39,0),2)*10%,IF(R30>(8*(INDEX($Q$33:$R$39,MATCH($G$38,$Q$33:$Q$39,0),2))),(8*(INDEX($Q$33:$R$39,MATCH($G$38,$Q$33:$Q$39,0),2)))*10%,R30*10%)))) -> 4710 | M38: ='Avis IR N-2'!M26 -> 0 | N38: =IF(J34<=M38,IF(OR(J19="Non",J19=""),0,IF(I34>I32,I34+J34-I32-M38,J34-M38)),IF(P15="Non",J34-M38,IF(I34>I32,I34+J34-I32-M38,J34-M38))) -> 0 | O38: =M38-IF(OR(J19="Non",J19=""),J34,I33-I32+J34) -> 0 | Q38: =Données!D55 -> 2024 | R38: =Données!E55 -> 46368
D39: Plafond pour les cotisations versées en ….................................................. | G39: =G37+1 -> 2026 | H39: ="=" -> = | I39: =SUM(I35:I38) -> 4710 | J39: =IF('Décla N-1'!G13=Données!L51,0,SUM(J35:J38)) -> 4710 | Q39: =Données!D56 -> 2025 | R39: =Données!E56 -> 47100

Sheet Estimation N
Z4: Barème | AA4: =Données!F4 -> 2026
B5: =TODAY() -> 46023 | X5: sur revenus | AA5: =AA4-1 -> 2025
Q10: Versements épargne retraite
U11: Déclarant 1 | X11: Déclarant 2
D13: Situation familiale | J13: Estimation IR | Q13: Cotisations PER 163 Quatervicies CGI
J14: TMI… | K14: =U26 -> 0 | L14: =U27 -> 0.11 | M14: =U28 -> 0.3 | N14: =U29 -> 0.41 | O14: =U30 -> 0.45 | Q14: Cotisations PERP et assimilées
D15: Nombre de parts | G15: =IF(G13="",0,IF(G13="Célibataire/veuf/divorcé",1,2)+(I15*0.25)) -> 0 | J15: IR… | K15: =S35 -> 0 | Q15: Cotisations art83 (employeur et salarié sur fiche de paie)
D16: Isolé | J16: Montant des revenus dans cette TMI : | N16: =IF(W35<0,0,W35) -> 0 | Q16: Abondement brut versé par l'employeur PERCO
J17: ="+CEHR" -> +CEHR | N17: =IF('Estimation N'!G13=Données!L51,IF('Estimation N'!R23<Données!N13,0,IF('Estimation N'!R23<Données!N14,('Estimation N'!R23-Données!N13)*Données!P14,(('Estimation N'!R23-Données!N14)*Données!P15)+((Données!N14-Données!N13)*Données!P14))),IF('Estimation N'!R23<Données!N14,0,IF('Estimation N'!R23<Données!N15,('Estimation N'!R23-Données!N14)*Données!Q15,(('Estimation N'!R23-Données!N15)*Données!Q16+((Données!N15-Données!N14)*Données!Q15))))) -> 0 | Q17: Cotisations PER 154 bis CGI
Q18: Cotisations Madelin retraite
Q19: Cotisations prévoyance et santé Madelin (part Madelin)
U20: =IF(U19>0,"",IF(H24+H29>0,"Attention, la cotisation prévoyance entre dans le calcul du potentiel","")) | X20: =IF(G13=Données!L51,"",IF(X19>0,"",IF(K24+K29>0,"Attention, la cotisation prévoyance entre dans le calcul du potentiel","")))
H21: Déclarant 1 | K21: Déclarant 2
T22: Estimation IR | U22: =AA4 -> 2026
D23: Traitement et salaires | Q23: Revenu | R23: =IF(G13=Données!L51,'Estimation N'!H35,H35+K35) -> 0 | S23: =G15 -> 0 | T23: Situation (marié, ...) | W23: Plafond quotient
D24: Revenus des associés et gérants (article 62 CGI) | R24: =IFERROR(R23/S23,0) -> 0 | S24: =R23/IF(T24=Données!$L$51,1,2) -> 0 | T24: =G13 -> 0 | W24: =IF(OR(G16="Non",G16=""),(S23-(IF(T24="Célibataire/veuf/divorcé",1,2)))*(Données!F18*2),IF(T24="Célibataire/veuf/divorcé",IF(S23<=2,(S23-1)*Données!G18,Données!G18+((S23-2)*Données!F18*2)),(S23-(IF(T24="Célibataire/veuf/divorcé",1,2)))*(Données!F18*2))) -> -7164
D25: Frais réels | H25: Non | K25: Non | R25: 1er T | S25: 2ème T | T25: Tranches | U25: TMI | V25: Retraitement | W25: IR (nb parts) | X25: IR (plaf quotient)
D26: Abattement | H26: =IF(H25="Oui",I25,IF((H23+H24)<Données!$G$24,(H23+H24),IF(((H23+H24)*10%)<Données!$G$24,Données!$G$24,IF(((H23+H24)*10%)<Données!$F$24,(H23+H24)*10%,Données!$F$24)))) -> 0 | K26: =IF(K25="Oui",L25,IF((K23+K24)<Données!$G$24,(K23+K24),IF(((K23+K24)*10%)<Données!$G$24,Données!$G$24,IF(((K23+K24)*10%)<Données!$F$24,(K23+K24)*10%,Données!$F$24)))) -> 0 | R26: =IF(R24<=T26,R24,0) -> 0 | S26: =IF(S24<=T26,S24,0) -> 0 | T26: =Données!E13 -> 11498 | U26: =Données!F13 -> 0
D27: Pensions, retraites et rentes | R27: =IF(AND(R24<=T27,R24>T26),R24,0) -> 0 | S27: =IF(AND(S24<=T27,S24>T26),S24,0) -> 0 | T27: =Données!E14 -> 29315 | U27: =Données!F14 -> 0.11 | V27: =T26*U27 -> 1264.78 | W27: =IF(R27>0,(R23*U27)-(V27*S23),0) -> 0 | X27: =IF(S27>0,(R23*U27)-(V27*(IF(T24="Célibataire/veuf/divorcé",1,2)))-W24,0) -> 0
D28: Abattement spécial | H28: =IF((H27+K27)<Données!$G$25,(H27+K27),IF(((H27+K27)*10%)<Données!$G$25,Données!$G$25,IF(((H27+K27)*10%)<Données!$F$25,(H27+K27)*10%,Données!$F$25))) -> 0 | R28: =IF(AND(R24<=T28,R24>T27),R24,0) -> 0 | S28: =IF(AND(S24<=T28,S24>T27),S24,0) -> 0 | T28: =Données!E15 -> 83823 | U28: =Données!F15 -> 0.3 | V28: =(T26-S26)*U28+(T27-T26)*(U28-U27) -> 6834.63 | W28: =IF(R28>0,(R23*U28)-(V28*S23),0) -> 0 | X28: =IF(S28>0,(R23*U28)-(V28*(IF(T24="Célibataire/veuf/divorcé",1,2)))-W24,0) -> 0
D29: BIC-BNC-BA imposables | R29: =IF(AND(R24<=T29,R24>T28),R24,0) -> 0 | S29: =IF(AND(S24<=T29,S24>T28),S24,0) -> 0 | T29: =Données!E16 -> 180294 | U29: =Données!F16 -> 0.41 | V29: =(T26-S26)*U29+(T27-T26)*(U29-U27)+(T28-T27)*(U29-U28) -> 16055.16 | W29: =IF(R29>0,(R23*U29)-(V29*S23),0) -> 0 | X29: =IF(S29>0,(R23*U29)-(V29*(IF(T24="Célibataire/veuf/divorcé",1,2)))-W24,0) -> 0
D30: Revenus fonciers nets | R30: =IF(R24>T29,R24,0) -> 0 | S30: =IF(S24>T29,S24,0) -> 0 | T30: =Données!E17 -> 0 | U30: =Données!F17 -> 0.45 | V30: =(T26-S26)*U30+(T27-T26)*(U30-U27)+(T28-T27)*(U30-U28)+(T29-T28)*(U30-U29) -> 23266.92 | W30: =IF(R30>0,(R23*U30)-(V30*S23),0) -> 0 | X30: =IF(S30>0,(R23*U30)-(V30*(IF(T24="Célibataire/veuf/divorcé",1,2)))-W24,0) -> 0
D31: Autres revenus imposables | W31: =SUM(W27:W30) -> 0 | X31: =SUM(X27:X30) -> 0
D32: Déductions d'impôt (autres que PER) | Q32: IR avant décote | S32: =IF(W31<=X31,X31,W31) -> 0 | V32: TMI | W32: =IF(W31<=X31,IF(X27>0,U27,IF(X28>0,U28,IF(X29>0,U29,IF(X30>0,U30,0)))),IF(W27>0,U27,IF(W28>0,U28,IF(W29>0,U29,IF(W30>0,U30,0))))) -> 0
D33: Crédits, réductions d'impôt | Q33: Décote | S33: =IF(S32=0,0,IF(AND(S32<Données!$F$19,T24="Célibataire/veuf/divorcé"),Données!$F$20-(S32*Données!$F$21),IF(AND(S32<Données!$G$19,T24="Marié/pacsé"),Données!$G$20-(S32*Données!$F$21),0))) -> 0 | U33: Reste T1 | V33: Reste T2 | W33: Seuil plaf Q | X33: Seuil décote
Q34: IR | S34: =IF(S32-S33<0,0,S32-S33) -> 0 | U34: =IF(W27>0,($R$24-$T$26)*$S$23,IF(W28>0,($R$24-T27)*$S$23,IF(W29>0,($R$24-T28)*$S$23,($R$24-T29)*$S$23))) -> 0 | V34: =IF(X27>0,R23-(T26*IF($T$24=Données!$L$50,2,1)),IF(X28>0,R23-(T27*IF($T$24=Données!$L$50,2,1)),IF(X29>0,R23-(T28*IF($T$24=Données!$L$50,2,1)),R23-(T29*IF($T$24=Données!$L$50,2,1))))) -> -180294 | W34: =(-(V27*S23)/(U28-U27))+((W24+(IF($T$24="Célibataire/veuf/divorcé",1,2)*V28))/(U28-U27)) -> 34238.211 | X34: =(IF(T24=Données!$L$51,Données!$F$20,Données!$G$20)/(1+Données!$F$21)+(V27*S23))/U27 -> 9200.4381
D35: Revenus imposables | H35: =H23+H24-H26+H27-H28+H29+H30+H31-H32-Synthèse!I34 -> 0 | K35: =K23+K24-K26+K27+K29+K30+K31-K32-Synthèse!J34 -> 0 | Q35: IR après réductions | S35: =S34-H33-K33 -> 0 | U35: Reste dans la TMI => | W35: =IF(W32=U27,R23-X34,IF(W31>X31,U34,IF(W32=U28,R23-W34,V34))) -> -180294

Sheet Synthèse
Q4: Barème | R4: =Données!F4 -> 2026
B5: =TODAY() -> 46023 | Q5: sur revenus | R5: =R4-1 -> 2025
Q9: PASS | R9: =J13 -> 2026
Q10: =VLOOKUP(J13,Données!$D$50:$E$56,2) -> 47100
D13: Déclatation des revenus | G13: =R4+1 -> 2027 | H13: Sur les revenus | J13: =G13-1 -> 2026 | N13: Choix pour le report 154 bis (Madelin) : | O13: Interprétation recalcul sur Revenu Brut Global
M14: Mad 15 décla1 | N14: =IF(O14-Q10<=0,0,IF(O14<=Synthèse!$Q$10,0,IF(O14<=8*Synthèse!$Q$10,(O14-Synthèse!$Q$10)*0.15,((8*Synthèse!$Q$10)-Synthèse!$Q$10)*0.15))) -> 0 | O14: =IF('Estimation N'!H24-'Estimation N'!H26+'Estimation N'!H29<0,0,'Estimation N'!H24-'Estimation N'!H26+'Estimation N'!H29) -> 0 | P14: =IF('Estimation N'!K24-'Estimation N'!K26+'Estimation N'!K29<0,0,'Estimation N'!K24-'Estimation N'!K26+'Estimation N'!K29) -> 0 | Q14: =IF(P14-Q10<=0,0,IF(P14<=Synthèse!$Q$10,0,IF(P14<=8*Synthèse!$Q$10,(P14-Synthèse!$Q$10)*0.15,((8*Synthèse!$Q$10)-Synthèse!$Q$10)*0.15))) -> 0 | R14: Mad 15 Décla2
D15: Epargne retraite (2042) | H15: Déclarant 1 | J15: Déclarant 2 | M15: Déclarant 1 : Potentiel 154 BIS (Madelin retraite) | P15: Déclarant 2 : Potentiel 154 BIS (Madelin retraite)
D16: Cotisations versées sur les nouveaux plans d'épargne retraite (PER) déduction du revenu global…….............6NS | H16: ='Estimation N'!U13 -> 0 | I16: 6NT | J16: ='Estimation N'!X13 -> 0 | M16: Revenu imposable TNS | N16: ='Estimation N'!H24+'Estimation N'!H29 -> 0 | P16: Revenu imposable TNS | Q16: ='Estimation N'!K24+'Estimation N'!K29 -> 0
D17: Cotisations PERP, Préfon, Corem, CGOS et assimilées…................................................................................6RS | H17: ='Estimation N'!U14 -> 0 | I17: 6RT | J17: ='Estimation N'!X14 -> 0 | M17: Assiette Madelin | N17: =N16+N18+N19+'Estimation N'!U19 -> 0 | P17: Assiette Madelin | Q17: =Q16+Q18+Q19+'Estimation N'!X19 -> 0
D18: Plafond de déduction…..............................................................................................................................6PS | I18: 6PT | M18: Versement Madelin retraite | N18: ='Estimation N'!U18 -> 0 | P18: Versement Madelin Retraite | Q18: ='Estimation N'!$X$18 -> 0
D19: Vous souhaitez bénéficier du plafond de votre conjoint…..................................................................................... | H19: ............................ | I19: .…..................6QR | J19: Non | L19: =IF('Estimation N'!G13=Données!L51,"",IF(J19="Oui","",IF(OR(J17+J16>J34,H16+H17>I34),"?",""))) | M19: Versement PER 154bis | N19: ='Estimation N'!U17 -> 0 | P19: Versement PER 154bis | Q19: ='Estimation N'!$X$17 -> 0
D20: Vous êtes nouvellement domicilié en France en…................................................................................................. | H20: ............................ | I20: ….................6QW | M20: Potentiel Madelin total | N20: =N21+N22 -> 0 | P20: Potentiel Madelin total | Q20: =Q21+Q22 -> 0
D21: Cotisations sur les nouveaux plans d'épargne retraite déduites des BIC, BNC, BA, Rem art62….....................6OS | H21: =IF(O13="Interprétation recalcul sur Revenu Brut Global",MAX(0,IF(IF(N18<N14,0,N18-N14)>0,N19,(N19+N18)-N14)),MAX(0,IF(IF(N18<N21,0,N18-N21)>0,N19,(N19+N18)-N21))) -> 0 | I21: 6OT | J21: =IF(O13="Interprétation recalcul sur Revenu Brut Global",MAX(0,IF(IF(Q18<Q14,0,Q18-Q14)>0,Q19,(Q19+Q18)-Q14)),MAX(0,IF(IF(Q18<Q21,0,Q18-Q21)>0,Q19,(Q19+Q18)-Q21))) -> 0 | M21: Enveloppe 15% | N21: =IF(N17<=Synthèse!$Q$10,0,IF(N17<=8*Synthèse!$Q$10,(N17-Synthèse!$Q$10)*0.15,((8*Synthèse!$Q$10)-Synthèse!$Q$10)*0.15)) -> 0 | O21: =IF((N18+N19)>=N21,0,N21-(N18+N19)) -> 0 | P21: Enveloppe 15% | Q21: =IF(Q17<=Synthèse!$Q$10,0,IF(Q17<=8*Synthèse!$Q$10,(Q17-Synthèse!$Q$10)*0.15,((8*Synthèse!$Q$10)-Synthèse!$Q$10)*0.15)) -> 0 | R21: =IF((Q18+Q19)>=Q21,0,Q21-(Q18+Q19)) -> 0
D22: Autres cotisations déduites des BIC, BNC, BA, rémun. art. 62 ou salaires …..................................................6QS | H22: =IF(O13="Interprétation recalcul sur Revenu Brut Global",'Estimation N'!U16+'Estimation N'!U15+IF(N18<N14,0,N18-N14),'Estimation N'!U16+'Estimation N'!U15+IF(N18<N21,0,N18-N21)) -> 0 | I22: 6QT | J22: =IF(O13="Interprétation recalcul sur Revenu Brut Global",'Estimation N'!X16+'Estimation N'!X15+IF(Q18<Q14,0,Q18-Q14),'Estimation N'!X16+'Estimation N'!X15+IF(Q18<Q21,0,Q18-Q21)) -> 0 | M22: Enveloppe 10% | N22: =IF(N16=0,0,IF(N17<=Synthèse!$Q$10,0.1*Synthèse!$Q$10,IF(N17<=8*Synthèse!$Q$10,N17*0.1,8*Synthèse!$Q$10*0.1))) -> 0 | O22: =IF(N16=0,0,IF(('Estimation N'!U15+'Estimation N'!U16)>=N22,IF((N18+N19)>N21,N22-(MAX(0,IF(IF(N18<N21,0,N18-N21)>0,N19,(N19+N18)-N21)))-('Estimation N'!U16+'Estimation N'!U15+IF(N18<N21,0,N18-N21)),0),N22-(MAX(0,IF(IF(N18<N21,0,N18-N21)>0,N19,(N19+N18)-N21)))-('Estimation N'!U16+'Estimation N'!U15+IF(N18<N21,0,N18-N21)))) -> 0 | P22: Enveloppe 10% | Q22: =IF(Q16=0,0,IF(Q17<=Synthèse!$Q$10,0.1*Synthèse!$Q$10,IF(Q17<=8*Synthèse!$Q$10,Q17*0.1,8*Synthèse!$Q$10*0.1))) -> 0 | R22: =IF(Q16=0,0,IF(('Estimation N'!X15+'Estimation N'!X16)>=Q22,IF((Q18+Q19)>Q21,Q22-(MAX(0,IF(IF(Q18<Q21,0,Q18-Q21)>0,Q19,(Q19+Q18)-Q21)))-('Estimation N'!X16+'Estimation N'!X15+IF(Q18<Q21,0,Q18-Q21)),0),Q22-(MAX(0,IF(IF(Q18<Q21,0,Q18-Q21)>0,Q19,(Q19+Q18)-Q21)))-('Estimation N'!X16+'Estimation N'!X15+IF(Q18<Q21,0,Q18-Q21)))) -> 0
M23: Potentiel Madelin restant : | O23: =O21+O22 -> 0 | P23: Potentiel Madelin restant | R23: =R21+R22 -> 0
M24: =IF(O23<0,"Réintégration fiscale à opérer","") | P24: =IF(R23<0,"Réintégration fiscale à opérer","")
D25: Simulation de l'AVIS IR
D27: AVIS D'IMPÔT | F27: =G13 -> 2027
D28: PLAFOND EPARGNE RETRAITE | H28: total cotiz | I28: =H16+H17 -> 0 | J28: =J16+J17 -> 0 | N28: report en avant déclarant 1 | Q28: Données pour calcul 2023
D29: Le plafond disponible pour la déduction des cotisations verées en …........ | G29: =F27 -> 2027 | H29: total plaf | I29: =I32+J32 -> 9420 | M29: =IF(AND('Pot ER Mode'!$G$13="Réaliser un versement N (et vérifier si le potentiel le permet)",'Pot ER Mode'!$H$15=Synthèse!$J$13),'Avis IR N-2'!L23,'Synthèse décla'!I35) -> 0 | N29: =IF(N32=0,0,IF(N32<=M29,0,N32-M29)) -> 0 | O29: =M29-N32 -> 0 | Q29: Déclarant 1 | R29: Déclarant 2
D30: pour la déclaration des revenus à souscrire en …...................................... | G30: =G29+1 -> 2028 | I30: =I32-H16-H17 -> 4710 | J30: =J32-J16-J17 -> 4710 | M30: =IF(AND('Pot ER Mode'!$G$13="Réaliser un versement N (et vérifier si le potentiel le permet)",'Pot ER Mode'!$H$15=Synthèse!$J$13),'Avis IR N-2'!L24,'Synthèse décla'!I36) -> 0 | N30: =IF(N29=0,0,IF(N29<=M30,0,N29-M30)) -> 0 | O30: =M30-N29 -> 0 | Q30: ='Estimation N'!H23+'Estimation N'!H24-'Estimation N'!H26+'Estimation N'!H29 -> 0 | R30: ='Estimation N'!K23+'Estimation N'!K24-'Estimation N'!K26+'Estimation N'!K29 -> 0
I31: Déclar. 1 | J31: Déclar. 2 | M31: =IF(AND('Pot ER Mode'!$G$13="Réaliser un versement N (et vérifier si le potentiel le permet)",'Pot ER Mode'!$H$15=Synthèse!$J$13),'Avis IR N-2'!L25,'Synthèse décla'!I37) -> 0 | N31: =IF(N30=0,0,IF(N30<=M31,0,N30-M31)) -> 0 | O31: =M31-N30 -> 0
D32: Plafond total de …...................................................................................... | G32: =G29-2 -> 2025 | I32: =IF(AND('Pot ER Mode'!G13="Réaliser un versement N (et vérifier si le potentiel le permet)",'Pot ER Mode'!H15=Synthèse!J13),'Avis IR N-2'!L28,'Synthèse décla'!I39) -> 4710 | J32: =IF('Estimation N'!G13=Données!L51,0,IF(AND('Pot ER Mode'!G13="Réaliser un versement N (et vérifier si le potentiel le permet)",'Pot ER Mode'!H15=Synthèse!J13),'Avis IR N-2'!M28,'Synthèse décla'!J39)) -> 4710 | M32: =IF(AND('Pot ER Mode'!$G$13="Réaliser un versement N (et vérifier si le potentiel le permet)",'Pot ER Mode'!$H$15=Synthèse!$J$13),'Avis IR N-2'!L26,'Synthèse décla'!I38) -> 4710 | N32: =IF(I34<=M32,IF(OR(J19="Non",J19=""),0,IF(J34>J32,I34+J34-J32-M32,I34-M32)),IF(J19="Non",I34-M32,IF(J34>J32,I34+J34-J32-M32,I34-M32))) -> 0 | O32: =M32-IF(OR(J19="Non",J19=""),I34,J33-J32+I34) -> 4710 | Q32: PASS
D33: Plafond après mutualisation…................................................................... | I33: =IF(AND(I28>=I32,J19="Oui",J30>=0),I32+IF(J30>=(I28-I32),I28-I32,J30),IF(J19="Oui",IF(J28>J32,IF(I30+J30>0,I29-J28,I28),I32),"")) | J33: =IF(AND(J28>=J32,J19="Oui",I30>=0),J32+IF(I30>=(J28-J32),J28-J32,I30),IF(J19="Oui",IF(I28>I32,IF(J30+I30>0,I29-I28,J28),J32),"")) | Q33: =Données!D50 -> 2019 | R33: =Données!E50 -> 40524
D34: Cotisations prises en compte pour …......................................................... | G34: =G32+1 -> 2026 | I34: =IF((H16+H17)>I32,IF(J19="Oui",I33,I32),(H16+H17)) -> 0 | J34: =IF('Estimation N'!G13=Données!L51,0,IF((J16+J17)>J32,IF(J19="Oui",J33,J32),(J16+J17))) -> 0 | N34: report en avant déclarant 2 | Q34: =Données!D51 -> 2020 | R34: =Données!E51 -> 41136
D35: Plafond non utilisé pour les revenus de ….................................................. | G35: =G32-1 -> 2024 | I35: =IF(O30>0,O30,0) -> 0 | J35: =IF('Estimation N'!G13=Données!L51,0,IF(O36>0,O36,0)) -> 0 | M35: =IF(AND('Pot ER Mode'!$G$13="Réaliser un versement N (et vérifier si le potentiel le permet)",'Pot ER Mode'!$H$15=Synthèse!$J$13),'Avis IR N-2'!M23,'Synthèse décla'!J35) -> 0 | N35: =IF(N38=0,0,IF(N38<=M35,0,N38-M35)) -> 0 | O35: =M35-N38 -> 0 | Q35: =Données!D52 -> 2021 | R35: =Données!E52 -> 41136
D36: Plafond non utilisé pour les revenus de ….................................................. | G36: =G35+1 -> 2025 | H36: ="+" -> + | I36: =IF(O31>0,O31,0) -> 0 | J36: =IF('Estimation N'!G13=Données!L51,0,IF(O37>0,O37,0)) -> 0 | M36: =IF(AND('Pot ER Mode'!$G$13="Réaliser un versement N (et vérifier si le potentiel le permet)",'Pot ER Mode'!$H$15=Synthèse!$J$13),'Avis IR N-2'!M24,'Synthèse décla'!J36) -> 0 | N36: =IF(N35=0,0,IF(N35<=M36,0,N35-M36)) -> 0 | O36: =M36-N35 -> 0 | Q36: =Données!D53 -> 2022 | R36: =Données!E53 -> 41136
D37: Plafond non utilisé pour les revenus de ….................................................. | G37: =G36+1 -> 2026 | H37: ="+" -> + | I37: =IF(O32>0,O32,0) -> 4710 | J37: =IF('Estimation N'!G13=Données!L51,0,IF(O38>0,O38,0)) -> 4710 | M37: =IF(AND('Pot ER Mode'!$G$13="Réaliser un versement N (et vérifier si le potentiel le permet)",'Pot ER Mode'!$H$15=Synthèse!$J$13),'Avis IR N-2'!M25,'Synthèse décla'!J37) -> 0 | N37: =IF(N36=0,0,IF(N36<=M37,0,N36-M37)) -> 0 | O37: =M37-N36 -> 0 | Q37: =Données!D54 -> 2023 | R37: =Données!E54 -> 43992
D38: Plafond calculé sur les revenus de ….......................................................... | G38: =G37 -> 2026 | H38: ="+" -> + | I38: =IF(Q30<=(INDEX($Q$33:$R$39,MATCH($G$38,$Q$33:$Q$39,0),2)),INDEX($Q$33:$R$39,MATCH($G$38,$Q$33:$Q$39,0),2)*10%,IF(Q30>(8*(INDEX($Q$33:$R$39,MATCH($G$38,$Q$33:$Q$39,0),2))),(8*(INDEX($Q$33:$R$39,MATCH($G$38,$Q$33:$Q$39,0),2)))*10%,Q30*10%))-IF(IF(Q30<=(INDEX($Q$33:$R$39,MATCH($G$38,$Q$33:$Q$39,0),2)),INDEX($Q$33:$R$39,MATCH($G$38,$Q$33:$Q$39,0),2)*10%,IF(Q30>(8*(INDEX($Q$33:$R$39,MATCH($G$38,$Q$33:$Q$39,0),2))),(8*(INDEX($Q$33:$R$39,MATCH($G$38,$Q$33:$Q$39,0),2)))*10%,Q30*10%))>(H21+H22),(H21+H22),IF(Q30<=(INDEX($Q$33:$R$39,MATCH($G$38,$Q$33:$Q$39,0),2)),INDEX($Q$33:$R$39,MATCH($G$38,$Q$33:$Q$39,0),2)*10%,IF(Q30>(8*(INDEX($Q$33:$R$39,MATCH($G$38,$Q$33:$Q$39,0),2))),(8*(INDEX($Q$33:$R$39,MATCH($G$38,$Q$33:$Q$39,0),2)))*10%,Q30*10%))) -> #N/A | J38: =IF('Estimation N'!G13=Données!L51,0,IF(R30<=(INDEX($Q$33:$R$39,MATCH($G$38,$Q$33:$Q$39,0),2)),INDEX($Q$33:$R$39,MATCH($G$38,$Q$33:$Q$39,0),2)*10%,IF(R30>(8*(INDEX($Q$33:$R$39,MATCH($G$38,$Q$33:$Q$39,0),2))),(8*(INDEX($Q$33:$R$39,MATCH($G$38,$Q$33:$Q$39,0),2)))*10%,R30*10%))-IF(IF(R30<=(INDEX($Q$33:$R$39,MATCH($G$38,$Q$33:$Q$39,0),2)),INDEX($Q$33:$R$39,MATCH($G$38,$Q$33:$Q$39,0),2)*10%,IF(R30>(8*(INDEX($Q$33:$R$39,MATCH($G$38,$Q$33:$Q$39,0),2))),(8*(INDEX($Q$33:$R$39,MATCH($G$38,$Q$33:$Q$39,0),2)))*10%,R30*10%))>(J21+J22),(J21+J22),IF(R30<=(INDEX($Q$33:$R$39,MATCH($G$38,$Q$33:$Q$39,0),2)),INDEX($Q$33:$R$39,MATCH($G$38,$Q$33:$Q$39,0),2)*10%,IF(R30>(8*(INDEX($Q$33:$R$39,MATCH($G$38,$Q$33:$Q$39,0),2))),(8*(INDEX($Q$33:$R$39,MATCH($G$38,$Q$33:$Q$39,0),2)))*10%,R30*10%)))) -> #N/A | M38: =IF(AND('Pot ER Mode'!$G$13="Réaliser un versement N (et vérifier si le potentiel le permet)",'Pot ER Mode'!$H$15=Synthèse!$J$13),'Avis IR N-2'!M26,'Synthèse décla'!J38) -> 4710 | N38: =IF(J34<=M38,IF(OR(J19="Non",J19=""),0,IF(I34>I32,I34+J34-I32-M38,J34-M38)),IF(P15="Non",J34-M38,IF(I34>I32,I34+J34-I32-M38,J34-M38))) -> 0 | O38: =M38-IF(OR(J19="Non",J19=""),J34,I33-I32+J34) -> 4710 | Q38: =Données!D55 -> 2024 | R38: =Données!E55 -> 46368
D39: Plafond pour les cotisations versées en ….................................................. | G39: =G37+1 -> 2027 | H39: ="=" -> = | I39: =SUM(I35:I38) -> #N/A | J39: =IF('Estimation N'!G13=Données!L51,0,SUM(J35:J38)) -> #N/A | Q39: =Données!D56 -> 2025 | R39: =Données!E56 -> 47100

Sheet Impr (2)
A1: Edition étude Page 1 | W1: Titre des diapos
V2: Slide 2 | W2: OBJECTIFS & CONTEXTE | Z2: =IF('Pot ER Mode'!G13="Réaliser un versement N (et vérifier si le potentiel le permet)","Vous souhaitez estimer vos potentiels épargne retraite.","Vous souhaitez être accompagné dans la déclaration fiscale de vos versements épargne retraite") -> Vous souhaitez être accompagné dans la déclaration fiscale de vos versements épargne retraite
V3: Slide 3 | W3: ESTIMATION DE LA SITUATION FISCALE
V4: Slide 4 | W4: =IF('Pot ER Mode'!G13="Réaliser un versement N (et vérifier si le potentiel le permet)","ESTIMATION DE VOS PLAFONDS DE VERSEMENTS EPARGNE RETRAITE A TITRE PERSONNEL POUR "&Synthèse!R9,"VOS PLAFONDS DE VERSEMENTS EPARGNE RETRAITE A TITRE PERSONNEL POUR "&'Synthèse décla'!R5) -> VOS PLAFONDS DE VERSEMENTS EPARGNE RETRAITE A TITRE PERSONNEL POUR 2025
V5: Slide 6 | W5: ESTIMATION DES MONTANTS A REPROTER ET SIMULATION DE VOTRE FUTUR AVIS D'IMPOT
V6: Slide 5 | W6: =IF('Pot ER Mode'!G13="Réaliser un versement N (et vérifier si le potentiel le permet)","ESTIMATION DE VOS PLAFONDS DE VERSEMENTS EPARGNE RETRAITE MADELIN POUR "&Synthèse!R9,"VOS PLAFONDS DE VERSEMENTS EPARGNE RETRAITE MADELIN POUR "&'Synthèse décla'!R5) -> VOS PLAFONDS DE VERSEMENTS EPARGNE RETRAITE MADELIN POUR 2025
V9: Slide 4 image
V19: Slide 5 image
C31: =IF('Pot ER Mode'!G13="Réaliser un versement N (et vérifier si le potentiel le permet)","Etude d'estimation du potentiel épargne retraite","Etude d'accompagnement à la déclaration des versements épargne retraite") -> Etude d'accompagnement à la déclaration des versements épargne retraite
E32: Madame et Monsieur …..............
G34: =TODAY() -> 46023
C36: Prénom CGP NOM CGP
C37: Conseiller en gestion de patrimoine
A41: Edition étude Page 2
B78: =(TODAY()) -> 46023 | E78: Document non contractuel établi en fonction des dispositions fiscales ou sociales en vigueur à la date des présentes | O78: 2
A81: Edition étude Page 3
B101: Estimation de vos revenus | F101: Estimation du revenu imposable | J101: Nombre de parts fiscales | N101: TMI
B103: Déclarant 1 | C103: =IF('Pot ER Mode'!G13="Réaliser un versement N (et vérifier si le potentiel le permet)",'Estimation N'!H23+'Estimation N'!H24+'Estimation N'!H27+'Estimation N'!H29,'Décla N-1'!H23+'Décla N-1'!H24+'Décla N-1'!H27+'Décla N-1'!H29) -> 0 | F103: =IF('Pot ER Mode'!G13="Réaliser un versement N (et vérifier si le potentiel le permet)",'Estimation N'!R23,'Décla N-1'!R23) -> 0 | J103: =IF('Pot ER Mode'!G13="Réaliser un versement N (et vérifier si le potentiel le permet)",'Estimation N'!S23,'Décla N-1'!S23) -> 0 | N103: =IF('Pot ER Mode'!G13="Réaliser un versement N (et vérifier si le potentiel le permet)",'Estimation N'!W32,'Décla N-1'!W32) -> 0
B104: Déclarant 2 | C104: =IF('Pot ER Mode'!G13="Réaliser un versement N (et vérifier si le potentiel le permet)",'Estimation N'!K23+'Estimation N'!K24+'Estimation N'!K27+'Estimation N'!K29,'Décla N-1'!K23+'Décla N-1'!K24+'Décla N-1'!K27+'Décla N-1'!K29) -> 0
B110: 0 | C110: 0.11 | E110: 0.3 | H110: 0.41 | L110: 0.45
C113: =IF(N103=11%,IF('Pot ER Mode'!G13="Réaliser un versement N (et vérifier si le potentiel le permet)",'Estimation N'!N16,'Décla N-1'!N16),"") | E113: =IF(N103=30%,IF('Pot ER Mode'!G13="Réaliser un versement N (et vérifier si le potentiel le permet)",'Estimation N'!N16,'Décla N-1'!N16),"") | H113: =IF(N103=41%,IF('Pot ER Mode'!G13="Réaliser un versement N (et vérifier si le potentiel le permet)",'Estimation N'!N16,'Décla N-1'!N16),"") | L113: =IF(N103=45%,IF('Pot ER Mode'!G13="Réaliser un versement N (et vérifier si le potentiel le permet)",'Estimation N'!N16,'Décla N-1'!N16),"")
D116: Estimation du montant de votre impôt sur le revenu : | I116: =IF('Pot ER Mode'!G13="Réaliser un versement N (et vérifier si le potentiel le permet)",'Estimation N'!K15,'Décla N-1'!K15) -> 0
G117: + | H117: CEHR | I117: =IF('Pot ER Mode'!G13="Réaliser un versement N (et vérifier si le potentiel le permet)",'Estimation N'!N17,'Décla N-1'!N17) -> 0
A121: Edition étude Page 4 - potentiel | N121: =IF('Pot ER Mode'!G13="Déclarer dans la 2042 les montants versés en N-1",IF('Décla N-1'!G13=Données!L50,"Décla2",""),IF('Estimation N'!G13=Données!L50,"Décla2","")) | O121: =IF('Pot ER Mode'!G13="Réaliser un versement N (et vérifier si le potentiel le permet)",IF(('Estimation N'!H24+'Estimation N'!H29)>0,"TNS1",""),IF(('Décla N-1'!H24+'Décla N-1'!H29)>0,"TNS1","")) | P121: =IF('Pot ER Mode'!G13="Réaliser un versement N (et vérifier si le potentiel le permet)",IF('Estimation N'!G13=Données!L51,"",IF('Estimation N'!K24+'Estimation N'!K29>0,"TNS2","")),IF('Décla N-1'!G13=Données!L51,"",IF('Décla N-1'!K24+'Décla N-1'!K29>0,"TNS2","")))
B125: Pour un travailleur salarié ou non salarié, le PER permet de déduire fiscalement les cotisations versées chaque année dans la limite des plafonds légaux propres à chaque catégorie de travailleur (salarié ou non salarié). Plus la tranche marginale d’imposition de l’épargnant est élevée, et plus cette déduction fiscale est efficace.
B128: Le potentiel "dit personnel" ou 163 quatervicies du CGI : | G128: Les versements sont déductibles dans la limite de 10 % des revenus d’activité professionnelle de l’année de référence N-1 (avec un minimum égal 10 % du PASS N-1).Le plafond s’apprécie après déduction des cotisations obligatoires au titre de l’année N-1 versées par l’employeur dans un contrat retraite Article 83, PERE, PERCO ou PERECO. Viennent également en déduction les cotisations dites « Madelin » N-1 pour leur part excédant 15% du bénéfice imposable N-1 dépassant 1 PASS N-1.
C142: Votre disponible 163Q | G142: Vos versements 163Q | K142: Votre disponible restant 163Q
C145: Déclarant 1 | D145: =IF('Pot ER Mode'!G13="Réaliser un versement N (et vérifier si le potentiel le permet)",Synthèse!I32,'Synthèse décla'!I32) -> 0 | G145: Déclarant 1 | H145: =IF('Pot ER Mode'!G13="Réaliser un versement N (et vérifier si le potentiel le permet)",Synthèse!H16+Synthèse!H17,'Synthèse décla'!H16+'Synthèse décla'!H17) -> 0 | K145: Déclarant 1 | L145: =D145-H145 -> 0 | N145: =IF(L145<0,"Dépassement","")
C146: Déclarant 2 | D146: =IF('Pot ER Mode'!G13="Réaliser un versement N (et vérifier si le potentiel le permet)",Synthèse!J32,'Synthèse décla'!J32) -> 0 | G146: Déclarant 2 | H146: =IF('Pot ER Mode'!G13="Réaliser un versement N (et vérifier si le potentiel le permet)",Synthèse!J16+Synthèse!J17,'Synthèse décla'!J16+'Synthèse décla'!J17) -> 0 | K146: Déclarant 2 | L146: =D146-H146 -> 0 | N146: =IF(L146<0,"Dépassement","")
C150: =IF('Pot ER Mode'!G13="Réaliser un versement N (et vérifier si le potentiel le permet)",IF(Synthèse!J19="Oui","Vous nous indiquez vouloir opter pour la mutualisation des plafonds entre conjoint",""),IF('Synthèse décla'!J19="Oui","Vous nous indiquez vouloir opter pour la mutualisation des plafonds entre conjoint",""))
A161: Edition étude Page suivante - Synthèse délration IR | P161: =IF('Pot ER Mode'!$G$13="Déclarer dans la 2042 les montants versés en N-1",'Décla N-1'!G13,'Estimation N'!G13) -> 0
B169: Déclatation des revenus | E169: =IF('Pot ER Mode'!$G$13="Déclarer dans la 2042 les montants versés en N-1",'Synthèse décla'!G13,Synthèse!G13) -> 2027 | H169: Sur les revenus | J169: =E169-1 -> 2026
B171: Epargne retraite (2042) | H171: Déclarant 1 | J171: Déclarant 2
B172: Cotisations versées sur les nouveaux plans d'épargne retraite (PER) déduction du revenu global.......................6NS | H172: =IF('Pot ER Mode'!$G$13="Déclarer dans la 2042 les montants versés en N-1",'Synthèse décla'!H16,Synthèse!H16) -> 0 | I172: 6NT | J172: =IF('Pot ER Mode'!$G$13="Déclarer dans la 2042 les montants versés en N-1",'Synthèse décla'!J16,Synthèse!J16) -> 0
B173: Cotisations PERP, Préfon, Corem, CGOS et assimilées….........................................................................................6RS | H173: =IF('Pot ER Mode'!$G$13="Déclarer dans la 2042 les montants versés en N-1",'Synthèse décla'!H17,Synthèse!H17) -> 0 | I173: 6RT | J173: =IF('Pot ER Mode'!$G$13="Déclarer dans la 2042 les montants versés en N-1",'Synthèse décla'!J17,Synthèse!J17) -> 0
B174: Plafond de déduction…...........................................................................................................................................6PS | I174: 6PT
B175: Vous souhaitez bénéficier du plafond de votre conjoint….................................................................................. | I175: 6QR | J175: =IF('Pot ER Mode'!$G$13="Déclarer dans la 2042 les montants versés en N-1",'Synthèse décla'!J19,Synthèse!J19) -> Non
B176: Vous êtes nouvellement domicilié en France en…............................................................................................... | I176: 6QW
B177: Cotisations sur les nouveaux plans d'épargne retraite déduites des BIC, BNC, BA, Rem art62…..........................6OS | H177: =IF('Pot ER Mode'!$G$13="Déclarer dans la 2042 les montants versés en N-1",'Synthèse décla'!H21,Synthèse!H21) -> 0 | I177: 6OT | J177: =IF('Pot ER Mode'!$G$13="Déclarer dans la 2042 les montants versés en N-1",'Synthèse décla'!J21,Synthèse!J21) -> 0
B178: Autres cotisations déduites des BIC, BNC, BA, rémun. art. 62 ou salaires ….........................................................6QS | H178: =IF('Pot ER Mode'!$G$13="Déclarer dans la 2042 les montants versés en N-1",'Synthèse décla'!H22,Synthèse!H22) -> 0 | I178: 6QT | J178: =IF('Pot ER Mode'!$G$13="Déclarer dans la 2042 les montants versés en N-1",'Synthèse décla'!J22,Synthèse!J22) -> 0
B182: Simulation de l'AVIS IR
B184: AVIS D'IMPÔT | D184: =E169 -> 2027
B185: PLAFOND EPARGNE RETRAITE | H185: total cotiz
B186: Le plafond disponible pour la déduction des cotisations verées en ……... | G186: =D184 -> 2027 | H186: total plaf
B187: pour la déclaration des revenus à souscrire en …..................................... | G187: =G186+1 -> 2028
I188: Déclar. 1 | J188: Déclar. 2
B189: Plafond total de …...................................................................................... | G189: =G186-2 -> 2025 | I189: =IF('Pot ER Mode'!$G$13="Déclarer dans la 2042 les montants versés en N-1",'Synthèse décla'!I32,Synthèse!I32) -> 4710 | J189: =IF('Pot ER Mode'!$G$13="Déclarer dans la 2042 les montants versés en N-1",'Synthèse décla'!J32,Synthèse!J32) -> 4710
B190: Plafond après mutualisation…................................................................... | I190: =IF('Pot ER Mode'!$G$13="Déclarer dans la 2042 les montants versés en N-1",'Synthèse décla'!I33,Synthèse!I33) | J190: =IF('Pot ER Mode'!$G$13="Déclarer dans la 2042 les montants versés en N-1",'Synthèse décla'!J33,Synthèse!J33)
B191: Cotisations prises en compte pour …......................................................... | G191: =G189+1 -> 2026 | I191: =IF('Pot ER Mode'!$G$13="Déclarer dans la 2042 les montants versés en N-1",'Synthèse décla'!I34,Synthèse!I34) -> 0 | J191: =IF('Pot ER Mode'!$G$13="Déclarer dans la 2042 les montants versés en N-1",'Synthèse décla'!J34,Synthèse!J34) -> 0
B192: Plafond non utilisé pour les revenus de …................................................. | G192: =G189-1 -> 2024 | I192: =IF('Pot ER Mode'!$G$13="Déclarer dans la 2042 les montants versés en N-1",'Synthèse décla'!I35,Synthèse!I35) -> 0 | J192: =IF('Pot ER Mode'!$G$13="Déclarer dans la 2042 les montants versés en N-1",'Synthèse décla'!J35,Synthèse!J35) -> 0
B193: Plafond non utilisé pour les revenus de …................................................. | G193: =G192+1 -> 2025 | H193: ="+" -> + | I193: =IF('Pot ER Mode'!$G$13="Déclarer dans la 2042 les montants versés en N-1",'Synthèse décla'!I36,Synthèse!I36) -> 0 | J193: =IF('Pot ER Mode'!$G$13="Déclarer dans la 2042 les montants versés en N-1",'Synthèse décla'!J36,Synthèse!J36) -> 0
B194: Plafond non utilisé pour les revenus de …................................................. | G194: =G193+1 -> 2026 | H194: ="+" -> + | I194: =IF('Pot ER Mode'!$G$13="Déclarer dans la 2042 les montants versés en N-1",'Synthèse décla'!I37,Synthèse!I37) -> 4710 | J194: =IF('Pot ER Mode'!$G$13="Déclarer dans la 2042 les montants versés en N-1",'Synthèse décla'!J37,Synthèse!J37) -> 4710
B195: Plafond calculé sur les revenus de …......................................................... | G195: =G194 -> 2026 | H195: ="+" -> + | I195: =IF('Pot ER Mode'!$G$13="Déclarer dans la 2042 les montants versés en N-1",'Synthèse décla'!I38,Synthèse!I38) -> #N/A | J195: =IF('Pot ER Mode'!$G$13="Déclarer dans la 2042 les montants versés en N-1",'Synthèse décla'!J38,Synthèse!J38) -> #N/A
B196: Plafond pour les cotisations versées en …................................................. | G196: =G194+1 -> 2027 | H196: ="=" -> = | I196: =SUM(I192:I195) -> #N/A | J196: =SUM(J192:J195) -> #N/A
A201: Edition étude Page suivante
A241: Option Page Madelin
B246: En tant que travailleur non salarié, vous disposez d'une enveloppe supplémentaire dite Madelin (art154bis du CGI).
B248: Le potentiel "dit Madelin" ou 154 bis du CGI : | G248: Les versements volontaires effectués par un adhérent affilié à un régime de Sécurité sociale de travailleurs non-salariés non-agricoles sont déductibles de son revenu professionnel (bénéfices industriels et commerciaux, bénéfices non commerciaux ou rémunération de gérance versées dans le cadre de l’article 62 du Code général des impôts) dans une limite égale au plus élevé des deux montants suivants : soit 10 % de la fraction de son bénéfice imposable (retenue à concurrence de huit PASS) auxquels s’ajoutent 15 % de la fraction du bénéfice comprise entre une fois et huit fois ce même plafond ; soit 10 % du PASS. Le plafond s’apprécie après déduction de l’éventuel abondement versé par l’Entreprise dans le compartiment 2 du PERECO.
B260: Votre disponible 154 bis | G260: Vos versements | L260: Votre disponible restant 154 bis
B262: Déclarant 1 | C262: Assiette : | D262: =IF('Pot ER Mode'!G13="Réaliser un versement N (et vérifier si le potentiel le permet)",Synthèse!N17,'Synthèse décla'!N17) -> 0 | G262: Déclarant 1 | H262: PERin 154 bis | J262: =IF('Pot ER Mode'!G13="Réaliser un versement N (et vérifier si le potentiel le permet)",'Estimation N'!U17,'Décla N-1'!U17) -> 0 | L262: Déclarant 1 | M262: Assiette : | N262: =D262 -> 0
C263: 0.15 | D263: =IF('Pot ER Mode'!G13="Réaliser un versement N (et vérifier si le potentiel le permet)",Synthèse!N21,'Synthèse décla'!N21) -> 0 | E263: =D263+D264 -> 0 | H263: Madelin | J263: =IF('Pot ER Mode'!G13="Réaliser un versement N (et vérifier si le potentiel le permet)",'Estimation N'!U18,'Décla N-1'!U18) -> 0 | M263: 0.15 | N263: =IF('Pot ER Mode'!G13="Réaliser un versement N (et vérifier si le potentiel le permet)",Synthèse!O21,'Synthèse décla'!O21) -> 0 | O263: =N263+N264 -> 0
C264: 0.1 | D264: =IF('Pot ER Mode'!G13="Réaliser un versement N (et vérifier si le potentiel le permet)",Synthèse!N22,'Synthèse décla'!N22) -> 0 | H264: PERCO-PEROB | J264: =IF('Pot ER Mode'!G13="Réaliser un versement N (et vérifier si le potentiel le permet)",'Estimation N'!U15+'Estimation N'!U16,'Décla N-1'!U15+'Décla N-1'!U16) -> 0 | M264: 0.1 | N264: =IF('Pot ER Mode'!G13="Réaliser un versement N (et vérifier si le potentiel le permet)",Synthèse!O22,'Synthèse décla'!O22) -> 0
B265: Déclarant 2 | C265: Assiette : | D265: =IF('Pot ER Mode'!G13="Réaliser un versement N (et vérifier si le potentiel le permet)",Synthèse!Q17,'Synthèse décla'!Q17) -> 0 | G265: Déclarant 2 | H265: PERin 154 bis | J265: =IF('Pot ER Mode'!G13="Réaliser un versement N (et vérifier si le potentiel le permet)",'Estimation N'!X17,'Décla N-1'!X17) -> 0 | L265: Déclarant 2 | M265: Assiette : | N265: =D265 -> 0
C266: 0.15 | D266: =IF('Pot ER Mode'!G13="Réaliser un versement N (et vérifier si le potentiel le permet)",Synthèse!Q21,'Synthèse décla'!Q21) -> 0 | E266: =D266+D267 -> 0 | H266: Madelin | J266: =IF('Pot ER Mode'!G13="Réaliser un versement N (et vérifier si le potentiel le permet)",'Estimation N'!X18,'Décla N-1'!X18) -> 0 | M266: 0.15 | N266: =IF('Pot ER Mode'!G13="Réaliser un versement N (et vérifier si le potentiel le permet)",Synthèse!R21,'Synthèse décla'!R21) -> 0 | O266: =N266+N267 -> 0
C267: 0.1 | D267: =IF('Pot ER Mode'!G13="Réaliser un versement N (et vérifier si le potentiel le permet)",Synthèse!Q22,'Synthèse décla'!Q22) -> 0 | H267: PERCO-PEROB | J267: =IF('Pot ER Mode'!G13="Réaliser un versement N (et vérifier si le potentiel le permet)",'Estimation N'!X15+'Estimation N'!X16,'Décla N-1'!X15+'Décla N-1'!X16) -> 0 | M267: 0.1 | N267: =IF('Pot ER Mode'!G13="Réaliser un versement N (et vérifier si le potentiel le permet)",Synthèse!R22,'Synthèse décla'!R22) -> 0
B271: Déclarant 1 | C271: Assiette de calcul du report (6OS- 6QS) | E271: =IF('Pot ER Mode'!G13="Réaliser un versement N (et vérifier si le potentiel le permet)",IF(Synthèse!O13="Interprétation recalcul sur Revenu Brut Global",Synthèse!O14,Synthèse!N17),IF('Synthèse décla'!O13="Interprétation recalcul sur Revenu Brut Global",'Synthèse décla'!O14,'Synthèse décla'!N17)) -> 0 | F271: Soit une enveloppe de 15% : | H271: =IF('Pot ER Mode'!G13="Réaliser un versement N (et vérifier si le potentiel le permet)",IF(Synthèse!O13="Interprétation recalcul sur Revenu Brut Global",Synthèse!N14,Synthèse!N21),IF('Synthèse décla'!O13="Interprétation recalcul sur Revenu Brut Global",'Synthèse décla'!N14,'Synthèse décla'!N21)) -> 0 | I271: Soit un report à opérer : | K271: =H177+H178 -> 0
B272: Déclarant 2 | C272: Assiette de calcul du report (6OT- 6QT) | E272: =IF('Pot ER Mode'!G13="Réaliser un versement N (et vérifier si le potentiel le permet)",IF(Synthèse!O13="Interprétation recalcul sur Revenu Brut Global",Synthèse!P14,Synthèse!Q17),IF('Synthèse décla'!O13="Interprétation recalcul sur Revenu Brut Global",'Synthèse décla'!P14,'Synthèse décla'!Q17)) -> 0 | F272: Soit une enveloppe de 15% : | H272: =IF('Pot ER Mode'!G13="Réaliser un versement N (et vérifier si le potentiel le permet)",IF(Synthèse!O13="Interprétation recalcul sur Revenu Brut Global",Synthèse!Q14,Synthèse!Q21),IF('Synthèse décla'!O13="Interprétation recalcul sur Revenu Brut Global",'Synthèse décla'!Q14,'Synthèse décla'!Q21)) -> 0 | I272: Soit un report à opérer : | K272: =J177+J178 -> 0
A281: Edition étude Page suivante+164:2161:201

Sheet CT à Transf
B5: =TODAY() -> 46023
L9: ="La base est composée de 396 contrats dont "&BASECG!A2&" analysés. Si votre contrat n'est pas automatiquement analysé, nous vous invitons à reprendre les CG puis à compléter les champs" -> La base est composée de 396 contrats dont 161 analysés. Si votre contrat n'est pas automatiquement analysé, nous vous invitons à reprendre les CG puis à compléter les champs
F12: Type de contrat | R12: =IF(AND(K12=Données!H50,R16="MADELIN"),"",IF(AND(OR(K12=Données!H51,K12=Données!H55),R16="ART83"),"",IF(AND(OR(K12=Données!H52,K12=Données!H53,K12=Données!H54),OR(R16="PERIN",S16=TRUE)),"",IF(AND(K12=Données!H56,R16="PERP"),"",IF(AND(K12=Données!H57,R16="PERCO"),"",IF(K16="","","FAUX"))))))
F14: Compagnie | AA14: 1 | AB14: 2 | AC14: 3 | AD14: 4 | AE14: 5 | AF14: 6 | AG14: 7 | AH14: 8 | AI14: 9 | AJ14: 10 | AK14: 11 | AL14: 12 | AM14: 13 | AN14: 14 | AO14: 15 | AP14: 16 | AQ14: 17 | AR14: 18 | AS14: 19 | AT14: 20 | AU14: 21 | AV14: 22 | AW14: 23 | AX14: 24 | AY14: 25 | AZ14: 26 | BA14: 27 | BB14: 28 | BC14: 29 | BD14: 30 | BE14: 31 | BF14: 32 | BG14: 33 | BH14: 34 | BI14: 35
F16: Nom du contrat | R16: =IF(LEFT(K16,5)="PERIN","PERIN",IF(LEFT(K16,7)="MADELIN","MADELIN",IF(LEFT(K16,4)="PERP","PERP",IF(LEFT(K16,5)="ART83","ART83",IF(LEFT(K16,5)="PERCO","PERCO",""))))) | S16: FALSE | Z16: {=IFERROR(OFFSET(BASECG!$B$4,0,MATCH(0,COUNTIF($Z$15:Z15,BASECG!$C$4:'BASECG'!$OG$4))),"")} -> ABEILLE | AA16: {=IFERROR(_xlfn._xlws.FILTER(BASECG!$C$5:'BASECG'!$OG$5,BASECG!$C$4:'BASECG'!$OG$4=Z16),"")} -> ART83- ABEILLE RETRAITE ENTREPRISE ARTICLE 83 | AB16: ART83- NORWICH STRATEGIE RETRAITE - Article 83 | AC16: PERP- ABEILLE RETRAITE PERP | AD16: MADELIN- ABEILLE RETRAITE MADELIN | AE16: MADELIN- ABEILLE RETRAITE PLURIELLE MADELIN | AF16: MADELIN- ATTITUDE STRATEGIE RETRAITE "LOI MADELIN" | AG16: MADELIN- ATTITUDE STRATEGIE RETRAITE AGRICOLE | AH16: MADELIN- NORWICH HORIZON LOI MADELIN | AI16: MADELIN- NORWICH STRATEGIE RETRAITE LOI MADELIN | AJ16: MADELIN- NORWICH UNION OPTION AVENIR LOI MADELIN | AK16: MADELIN- VICTOIRE INVESTISSEMENT RETRAITE 2 | AL16: PERIN- ABEILLE RETRAITE PLURIELLE | AM16: PERIN- ABEILLE RETRAITE PLURIELLE ENTREPRISE
K17: =IF(K14="PREFON","Particularité du régime PREFON, le C0 figurant sur le relevé correspond au PERP","") | Z17: {=IFERROR(OFFSET(BASECG!$B$4,0,MATCH(0,COUNTIF($Z$15:Z16,BASECG!$C$4:'BASECG'!$OG$4))),"")} -> AFER | AA17: {=IFERROR(_xlfn._xlws.FILTER(BASECG!$C$5:'BASECG'!$OG$5,BASECG!$C$4:'BASECG'!$OG$4=Z17),"")} -> ART83- CONTRAT COLLECTIF DE RETRAITE SUPPLÉMENTAIRE MULTISUPPORT AFER | AB17: ART83- RETRAITE SUPPLEMENTAIRE AFER | AC17: PERIN- AFER RETRAITE INDIVIDUELLE
Z18: {=IFERROR(OFFSET(BASECG!$B$4,0,MATCH(0,COUNTIF($Z$15:Z17,BASECG!$C$4:'BASECG'!$OG$4))),"")} -> AG2R_LA_MONDIALE | AA18: {=IFERROR(_xlfn._xlws.FILTER(BASECG!$C$5:'BASECG'!$OG$5,BASECG!$C$4:'BASECG'!$OG$4=Z18),"")} -> ART83- EQUATION 83 MULTISUPPORTS | AB18: ART83- MONDIALE PERSPECTIVES ENTREPRISE | AC18: ART83- MONDIALE RETRAITE PLUS | AD18: ART83- PER ENTREPRISES | AE18: ART83- RETRAITE SUPPLEMENTAIRE | AF18: ART83- RETRAITE SUPPLÉMENTAIRE II | AG18: ART83- RETRAITE SUPPLEMENTAIRE LIBRE | AH18: ART83- RETRAITE SUPPLEMENTAIRE LIBRE II | AI18: PERP- COMPLEMENT EPARGNE RETRAITE (EX -MONDIALE STRATEGIE RETRAITE) | AJ18: PERP- MONDIALE SOLUTIONS RETRAITE | AK18: MADELIN- MONDIALE PRIVILEGE ACTIONS | AL18: MADELIN- MONDIALE RETRAITE PROFESSIONNELS | AM18: MADELIN- RETRAITE AGRICOLE | AN18: MADELIN- RETRAITE PROFESSIONNELS | AO18: PERIN- AMBITION RETRAITE ENTREPRISE | AP18: PERIN- AMBITION RETRAITE INDIVIDUELLE | AQ18: PERIN- AMBITION RETRAITE PRO | AR18: PERIN- EXCELLIE RETRAITE | AS18: PERIN- UNIVERS RETRAITE ENTREPRISE LIBRE
Z19: {=IFERROR(OFFSET(BASECG!$B$4,0,MATCH(0,COUNTIF($Z$15:Z18,BASECG!$C$4:'BASECG'!$OG$4))),"")} -> AGEAS | AA19: {=IFERROR(_xlfn._xlws.FILTER(BASECG!$C$5:'BASECG'!$OG$5,BASECG!$C$4:'BASECG'!$OG$4=Z19),"")} -> PERIN- PER ZEN
D20: Phase Epargne | F20: Versement annuel | M20: Phase Liquidation | O20: Age limite liquidation | Z20: {=IFERROR(OFFSET(BASECG!$B$4,0,MATCH(0,COUNTIF($Z$15:Z19,BASECG!$C$4:'BASECG'!$OG$4))),"")} -> AGIPI | AA20: {=IFERROR(_xlfn._xlws.FILTER(BASECG!$C$5:'BASECG'!$OG$5,BASECG!$C$4:'BASECG'!$OG$4=Z20),"")} -> PERP- PAIR | AB20: MADELIN- FAR | AC20: PERIN- FAR PER
F21: Date d’effet | N21: Capital | O21: Sortie capital possible à la retraite (sauf exception) | Z21: {=IFERROR(OFFSET(BASECG!$B$4,0,MATCH(0,COUNTIF($Z$15:Z20,BASECG!$C$4:'BASECG'!$OG$4))),"")} -> ALLIANZ | AA21: {=IFERROR(_xlfn._xlws.FILTER(BASECG!$C$5:'BASECG'!$OG$5,BASECG!$C$4:'BASECG'!$OG$4=Z21),"")} -> ART83- AGF PLANEO 2 ENTREPRISE | AB21: ART83- AGF PLANEO 3 ENTREPRISE | AC21: ART83- AGF PLANEO 4 ENTREPRISE | AD21: ART83- AGF PLANEO EUROPEAN PENSION | AE21: ART83- AGF SOLEO RETRAITE | AF21: ART83- ALLIANZ PLANEO 5 ENTREPRISE | AG21: ART83- ALLIANZ RENTEO | AH21: ART83- ALLIANZ RETRAITE ENTREPRISE | AI21: PERP- PERP ALLIANZ PLEINE RETRAITE | AJ21: MADELIN- ALLIANZ ITINERAIRES RETRAITE MADELIN / AGRICOLE | AK21: MADELIN- ALLIANZ RETRAITE TNS / AGRI | AL21: MADELIN- OPTI'RETRAITE | AM21: MADELIN- PLATINIA RETRAITE MADELIN | AN21: MADELIN- TELLUS AVENIR TNS / AGRI | AO21: MADELIN- TELLUS TNS | AP21: PERIN- ALLIANZ PER ENTREPRISE | AQ21: PERIN- ALLIANZ PER HORIZON
F22: Commercialisation du contrat par la compagnie | O22: Fractionnement du capital | Z22: {=IFERROR(OFFSET(BASECG!$B$4,0,MATCH(0,COUNTIF($Z$15:Z21,BASECG!$C$4:'BASECG'!$OG$4))),"")} -> ALPTIS | AA22: {=IFERROR(_xlfn._xlws.FILTER(BASECG!$C$5:'BASECG'!$OG$5,BASECG!$C$4:'BASECG'!$OG$4=Z22),"")} -> MADELIN- IMPERATIF RETRAITE MADELIN
F23: Provision mathématique | L23: =IF(K23="","Obligatoire","") -> Obligatoire | O23: Rachat libre | Z23: {=IFERROR(OFFSET(BASECG!$B$4,0,MATCH(0,COUNTIF($Z$15:Z22,BASECG!$C$4:'BASECG'!$OG$4))),"")} -> APICIL | AA23: {=IFERROR(_xlfn._xlws.FILTER(BASECG!$C$5:'BASECG'!$OG$5,BASECG!$C$4:'BASECG'!$OG$4=Z23),"")} -> ART83- APICIL CAP' XL (ancien Apicil Retraite entreprise) | AB23: ART83- APICIL CAP'XL & CO (ancien APICIL PERENNITE ENTREPRISE) | AC23: PERP- APICIL PERSPECTIVES GENERATION | AD23: PERP- PERSPECTIVE GENERATION PLUS | AE23: MADELIN- APICIL PROFORMANCE | AF23: MADELIN- APICIL PROFORMANCE PLUS | AG23: PERIN- APICIL AVENIR PER-OB | AH23: PERIN- APICIL CONNECT PER | AI23: PERIN- INTENCIAL LIBERALYS RETRAITE | AJ23: PERIN- CONCORDANCES PERIN
F24: Dont intérets* | N24: Rente | O24: Table utilisée pour la conversion en rente | Z24: {=IFERROR(OFFSET(BASECG!$B$4,0,MATCH(0,COUNTIF($Z$15:Z23,BASECG!$C$4:'BASECG'!$OG$4))),"")} -> APRIL | AA24: {=IFERROR(_xlfn._xlws.FILTER(BASECG!$C$5:'BASECG'!$OG$5,BASECG!$C$4:'BASECG'!$OG$4=Z24),"")} -> ART83- AFFLUANCE RETRAITE ARTICLE 83 | AB24: ART83- APRIL RETRAITE ARTICLE 83 | AC24: PERP- APRIL PERP MULTISUPPORT | AD24: MADELIN- AFFLUANCE RETRAITE MADELIN | AE24: MADELIN- APRIL RETRAITE MADELIN | AF24: MADELIN- CARDIF RETRAITE PROFESSIONNELS (APRIL) | AG24: MADELIN- RETRAITE MADELIN APRIL
F25: Nombre de fonds accessibles | O25: Table garantie à l’adhésion | Q25: Table garantie à l’adhésion | Z25: {=IFERROR(OFFSET(BASECG!$B$4,0,MATCH(0,COUNTIF($Z$15:Z24,BASECG!$C$4:'BASECG'!$OG$4))),"")} -> AREAS | AA25: {=IFERROR(_xlfn._xlws.FILTER(BASECG!$C$5:'BASECG'!$OG$5,BASECG!$C$4:'BASECG'!$OG$4=Z25),"")} -> ART83- RETRAITE COLLECTIVE ENTREPRISE | AB25: ART83- PERI | AC25: PERP- PERP MULTISUPPORT | AD25: MADELIN- ARELIA MULTISUPPORT | AE25: MADELIN- ARELIA RETRAITE COMPLEMENTAIRE DES INDEPENDANTS | AF25: PERIN- PER INDIVIDUEL AREAS
F26: Répartition UC/€ | O26: Taux technique | Q26: Taux technique | Z26: {=IFERROR(OFFSET(BASECG!$B$4,0,MATCH(0,COUNTIF($Z$15:Z25,BASECG!$C$4:'BASECG'!$OG$4))),"")} -> AXA | AA26: {=IFERROR(_xlfn._xlws.FILTER(BASECG!$C$5:'BASECG'!$OG$5,BASECG!$C$4:'BASECG'!$OG$4=Z26),"")} -> ART83- 4G STRATEGIE RETRAITE | AB26: ART83- QUANTILE RETRAITE SECURITE | AC26: ART83- RETRAITE 4 G | AD26: ART83- RETRAITE ENTREPRISE A ADHÉSION OBLIGATOIRE | AE26: ART83- RETRAITE ENTREPRISE GESTION PROGRAMMEE | AF26: ART83- RETRAITE ENTREPRISE PÈRE | AG26: ART83- SOLERE 83 | AH26: PERP- PERP CONFORT | AI26: PERP- PERP REFERENCE | AJ26: MADELIN- AGRISSIAL | AK26: MADELIN- COLIADE RETRAITE INDEPENDANT | AL26: MADELIN- CORALIS INDEPENDANTS | AM26: MADELIN- CORETIS | AN26: MADELIN- GERANT MAJORITAIRE RETRAITE | AO26: MADELIN- NOVIAL AVENIR | AP26: MADELIN- ORIAL | AQ26: MADELIN- PLANISSIM | AR26: MADELIN- REGULARITE RETRAITE PRO / EURACTIEL DES PROFESSIONNELS | AS26: MADELIN- RETRAITE DES PROFESSIONNELS - AGRICOLES | AT26: MADELIN- RETRAITE DES PROFESSIONNELS - NON AGRICOLES | AU26: PERIN- AXA MA RETRAITE | AV26: PERIN- PER AMADEO | AW26: PERIN- PER CORALIS | AX26: PERCO- EPARGNE SALARIALE PEI / PERCO-I | AY26: PERCO- PEE - PERCO AXA
F27: Rendement fonds € | O27: Frais sur arrérages | Q27: Frais sur arrérages | Z27: {=IFERROR(OFFSET(BASECG!$B$4,0,MATCH(0,COUNTIF($Z$15:Z26,BASECG!$C$4:'BASECG'!$OG$4))),"")} -> BANQUE_POPULAIRE | AA27: {=IFERROR(_xlfn._xlws.FILTER(BASECG!$C$5:'BASECG'!$OG$5,BASECG!$C$4:'BASECG'!$OG$4=Z27),"")} -> ART83- CAPI RESSOURCES | AB27: ART83- RESSOURCES SÉLECTION VIE | AC27: ART83- RESSOURCES SELECTION VIE II | AD27: PERP- PER BP | AE27: PERP- PERP CM | AF27: PERP- PERP DUETTO RETRAITE | AG27: PERP- SOLUTION PERP | AH27: MADELIN- FRUCTI - AGRI | AI27: MADELIN- FRUCTI-PROFESSIONNEL | AJ27: MADELIN- PREPAR PRO | AK27: MADELIN- PREPAR'SERENITE - GARANTIE RETRAITE | AL27: PERIN- PERI BRED | AM27: PERIN- PLAN EPARGNE RETRAITE | AN27: PERCO-ES - PL | AO27: PERCO- FRUCTI DUO - FRUCTI EPARGNE PLUS | AP27: PERCO- FRUCTI OPTIMUM
F28: Frais sur versements | O28: Annuités garanties | Q28: Annuités garanties | Z28: {=IFERROR(OFFSET(BASECG!$B$4,0,MATCH(0,COUNTIF($Z$15:Z27,BASECG!$C$4:'BASECG'!$OG$4))),"")} -> BNP | AA28: {=IFERROR(_xlfn._xlws.FILTER(BASECG!$C$5:'BASECG'!$OG$5,BASECG!$C$4:'BASECG'!$OG$4=Z28),"")} -> ART83- PARTENAIRE PER ENTREPRISES | AB28: ART83- PREFERENCE PER ENTREPRISES | AC28: ART83- PRÉFÉRENCE RETRAITE | AD28: PERP- PLAN D'EPARGNE RETRAITE DES PARTICULIERS (PERP) | AE28: MADELIN- NATIO VIE MULTIHORIZONS PROFESSIONNEL | AF28: MADELIN- PLAN D'EPARGNE RETRAITE LOI MADELIN | AG28: PERIN- BNP PARIBAS MULTIPLACEMENTS PER | AH28: PERIN- PRÉFÉRENCE PER OBLIGATOIRE | AI28: PERIN- BNP PARIBAS MULTIPLACEMENTS PRIVILÈGE PER | AJ28: PERCO- AMPLISSIM EPARGNE SALARIALE | AK28: PERCO- PARTENAIRE EPARGNE SALARIALE | AL28: PERCO- PERCOI EFFIGIE
F29: Frais de gestion | O29: Réversion possible | Q29: Réversion possible | Z29: {=IFERROR(OFFSET(BASECG!$B$4,0,MATCH(0,COUNTIF($Z$15:Z28,BASECG!$C$4:'BASECG'!$OG$4))),"")} -> CAISSE_D_EPARGNE | AA29: {=IFERROR(_xlfn._xlws.FILTER(BASECG!$C$5:'BASECG'!$OG$5,BASECG!$C$4:'BASECG'!$OG$4=Z29),"")} -> PERP- ASSYLIO | AB29: PERP- PERP CAISSE D'EPARGNE | AC29: PERP- SOLUTION PERP | AD29: MADELIN- ECUREUIL RETRAITE PRO | AE29: PERIN- MILLEVIE PER | AF29: PERIN- PER CE | AG29: PERCO- BOX OFFICE PERCOI
F30: Frais arbitrage | O30: Réversion incluse dans la rente ci-dessous | Z30: {=IFERROR(OFFSET(BASECG!$B$4,0,MATCH(0,COUNTIF($Z$15:Z29,BASECG!$C$4:'BASECG'!$OG$4))),"")} -> CARDIF | AA30: {=IFERROR(_xlfn._xlws.FILTER(BASECG!$C$5:'BASECG'!$OG$5,BASECG!$C$4:'BASECG'!$OG$4=Z30),"")} -> ART83- CARDIF RETRAITE 83 | AB30: PERP- CARDIF MULTIPLUS PERP | AC30: MADELIN- CARDIF AMBITION RETRAITE PROFESSIONNELS | AD30: MADELIN- CARDIF RETRAITE MADELIN | AE30: MADELIN- CARDIF RETRAITE PROFESSIONNELS | AF30: MADELIN- INITIATIVE RETRAITE | AG30: PERIN- CARDIF ELITE RETRAITE | AH30: PERIN- CARDIF ESSENTIEL RETRAITE
F31: Frais transfert sortant | O31: Rente estimée à | Q31: ans** | S31: =IF(P31="","Obligatoire",IF(AND(R31="",OR(K12=Données!H50,K12=Données!H51,K12=Données!H55,K12=Données!H56)),"Obligatoire","")) -> Obligatoire | Z31: {=IFERROR(OFFSET(BASECG!$B$4,0,MATCH(0,COUNTIF($Z$15:Z30,BASECG!$C$4:'BASECG'!$OG$4))),"")} -> CREDIT_AGRICOLE | AA31: {=IFERROR(_xlfn._xlws.FILTER(BASECG!$C$5:'BASECG'!$OG$5,BASECG!$C$4:'BASECG'!$OG$4=Z31),"")} -> ART83- EXTENSION RETRAITE MAITRISEE | AB31: ART83- EXTENSION RETRAITE SUPPLEMENTAIRE EURO | AC31: ART83- EXTENSION RETRAITE SUPPLÉMENTAIRE MULTISUPPORT | AD31: ART83- EXTENSION RETRAITE VOLONTAIRE | AE31: PERP- PLAN VERT AVENIR | AF31: PERP- PLAN VERT VITALITE | AG31: MADELIN- ACCORDANCE | AH31: MADELIN- ACCORDANCE MULTISUPPORTS | AI31: MADELIN- PREDIAGRI POINTS RETRAITE | AJ31: MADELIN- PREDIAGRI RETRAITE | AK31: PERIN- EXTENSION RETRAITE MAÎTRISÉE PACTE 2019 ERM PACTE 2019 | AL31: PERIN- PER ASSURANCE PERSPECTIVE | AM31: PERCO- ALIM 'ÉPARGNE | AN31: PERCO- FAST'AMUNDI | AO31: PERCO- L'EPARGNE SALARIALE | AP31: PERCO- PER CONVERGENCE
F32: Clause bénéficiaire | M32: *En cas de sortie en capital d'un PER (et après transfert vers un PER), les intérêts sont fiscalisés au PFU **Estimation provenant du relevé de situation du contrat, sur la base de la somme en compte et sans tenir compte des futures cotisations | Z32: {=IFERROR(OFFSET(BASECG!$B$4,0,MATCH(0,COUNTIF($Z$15:Z31,BASECG!$C$4:'BASECG'!$OG$4))),"")} -> CREDIT_DU_NORD | AA32: {=IFERROR(_xlfn._xlws.FILTER(BASECG!$C$5:'BASECG'!$OG$5,BASECG!$C$4:'BASECG'!$OG$4=Z32),"")} -> PERP- ANTARIUS PERP | AB32: MADELIN- ANTARIUS RETRAITE « MADELIN » | AC32: PERIN- ANTARIUS PERin
F33: Garanties complémentaires | Z33: {=IFERROR(OFFSET(BASECG!$B$4,0,MATCH(0,COUNTIF($Z$15:Z32,BASECG!$C$4:'BASECG'!$OG$4))),"")} -> CREDIT_MUTUEL | AA33: {=IFERROR(_xlfn._xlws.FILTER(BASECG!$C$5:'BASECG'!$OG$5,BASECG!$C$4:'BASECG'!$OG$4=Z33),"")} -> ART83- RETRAITE ENTREPRISE MONOSUPPORT | AB33: ART83- RETRAITE ENTREPRISE MULTISUPPORT | AC33: ART83- RETRAITE ENTREPRISE P.E.R.E. | AD33: ART83- RETRAITE ENTREPRISE UC P.E.R.E. | AE33: ART83- RETRAITE SUPPLEMENTAIRE 83 | AF33: ART83- RETRAITE SUPPLEMENTAIRE 83 EN EUROS (ex Prévi Retraite Entreprises) | AG33: ART83- TRIADYS RETRAITE 83 | AH33: ART83- GAN RETRAITE PERFORMANCE ENTREPRISE | AI33: PERP- LE PERP INDEPENDANT | AJ33: PERP- PLAN RETRAITE REVENUS | AK33: PERP- MYRIALIS PERP | AL33: PERP- PREVI - HORIZONS | AM33: MADELIN- PERENIAL PENSION HORIZONS | AN33: MADELIN- PERENIAL PENSION RETRAITE | AO33: MADELIN- PLAN ASSUR HORIZONS PRO | AP33: MADELIN- PLAN ASSURANCE VIE PRO | AQ33: MADELIN- PREVI-RETRAITE INDEPENDANTS | AR33: MADELIN- PREVI-RETRAITE INDEPENDANTS AGRI | AS33: MADELIN- PREVI-RETRAITE INDEPENDANTS PROS | AT33: PERIN- PER ASSURANCE RETRAITE | AU33: PERIN- PER ASSURANCE RETRAITE CORPORATE | AV33: PERIN- PER ASSURANCE RETRAITE ENTREPRISE | AW33: PERIN- PROJECTION RETRAITE | AX33: PERIN- PERTINENCE RETRAITE | AY33: PERIN- SURAVENIR PER | AZ33: PERCO- ACTIVEPARGNE RETRAITE - PERCOI
Z34: {=IFERROR(OFFSET(BASECG!$B$4,0,MATCH(0,COUNTIF($Z$15:Z33,BASECG!$C$4:'BASECG'!$OG$4))),"")} -> EPSENS | AA34: {=IFERROR(_xlfn._xlws.FILTER(BASECG!$C$5:'BASECG'!$OG$5,BASECG!$C$4:'BASECG'!$OG$4=Z34),"")} -> PERCO- OFFRE SUR MESURE EPSENS
D35: Ces données vous sont communiquées à titre d'information, nous vous invitons à vérifier les CG | Z35: {=IFERROR(OFFSET(BASECG!$B$4,0,MATCH(0,COUNTIF($Z$15:Z34,BASECG!$C$4:'BASECG'!$OG$4))),"")} -> EPSOR | AA35: {=IFERROR(_xlfn._xlws.FILTER(BASECG!$C$5:'BASECG'!$OG$5,BASECG!$C$4:'BASECG'!$OG$4=Z35),"")} -> PERCO- PEI-PERCOI EPSOR - EPSOR
Z36: {=IFERROR(OFFSET(BASECG!$B$4,0,MATCH(0,COUNTIF($Z$15:Z35,BASECG!$C$4:'BASECG'!$OG$4))),"")} -> ERES | AA36: {=IFERROR(_xlfn._xlws.FILTER(BASECG!$C$5:'BASECG'!$OG$5,BASECG!$C$4:'BASECG'!$OG$4=Z36),"")} -> ART83- ERES RETRAITE 83 | AB36: PERP- LE PERP ERES 163X | AC36: PERIN- LE PER | AD36: PERIN- LE PER ERES BY SPIRICA | AE36: PERCO- ERES SELECTION 2 - PEI / PERCOI | AF36: PERCO- ERES SELECTION 7 | AG36: PERCO- PEI PERCOI ERES SELECTION 4
Z37: {=IFERROR(OFFSET(BASECG!$B$4,0,MATCH(0,COUNTIF($Z$15:Z36,BASECG!$C$4:'BASECG'!$OG$4))),"")} -> GAN | AA37: {=IFERROR(_xlfn._xlws.FILTER(BASECG!$C$5:'BASECG'!$OG$5,BASECG!$C$4:'BASECG'!$OG$4=Z37),"")} -> ART83- DIMENSION RETRAITE ACTIF | AB37: ART83- DIMENSION RETRAITE ENERGIE | AC37: ART83- DIMENSION RETRAITE ENTREPRISES | AD37: ART83- EXCELLENCE RETRAITE ENTREPRISE | AE37: ART83- GALYA RETRAITE ENTREPRISE | AF37: ART83- GALYA RETRAITE GARANTIE | AG37: ART83- GAN RETRAITE ENTREPRISE | AH37: ART83- GAN RETRAITE PERFORMANCE ENTREPRISE TPE | AI37: ART83- GROUPAMA DIMENSION RETRAITE ENTREPRISES | AJ37: ART83- RECORD-VERSION B | AK37: ART83- GAN RETRAITE PERFORMANCE ENTREPRISE | AL37: PERP- GAN INITIATIVE RETRAITE | AM37: PERP- GAN RETRAITE GARANTIE | AN37: PERP- GAN RETRAITE PERP | AO37: MADELIN- DIMENSION AVENIR AGRICULTEUR II | AP37: MADELIN- DIMENSION AVENIR PROFESSIONNELS II | AQ37: MADELIN- GALYA RETRAITE MADELIN | AR37: MADELIN- GAN PATRIMOINE INDEPENDANTS | AS37: MADELIN- GAN PATRIMOINE MADELIN RETRAITE | AT37: MADELIN- GAN PERFORMANCE RETRAITE PRO | AU37: MADELIN- GAN PREVOYANCE RETRAITE INDEPENDANT | AV37: MADELIN- GAN PREVOYANCE RETRAITE MADELIN | AW37: MADELIN- GAN RETRAITE INDEPENDANT | AX37: PERIN- GAN ASSURANCE NOUVELLE VIE | AY37: PERIN- GAN PATRIMOINE NOUVELLE VIE | AZ37: PERIN- GAN PREVOYANCE NOUVELLE VIE
Z38: {=IFERROR(OFFSET(BASECG!$B$4,0,MATCH(0,COUNTIF($Z$15:Z37,BASECG!$C$4:'BASECG'!$OG$4))),"")} -> GARANCE | AA38: {=IFERROR(_xlfn._xlws.FILTER(BASECG!$C$5:'BASECG'!$OG$5,BASECG!$C$4:'BASECG'!$OG$4=Z38),"")} -> PERP- GARANCE RETRAITE PERP | AB38: MADELIN- ARIA GROUPE / ARIA EVOLUTION | AC38: PERIN- GARANCE SÉRÉNITÉ
Z39: {=IFERROR(OFFSET(BASECG!$B$4,0,MATCH(0,COUNTIF($Z$15:Z38,BASECG!$C$4:'BASECG'!$OG$4))),"")} -> GENERALI | AA39: {=IFERROR(_xlfn._xlws.FILTER(BASECG!$C$5:'BASECG'!$OG$5,BASECG!$C$4:'BASECG'!$OG$4=Z39),"")} -> ART83- FRANCE PROFIL RETRAITE | AB39: ART83- FRANCE PROFIL RETRAITE MULTISUPPORTS 2008 | AC39: ART83- LA RETRAITE 15 | AD39: ART83- LA RETRAITE 94 - ARTICLE 83 | AE39: ART83- LEADER SUPPLEMENT RETRAITE | AF39: ART83- SCENARIO RETRAITE | AG39: ART83- SERENIDAD RETRAITE ARTICLE 83 | AH39: ART83- XAELIDIA RETRAITE ENTREPRISE | AI39: PERP- ANTHOLOGIE | AJ39: PERP- GPA PERP | AK39: PERP- GRAFIC | AL39: PERP- SERENIDAD PERP | AM39: PERP- LE PERP GENERALI PATRIMOINE | AN39: MADELIN- ESPACE INVEST MADELIN | AO39: MADELIN- GPA RETRAITE PRO | AP39: MADELIN- GPA RETRAITE PRO DUO | AQ39: MADELIN- GPA RETRAITE PRO HORIZON | AR39: MADELIN- LEADER PROTECTION RETRAITE INDEPENDANTS | AS39: MADELIN- PRISM MULTISUPPORTS | AT39: MADELIN- SCENARIO RETRAITE - MADELIN | AU39: MADELIN- SERENIDAD RETRAITE MADELIN | AV39: MADELIN- XAELIDIA RETRAITE INDIVIDUELLE | AW39: MADELIN- La retraite 94 | AX39: MADELIN- La retraite 08 | AY39: MADELIN- La retraite 08 - V2010 | AZ39: MADELIN-La retraite 13 | BA39: MADELIN- La retraite 15 | BB39: PERIN- La retraite 20 | BC39: PERIN- PER Générali Patrimoine | BD39: PERCO- ESSENZIO | BE39: PERCO- ESSENZIO 2 | BF39: PERCO- ESSENZIO 3 PLUS | BG39: PERCO- GAELIA - PERCOI | BH39: PERCO- GENERALI EPARGNE SALARIALE
Z40: {=IFERROR(OFFSET(BASECG!$B$4,0,MATCH(0,COUNTIF($Z$15:Z39,BASECG!$C$4:'BASECG'!$OG$4))),"")} -> GO_EPARGNE | AA40: {=IFERROR(_xlfn._xlws.FILTER(BASECG!$C$5:'BASECG'!$OG$5,BASECG!$C$4:'BASECG'!$OG$4=Z40),"")} -> PERCO- JUST GO
Z41: {=IFERROR(OFFSET(BASECG!$B$4,0,MATCH(0,COUNTIF($Z$15:Z40,BASECG!$C$4:'BASECG'!$OG$4))),"")} -> GROUPAMA | AA41: {=IFERROR(_xlfn._xlws.FILTER(BASECG!$C$5:'BASECG'!$OG$5,BASECG!$C$4:'BASECG'!$OG$4=Z41),"")} -> ART83- GROUPAMA DIMENSION RETRAITE ENTREPRISES | AB41: ART83- GROUPAMA RETRAITE PERFORMANCE | AC41: ART83- SYNERGIE RETRAITE ENTREPRISE | AD41: ART83- SYNERGIE RETRAITE LIBERTE | AE41: ART83- SYNERGIE RETRAITE SERENITE | AF41: PERP- GROUPAMA RETRAITE ACTIVE | AG41: MADELIN- AGRI RETRAITE ACTIVE | AH41: MADELIN- ENERGIE RETRAITE ACTIVE | AI41: MADELIN- GROUPAMA AGRI-RETRAITE POINTS | AJ41: PERIN- GROUPAMA NOUVELLE VIE
Z42: {=IFERROR(OFFSET(BASECG!$B$4,0,MATCH(0,COUNTIF($Z$15:Z41,BASECG!$C$4:'BASECG'!$OG$4))),"")} -> HARMONIE_MUTUELLE | AA42: {=IFERROR(_xlfn._xlws.FILTER(BASECG!$C$5:'BASECG'!$OG$5,BASECG!$C$4:'BASECG'!$OG$4=Z42),"")} -> PERIN- PER INDIVIDUEL SOLUTION GROUPE VYV | AB42: PERIN- PER ENTREPRISE OBLIGATOIRE
Z43: {=IFERROR(OFFSET(BASECG!$B$4,0,MATCH(0,COUNTIF($Z$15:Z42,BASECG!$C$4:'BASECG'!$OG$4))),"")} -> HSBC | AA43: {=IFERROR(_xlfn._xlws.FILTER(BASECG!$C$5:'BASECG'!$OG$5,BASECG!$C$4:'BASECG'!$OG$4=Z43),"")} -> ART83- ELYS RETRAITE 83 | AB43: ART83- HSBC RETRAITE 83 | AC43: PERP- PLAN ELYSEES RETRAITE PATRIMOINE | AD43: MADELIN- ELYSEES RETRAITE INDEPENDANTS | AE43: PERIN- HSBC STRATEGIE RETRAITE
Z44: {=IFERROR(OFFSET(BASECG!$B$4,0,MATCH(0,COUNTIF($Z$15:Z43,BASECG!$C$4:'BASECG'!$OG$4))),"")} -> LA_BANQUE_POSTALE | AA44: {=IFERROR(_xlfn._xlws.FILTER(BASECG!$C$5:'BASECG'!$OG$5,BASECG!$C$4:'BASECG'!$OG$4=Z44),"")} -> ART83- PERE MULTISUPPORTS | AB44: ART83- RETRAITE 83 | AC44: PERP- SOLESIO PERP EVOLUTION | AD44: PERP- SOLESIO PERP HORIZON | AE44: PERIN- CACHEMIRE PER
Z45: {=IFERROR(OFFSET(BASECG!$B$4,0,MATCH(0,COUNTIF($Z$15:Z44,BASECG!$C$4:'BASECG'!$OG$4))),"")} -> LA_MEDICALE | AA45: {=IFERROR(_xlfn._xlws.FILTER(BASECG!$C$5:'BASECG'!$OG$5,BASECG!$C$4:'BASECG'!$OG$4=Z45),"")} -> MADELIN- MEDICALE HORIZON MADELIN 2 | AB45: MADELIN- MEDICALE RETRAITE | AC45: MADELIN- MEDICALE HORIZON MADELIN | AD45: MADELIN- LA MEDICALE SERENITE | AE45: PERIN- LA MEDICALE PERENNITE
Z46: {=IFERROR(OFFSET(BASECG!$B$4,0,MATCH(0,COUNTIF($Z$15:Z45,BASECG!$C$4:'BASECG'!$OG$4))),"")} -> LCL | AA46: {=IFERROR(_xlfn._xlws.FILTER(BASECG!$C$5:'BASECG'!$OG$5,BASECG!$C$4:'BASECG'!$OG$4=Z46),"")} -> ART83- LCL RETRAITE 83 | AB46: ART83- LCL RETRAITE MAITRISEE | AC46: ART83- LCL RETRAITE VOLONTAIRE | AD46: PERP- VELOURS | AE46: MADELIN- PRO LIGNES DE VIE | AF46: PERIN- LCL RETRAITE PER | AG46: PERCO- ALIM 'ÉPARGNE | AH46: PERCO- ES - PL
Z47: {=IFERROR(OFFSET(BASECG!$B$4,0,MATCH(0,COUNTIF($Z$15:Z46,BASECG!$C$4:'BASECG'!$OG$4))),"")} -> LPA | AA47: {=IFERROR(_xlfn._xlws.FILTER(BASECG!$C$5:'BASECG'!$OG$5,BASECG!$C$4:'BASECG'!$OG$4=Z47),"")} -> MADELIN- AVOCAPI
Z48: {=IFERROR(OFFSET(BASECG!$B$4,0,MATCH(0,COUNTIF($Z$15:Z47,BASECG!$C$4:'BASECG'!$OG$4))),"")} -> MAAF | AA48: {=IFERROR(_xlfn._xlws.FILTER(BASECG!$C$5:'BASECG'!$OG$5,BASECG!$C$4:'BASECG'!$OG$4=Z48),"")} -> ART83- MAAF 83 | AB48: PERP- WINNEO RETRAITE | AC48: MADELIN- DYNALTO PRO | AD48: MADELIN- MAAF 41 | AE48: MADELIN- WINALTO PRO | AF48: MADELIN- WINNEO PRO | AG48: PERIN- PER WINALTO RETRAITE
F49: Contrat N° | K49: =IFERROR(INDEX(BASECG!C1:OG1,MATCH("Oui",BASECG!C3:OG3,0)),0) -> 0 | Z49: {=IFERROR(OFFSET(BASECG!$B$4,0,MATCH(0,COUNTIF($Z$15:Z48,BASECG!$C$4:'BASECG'!$OG$4))),"")} -> MACIF | AA49: {=IFERROR(_xlfn._xlws.FILTER(BASECG!$C$5:'BASECG'!$OG$5,BASECG!$C$4:'BASECG'!$OG$4=Z49),"")} -> ART83- ACTIPLUS RETRAITE ENTREPRISE | AB49: PERP- MULTI PERP | AC49: MADELIN- MEDICIS RETRAITE MADELIN | AD49: MADELIN- ACTIFONDS RETRAITE | AE49: MADELIN- ACTIPLUS RETRAITE | AF49: PERIN- MULTI HORIZON RETRAITE - MUTAVIE
D50: Phase Epargne | F50: Versement annuel | Z50: {=IFERROR(OFFSET(BASECG!$B$4,0,MATCH(0,COUNTIF($Z$15:Z49,BASECG!$C$4:'BASECG'!$OG$4))),"")} -> MACSF | AA50: {=IFERROR(_xlfn._xlws.FILTER(BASECG!$C$5:'BASECG'!$OG$5,BASECG!$C$4:'BASECG'!$OG$4=Z50),"")} -> PERP- PERP'S (Plan d'Epargne Retraite des Professions de Santé) | AB50: MADELIN- RFPA RETRAITE MADELIN (RES FONDS DE PENSION AVENIR) | AC50: PERIN- RES RETRAITE
F51: Date d’effet | Z51: {=IFERROR(OFFSET(BASECG!$B$4,0,MATCH(0,COUNTIF($Z$15:Z50,BASECG!$C$4:'BASECG'!$OG$4))),"")} -> MAIF | AA51: {=IFERROR(_xlfn._xlws.FILTER(BASECG!$C$5:'BASECG'!$OG$5,BASECG!$C$4:'BASECG'!$OG$4=Z51),"")} -> PERP- PERP MAIF | AB51: PERIN- PER RESPONSABLE ET SOLIDAIRE
F52: Date de commercialisation du contrat par la cie | K52: =IF(K49=0,"",HLOOKUP(K49,BASECG!$C$1:$OG$31,8,FALSE)) | Z52: {=IFERROR(OFFSET(BASECG!$B$4,0,MATCH(0,COUNTIF($Z$15:Z51,BASECG!$C$4:'BASECG'!$OG$4))),"")} -> MALAKOFF_HUMANIS | AA52: {=IFERROR(_xlfn._xlws.FILTER(BASECG!$C$5:'BASECG'!$OG$5,BASECG!$C$4:'BASECG'!$OG$4=Z52),"")} -> MADELIN- RADIANCE HUMANIS RETRAITE PRO | AB52: PERIN- PER OBLIGATOIRE PATRIMONIAL
F53: Provision mathématique | Z53: {=IFERROR(OFFSET(BASECG!$B$4,0,MATCH(0,COUNTIF($Z$15:Z52,BASECG!$C$4:'BASECG'!$OG$4))),"")} -> MAPA | AA53: {=IFERROR(_xlfn._xlws.FILTER(BASECG!$C$5:'BASECG'!$OG$5,BASECG!$C$4:'BASECG'!$OG$4=Z53),"")} -> MADELIN- ACTIFONDS RETRAITE | AB53: MADELIN- MEDICIS RETRAITE MADELIN
F54: Dont intérets | Z54: {=IFERROR(OFFSET(BASECG!$B$4,0,MATCH(0,COUNTIF($Z$15:Z53,BASECG!$C$4:'BASECG'!$OG$4))),"")} -> MATMUT | AA54: {=IFERROR(_xlfn._xlws.FILTER(BASECG!$C$5:'BASECG'!$OG$5,BASECG!$C$4:'BASECG'!$OG$4=Z54),"")} -> PERIN- COMPLICE RETRAITE
F55: Nombre de fonds accessibles | K55: =IF(K49=0,"",HLOOKUP(K49,BASECG!$C$1:$OG$31,11,FALSE)) | Z55: {=IFERROR(OFFSET(BASECG!$B$4,0,MATCH(0,COUNTIF($Z$15:Z54,BASECG!$C$4:'BASECG'!$OG$4))),"")} -> MEDICIS | AA55: {=IFERROR(_xlfn._xlws.FILTER(BASECG!$C$5:'BASECG'!$OG$5,BASECG!$C$4:'BASECG'!$OG$4=Z55),"")} -> PERP- PERP MEDICIS | AB55: MADELIN- MEDICIS RETRAITE MADELIN | AC55: PERIN- PER MEDICIS MULTISUPPORT | AD55: PERIN- PER MEDICIS PATRIMONIAL | AE55: PERIN- PER MEDICIS PRODUIT EN POINTS
F56: Répartition UC/€ | Z56: {=IFERROR(OFFSET(BASECG!$B$4,0,MATCH(0,COUNTIF($Z$15:Z55,BASECG!$C$4:'BASECG'!$OG$4))),"")} -> MMA | AA56: {=IFERROR(_xlfn._xlws.FILTER(BASECG!$C$5:'BASECG'!$OG$5,BASECG!$C$4:'BASECG'!$OG$4=Z56),"")} -> ART83- MMA RETRAITE 83 (ancien MDM RETRAITE 83) | AB56: PERP- MULTISUPPORTS PERP | AC56: MADELIN- MMA MULTISUPPORTS RETRAITE INDEPENDANTS | AD56: MADELIN- MMA RETRAITE PRO | AE56: MADELIN- MMA SOLUTIONS RETRAITE AGRI | AF56: MADELIN- MMA SOLUTIONS RETRAITE AGRI + | AG56: MADELIN- MMA SOLUTIONS RETRAITE PRO | AH56: MADELIN- MMA SOLUTIONS RETRAITE PRO + | AI56: MADELIN- MULTISTRATEGIES RETRAITE AGRI | AJ56: MADELIN- MULTISTRATEGIES RETRAITE PRO | AK56: MADELIN- PLAN MDM RETRAITE INDEPENDANTS | AL56: MADELIN- SIGNATURE RETRAITE AGRI | AM56: MADELIN- SIGNATURE RETRAITE PRO | AN56: PERIN- SIGNATURE PER | AO56: PERIN- MMA PER AVENIR
F57: Rendement fonds € | K57: =IF(K49=0,"",HLOOKUP(K49,BASECG!$C$1:$OG$31,13,FALSE)) | Z57: {=IFERROR(OFFSET(BASECG!$B$4,0,MATCH(0,COUNTIF($Z$15:Z56,BASECG!$C$4:'BASECG'!$OG$4))),"")} -> MNRA | AA57: {=IFERROR(_xlfn._xlws.FILTER(BASECG!$C$5:'BASECG'!$OG$5,BASECG!$C$4:'BASECG'!$OG$4=Z57),"")} -> MADELIN- ARIA GROUPE / ARIA EVOLUTION
F58: Frais sur versements | K58: =IF(K49=0,"",HLOOKUP(K49,BASECG!$C$1:$OG$31,14,FALSE)) | Z58: {=IFERROR(OFFSET(BASECG!$B$4,0,MATCH(0,COUNTIF($Z$15:Z57,BASECG!$C$4:'BASECG'!$OG$4))),"")} -> NORTIA | AA58: {=IFERROR(_xlfn._xlws.FILTER(BASECG!$C$5:'BASECG'!$OG$5,BASECG!$C$4:'BASECG'!$OG$4=Z58),"")} -> PERP- COMPLEMENT EPARGNE RETRAITE | AB58: MADELIN- QUADRANCE | AC58: PERIN- PER PANTHEA | AD58: PERIN- PER ENEDIA | AE58: PERIN- PER PRIVATE
F59: Frais de gestion | K59: =IF(K49=0,"",HLOOKUP(K49,BASECG!$C$1:$OG$31,15,FALSE)) | Z59: {=IFERROR(OFFSET(BASECG!$B$4,0,MATCH(0,COUNTIF($Z$15:Z58,BASECG!$C$4:'BASECG'!$OG$4))),"")} -> ORADEA | AA59: {=IFERROR(_xlfn._xlws.FILTER(BASECG!$C$5:'BASECG'!$OG$5,BASECG!$C$4:'BASECG'!$OG$4=Z59),"")} -> PERP- PERP LIGNAGE | AB59: PERIN- PER LIGNAGE
F60: Frais arbitrage | K60: =IF(K49=0,"",HLOOKUP(K49,BASECG!$C$1:$OG$31,16,FALSE)) | Z60: {=IFERROR(OFFSET(BASECG!$B$4,0,MATCH(0,COUNTIF($Z$15:Z59,BASECG!$C$4:'BASECG'!$OG$4))),"")} -> PREFON | AA60: {=IFERROR(_xlfn._xlws.FILTER(BASECG!$C$5:'BASECG'!$OG$5,BASECG!$C$4:'BASECG'!$OG$4=Z60),"")} -> PERP- PREFON-RETRAITE | AB60: PERIN- PER PREFON RETRAITE
F61: Frais transfert sortant | K61: =IF(K49=0,"",HLOOKUP(K49,BASECG!$C$1:$OG$31,17,FALSE)) | Z61: {=IFERROR(OFFSET(BASECG!$B$4,0,MATCH(0,COUNTIF($Z$15:Z60,BASECG!$C$4:'BASECG'!$OG$4))),"")} -> PREVOIR | AA61: {=IFERROR(_xlfn._xlws.FILTER(BASECG!$C$5:'BASECG'!$OG$5,BASECG!$C$4:'BASECG'!$OG$4=Z61),"")} -> PERP- PERP LIGNAGE | AB61: MADELIN- PREVOIR PRO RETRAITE | AC61: PERIN- SOLUTION PLAN EPARGNE RETRAITE
F62: Clause bénéficiaire | K62: =IF(K49=0,"",HLOOKUP(K49,BASECG!$C$1:$OG$31,18,FALSE)) | Z62: {=IFERROR(OFFSET(BASECG!$B$4,0,MATCH(0,COUNTIF($Z$15:Z61,BASECG!$C$4:'BASECG'!$OG$4))),"")} -> PRIMONIAL | AA62: {=IFERROR(_xlfn._xlws.FILTER(BASECG!$C$5:'BASECG'!$OG$5,BASECG!$C$4:'BASECG'!$OG$4=Z62),"")} -> MADELIN- GESTION PRIVEE PROMADELIN | AB62: MADELIN- CARDIF RETRAITE PROFESSIONNELS ( PATRIMOINE MANAGEMENT ET ASSOCIES) | AC62: PERIN- PRIMOPER
F63: Garanties complémentaires | K63: =IF(K49=0,"",HLOOKUP(K49,BASECG!$C$1:$OG$31,19,FALSE)) | Z63: {=IFERROR(OFFSET(BASECG!$B$4,0,MATCH(0,COUNTIF($Z$15:Z62,BASECG!$C$4:'BASECG'!$OG$4))),"")} -> PRO_BTP | AA63: {=IFERROR(_xlfn._xlws.FILTER(BASECG!$C$5:'BASECG'!$OG$5,BASECG!$C$4:'BASECG'!$OG$4=Z63),"")} -> PERP- PERP CONFIANCE BTP | AB63: MADELIN- RETRAITE SUPPLEMENTAIRE DES ARTISANS | AC63: PERIN- PER INDIVIDUEL CONFIANCE
D64: Phase Liquidation | F64: Age limite liquidation | K64: =IF(K49=0,"",HLOOKUP(K49,BASECG!$C$1:$OG$31,20,FALSE)) | Z64: {=IFERROR(OFFSET(BASECG!$B$4,0,MATCH(0,COUNTIF($Z$15:Z63,BASECG!$C$4:'BASECG'!$OG$4))),"")} -> SMA | AA64: {=IFERROR(_xlfn._xlws.FILTER(BASECG!$C$5:'BASECG'!$OG$5,BASECG!$C$4:'BASECG'!$OG$4=Z64),"")} -> PERIN- PER INDIVIDUEL SMAVIE
E65: Capital | F65: Sortie capital possible à la retraite (sauf excepiton) | K65: =IF(K49=0,"",HLOOKUP(K49,BASECG!$C$1:$OG$31,21,FALSE)) | Z65: {=IFERROR(OFFSET(BASECG!$B$4,0,MATCH(0,COUNTIF($Z$15:Z64,BASECG!$C$4:'BASECG'!$OG$4))),"")} -> SOCIETE_GENERALE | AA65: {=IFERROR(_xlfn._xlws.FILTER(BASECG!$C$5:'BASECG'!$OG$5,BASECG!$C$4:'BASECG'!$OG$4=Z65),"")} -> ART83- PALISSANDRE ENTREPRISES | AB65: PERP- PERP EPICEA | AC65: MADELIN- PALISSANDRE | AD65: PERIN- PER ACACIA | AE65: PERCO- EPARGNE SALARIALE ARCANCIA V
F66: Fractionnement du capital | K66: =IF(K49=0,"",HLOOKUP(K49,BASECG!$C$1:$OG$31,22,FALSE)) | Z66: {=IFERROR(OFFSET(BASECG!$B$4,0,MATCH(0,COUNTIF($Z$15:Z65,BASECG!$C$4:'BASECG'!$OG$4))),"")} -> SWISSLIFE | AA66: {=IFERROR(_xlfn._xlws.FILTER(BASECG!$C$5:'BASECG'!$OG$5,BASECG!$C$4:'BASECG'!$OG$4=Z66),"")} -> ART83- GARANTIE RETRAITE ENTREPRISE 2000 | AB66: ART83- GARANTIE RETRAITE ENTREPRISES | AC66: ART83- SWISSLIFE PLAN D'EPARGNE RETRAITE ENTREPRISES | AD66: ART83- SWISSLIFE PREPARATION RETRAITE | AE66: ART83- SWISSLIFE RETRAITE ARTICLE 83 | AF66: ART83- SWISSLIFE RETRAITE ENTREPRISES | AG66: PERP- SWISSLIFE PERP | AH66: MADELIN- GARANTIE RETRAITE INDEPENDANTS | AI66: MADELIN- SWISSLIFE RETRAITE AGRICOLE | AJ66: MADELIN- SWISSLIFE RETRAITE INDEPENDANTS | AK66: MADELIN- SWISSLIFE RETRAITE MADELIN | AL66: MADELIN- SWISSLIFE RETRAITE SELECTION | AM66: PERIN- PER EXPERT | AN66: PERIN- SWISSLIFE PER INDIVIDUEL | AO66: PERCO- SWISSLIFE PER COLLECTIF
F67: Rachat libre | K67: =IF(K49=0,"",HLOOKUP(K49,BASECG!$C$1:$OG$31,23,FALSE)) | Z67: {=IFERROR(OFFSET(BASECG!$B$4,0,MATCH(0,COUNTIF($Z$15:Z66,BASECG!$C$4:'BASECG'!$OG$4))),"")} -> UFF | AA67: {=IFERROR(_xlfn._xlws.FILTER(BASECG!$C$5:'BASECG'!$OG$5,BASECG!$C$4:'BASECG'!$OG$4=Z67),"")} -> ART83- UFF 83 | AB67: ART83- UFF RETRAITE ENTREPRISE | AC67: ART83- UFF RETRAITE ENTREPRISE PLUS | AD67: MADELIN- UFF RETRAITE MADELIN | AE67: MADELIN-UFF RETRAITE INDEPENDANT
E68: Rente | F68: Table utilisée pour la conversion en rente | K68: =IF(K49=0,"",HLOOKUP(K49,BASECG!$C$1:$OG$31,24,FALSE)) | Z68: {=IFERROR(OFFSET(BASECG!$B$4,0,MATCH(0,COUNTIF($Z$15:Z67,BASECG!$C$4:'BASECG'!$OG$4))),"")} -> UMR | AA68: {=IFERROR(_xlfn._xlws.FILTER(BASECG!$C$5:'BASECG'!$OG$5,BASECG!$C$4:'BASECG'!$OG$4=Z68),"")} -> ART83- COREM CO | AB68: PERIN- ORIGINEO BY CRYSTAL | AC68: PERIN-COREM | AD68: PERIN- PERIVIE | AE68: PERIN- PLACEMENT-DIRECT RETRAITE ISR
F69: Table garantie à l’adhésion | H69: Table garantie à l’adhésion | K69: =IF(K49=0,"",HLOOKUP(K49,BASECG!$C$1:$OG$31,25,FALSE))
F70: Taux technique | H70: Taux technique | K70: =IF(K49=0,"",HLOOKUP(K49,BASECG!$C$1:$OG$31,26,FALSE))
F71: Frais sur arrérages | H71: Frais sur arrérages | K71: =IF(K49=0,"",HLOOKUP(K49,BASECG!$C$1:$OG$31,27,FALSE))
F72: Annuités garanties | H72: Annuités garanties | K72: =IF(K49=0,"",HLOOKUP(K49,BASECG!$C$1:$OG$31,28,FALSE))
F73: Réversion possible | H73: Réversion possible | K73: =IF(K49=0,"",HLOOKUP(K49,BASECG!$C$1:$OG$31,29,FALSE))
F74: Réversion incluse dans la rente ci-dessous | K74: =IF(K49=0,"",HLOOKUP(K49,BASECG!$C$1:$OG$31,30,FALSE))
F75: Rente estimée* | H75: ans

Sheet BASECG
A1: Total analysé | C1: Contrat N°1 | D1: Contrat N°2 | E1: Contrat N°3 | F1: Contrat N°4 | G1: Contrat N°5 | H1: Contrat N°6 | I1: Contrat N°7 | J1: Contrat N°8 | K1: Contrat N°9 | L1: Contrat N°10 | M1: Contrat N°11 | N1: Contrat N°12 | O1: Contrat N°13 | P1: Contrat N°14 | Q1: Contrat N°15 | R1: Contrat N°16 | S1: Contrat N°17 | T1: Contrat N°18 | U1: Contrat N°19 | V1: Contrat N°20 | W1: Contrat N°21 | X1: Contrat N°22 | Y1: Contrat N°23 | Z1: Contrat N°24 | AA1: Contrat N°25 | AB1: Contrat N°26 | AC1: Contrat N°27 | AD1: Contrat N°28 | AE1: Contrat N°29 | AF1: Contrat N°30 | AG1: Contrat N°31 | AH1: Contrat N°32 | AI1: Contrat N°33 | AJ1: Contrat N°34 | AK1: Contrat N°35 | AL1: Contrat N°36 | AM1: Contrat N°37 | AN1: Contrat N°38 | AO1: Contrat N°39 | AP1: Contrat N°40 | AQ1: Contrat N°41 | AR1: Contrat N°42 | AS1: Contrat N°43 | AT1: Contrat N°44 | AU1: Contrat N°45 | AV1: Contrat N°46 | AW1: Contrat N°47 | AX1: Contrat N°48 | AY1: Contrat N°49 | AZ1: Contrat N°50 | BA1: Contrat N°51 | BB1: Contrat N°52 | BC1: Contrat N°53 | BD1: Contrat N°54 | BE1: Contrat N°55 | BF1: Contrat N°56 | BG1: Contrat N°57 | BH1: Contrat N°58 | BI1: Contrat N°59 | BJ1: Contrat N°60 | BK1: Contrat N°61 | BL1: Contrat N°62 | BM1: Contrat N°63 | BN1: Contrat N°64 | BO1: Contrat N°65 | BP1: Contrat N°66 | BQ1: Contrat N°67 | BR1: Contrat N°68 | BS1: Contrat N°69 | BT1: Contrat N°70 | BU1: Contrat N°71 | BV1: Contrat N°72 | BW1: Contrat N°73 | BX1: Contrat N°74 | BY1: Contrat N°75 | BZ1: Contrat N°76 | CA1: Contrat N°77 | CB1: Contrat N°78 | CC1: Contrat N°79 | CD1: Contrat N°80 | CE1: Contrat N°81 | CF1: Contrat N°82 | CG1: Contrat N°83 | CH1: Contrat N°84 | CI1: Contrat N°85 | CJ1: Contrat N°86 | CK1: Contrat N°87 | CL1: Contrat N°88 | CM1: Contrat N°89 | CN1: Contrat N°90 | CO1: Contrat N°91 | CP1: Contrat N°92 | CQ1: Contrat N°93 | CR1: Contrat N°94 | CS1: Contrat N°95 | CT1: Contrat N°96 | CU1: Contrat N°97 | CV1: Contrat N°98 | CW1: Contrat N°99 | CX1: Contrat N°100 | CY1: Contrat N°101 | CZ1: Contrat N°102 | DA1: Contrat N°103 | DB1: Contrat N°104 | DC1: Contrat N°105 | DD1: Contrat N°106 | DE1: Contrat N°107 | DF1: Contrat N°108 | DG1: Contrat N°109 | DH1: Contrat N°110 | DI1: Contrat N°111 | DJ1: Contrat N°112 | DK1: Contrat N°113 | DL1: Contrat N°114 | DM1: Contrat N°115 | DN1: Contrat N°116 | DO1: Contrat N°117 | DP1: Contrat N°118 | DQ1: Contrat N°119 | DR1: Contrat N°120 | DS1: Contrat N°121 | DT1: Contrat N°122 | DU1: Contrat N°123 | DV1: Contrat N°124 | DW1: Contrat N°125 | DX1: Contrat N°126 | DY1: Contrat N°127 | DZ1: Contrat N°128 | EA1: Contrat N°129 | EB1: Contrat N°130 | EC1: Contrat N°131 | ED1: Contrat N°132 | EE1: Contrat N°133 | EF1: Contrat N°134 | EG1: Contrat N°135 | EH1: Contrat N°136 | EI1: Contrat N°137 | EJ1: Contrat N°138 | EK1: Contrat N°139 | EL1: Contrat N°140 | EM1: Contrat N°141 | EN1: Contrat N°142 | EO1: Contrat N°143 | EP1: Contrat N°144 | EQ1: Contrat N°145 | ER1: Contrat N°146 | ES1: Contrat N°147 | ET1: Contrat N°148 | EU1: Contrat N°149 | EV1: Contrat N°150 | EW1: Contrat N°151 | EX1: Contrat N°152 | EY1: Contrat N°153 | EZ1: Contrat N°154 | FA1: Contrat N°155 | FB1: Contrat N°156 | FC1: Contrat N°157 | FD1: Contrat N°158 | FE1: Contrat N°159 | FF1: Contrat N°160 | FG1: Contrat N°161 | FH1: Contrat N°162 | FI1: Contrat N°163 | FJ1: Contrat N°164 | FK1: Contrat N°165 | FL1: Contrat N°166 | FM1: Contrat N°167 | FN1: Contrat N°168 | FO1: Contrat N°169 | FP1: Contrat N°170 | FQ1: Contrat N°171 | FR1: Contrat N°172 | FS1: Contrat N°173 | FT1: Contrat N°174 | FU1: Contrat N°175 | FV1: Contrat N°176 | FW1: Contrat N°177 | FX1: Contrat N°178 | FY1: Contrat N°179 | FZ1: Contrat N°180 | GA1: Contrat N°181 | GB1: Contrat N°182 | GC1: Contrat N°183 | GD1: Contrat N°184 | GE1: Contrat N°185 | GF1: Contrat N°186 | GG1: Contrat N°187 | GH1: Contrat N°188 | GI1: Contrat N°189 | GJ1: Contrat N°190 | GK1: Contrat N°191 | GL1: Contrat N°192 | GM1: Contrat N°193 | GN1: Contrat N°194 | GO1: Contrat N°195 | GP1: Contrat N°196 | GQ1: Contrat N°197 | GR1: Contrat N°198 | GS1: Contrat N°199 | GT1: Contrat N°200 | GU1: Contrat N°201 | GV1: Contrat N°202 | GW1: Contrat N°203 | GX1: Contrat N°204 | GY1: Contrat N°205 | GZ1: Contrat N°206 | HA1: Contrat N°207 | HB1: Contrat N°208 | HC1: Contrat N°209 | HD1: Contrat N°210 | HE1: Contrat N°211 | HF1: Contrat N°212 | HG1: Contrat N°213 | HH1: Contrat N°214 | HI1: Contrat N°215 | HJ1: Contrat N°216 | HK1: Contrat N°217 | HL1: Contrat N°218 | HM1: Contrat N°219 | HN1: Contrat N°220 | HO1: Contrat N°221 | HP1: Contrat N°222 | HQ1: Contrat N°223 | HR1: Contrat N°224 | HS1: Contrat N°225 | HT1: Contrat N°226 | HU1: Contrat N°227 | HV1: Contrat N°228 | HW1: Contrat N°229 | HX1: Contrat N°230 | HY1: Contrat N°231 | HZ1: Contrat N°232 | IA1: Contrat N°233 | IB1: Contrat N°234 | IC1: Contrat N°235 | ID1: Contrat N°236 | IE1: Contrat N°237 | IF1: Contrat N°238 | IG1: Contrat N°239 | IH1: Contrat N°240 | II1: Contrat N°241 | IJ1: Contrat N°242 | IK1: Contrat N°243 | IL1: Contrat N°244 | IM1: Contrat N°245 | IN1: Contrat N°246 | IO1: Contrat N°247 | IP1: Contrat N°248 | IQ1: Contrat N°249 | IR1: Contrat N°250 | IS1: Contrat N°251 | IT1: Contrat N°252 | IU1: Contrat N°253 | IV1: Contrat N°254 | IW1: Contrat N°255 | IX1: Contrat N°256 | IY1: Contrat N°257 | IZ1: Contrat N°258 | JA1: Contrat N°259 | JB1: Contrat N°260 | JC1: Contrat N°261 | JD1: Contrat N°262 | JE1: Contrat N°263 | JF1: Contrat N°264 | JG1: Contrat N°265 | JH1: Contrat N°266 | JI1: Contrat N°267 | JJ1: Contrat N°268 | JK1: Contrat N°269 | JL1: Contrat N°270 | JM1: Contrat N°271 | JN1: Contrat N°272 | JO1: Contrat N°273 | JP1: Contrat N°274 | JQ1: Contrat N°275 | JR1: Contrat N°276 | JS1: Contrat N°277 | JT1: Contrat N°278 | JU1: Contrat N°279 | JV1: Contrat N°280 | JW1: Contrat N°281 | JX1: Contrat N°282 | JY1: Contrat N°283 | JZ1: Contrat N°284 | KA1: Contrat N°285 | KB1: Contrat N°286 | KC1: Contrat N°287 | KD1: Contrat N°288 | KE1: Contrat N°289 | KF1: Contrat N°290 | KG1: Contrat N°291 | KH1: Contrat N°292 | KI1: Contrat N°293 | KJ1: Contrat N°294 | KK1: Contrat N°295 | KL1: Contrat N°296 | KM1: Contrat N°297 | KN1: Contrat N°298 | KO1: Contrat N°299 | KP1: Contrat N°300 | KQ1: Contrat N°301 | KR1: Contrat N°302 | KS1: Contrat N°303 | KT1: Contrat N°304 | KU1: Contrat N°305 | KV1: Contrat N°306 | KW1: Contrat N°307 | KX1: Contrat N°308 | KY1: Contrat N°309 | KZ1: Contrat N°310 | LA1: Contrat N°311 | LB1: Contrat N°312 | LC1: Contrat N°313 | LD1: Contrat N°314 | LE1: Contrat N°315 | LF1: Contrat N°316 | LG1: Contrat N°317 | LH1: Contrat N°318 | LI1: Contrat N°319 | LJ1: Contrat N°320 | LK1: Contrat N°321 | LL1: Contrat N°322 | LM1: Contrat N°323 | LN1: Contrat N°324 | LO1: Contrat N°325 | LP1: Contrat N°326 | LQ1: Contrat N°327 | LR1: Contrat N°328 | LS1: Contrat N°329 | LT1: Contrat N°330 | LU1: Contrat N°331 | LV1: Contrat N°332 | LW1: Contrat N°333 | LX1: Contrat N°334 | LY1: Contrat N°335 | LZ1: Contrat N°336 | MA1: Contrat N°337 | MB1: Contrat N°338 | MC1: Contrat N°339 | MD1: Contrat N°340 | ME1: Contrat N°341 | MF1: Contrat N°342 | MG1: Contrat N°343 | MH1: Contrat N°344 | MI1: Contrat N°345 | MJ1: Contrat N°346 | MK1: Contrat N°347 | ML1: Contrat N°348 | MM1: Contrat N°349 | MN1: Contrat N°350 | MO1: Contrat N°351 | MP1: Contrat N°352 | MQ1: Contrat N°353 | MR1: Contrat N°354 | MS1: Contrat N°355 | MT1: Contrat N°356 | MU1: Contrat N°357 | MV1: Contrat N°358 | MW1: Contrat N°359 | MX1: Contrat N°360 | MY1: Contrat N°361 | MZ1: Contrat N°362 | NA1: Contrat N°363 | NB1: Contrat N°364 | NC1: Contrat N°365 | ND1: Contrat N°366 | NE1: Contrat N°367 | NF1: Contrat N°368 | NG1: Contrat N°369 | NH1: Contrat N°370 | NI1: Contrat N°371 | NJ1: Contrat N°372 | NK1: Contrat N°373 | NL1: Contrat N°374 | NM1: Contrat N°375 | NN1: Contrat N°376 | NO1: Contrat N°377 | NP1: Contrat N°378 | NQ1: Contrat N°379 | NR1: Contrat N°380 | NS1: Contrat N°381 | NT1: Contrat N°382 | NU1: Contrat N°383 | NV1: Contrat N°384 | NW1: Contrat N°385 | NX1: Contrat N°386 | NY1: Contrat N°387 | NZ1: Contrat N°388 | OA1: Contrat N°389 | OB1: Contrat N°390 | OC1: Contrat N°391 | OD1: Contrat N°392 | OE1: Contrat N°393 | OF1: Contrat N°394 | OG1: Contrat N°395
A2: =COUNTA(C8:OG8) -> 161 | C2: =IF('CT à Transf'!$K$14=C4,"Oui","") | D2: =IF('CT à Transf'!$K$14=D4,"Oui","") | E2: =IF('CT à Transf'!$K$14=E4,"Oui","") | F2: =IF('CT à Transf'!$K$14=F4,"Oui","") | G2: =IF('CT à Transf'!$K$14=G4,"Oui","") | H2: =IF('CT à Transf'!$K$14=H4,"Oui","") | I2: =IF('CT à Transf'!$K$14=I4,"Oui","") | J2: =IF('CT à Transf'!$K$14=J4,"Oui","") | ... OG2: =IF('CT à Transf'!$K$14=OG4,"Oui","")
C3: =IF(C2="Oui",IF(C5='CT à Transf'!$K$16,"Oui",""),"") | D3: =IF(D2="Oui",IF(D5='CT à Transf'!$K$16,"Oui",""),"") | E3: =IF(E2="Oui",IF(E5='CT à Transf'!$K$16,"Oui",""),"") | F3: =IF(F2="Oui",IF(F5='CT à Transf'!$K$16,"Oui",""),"") | G3: =IF(G2="Oui",IF(G5='CT à Transf'!$K$16,"Oui",""),"") | H3: =IF(H2="Oui",IF(H5='CT à Transf'!$K$16,"Oui",""),"") | I3: =IF(I2="Oui",IF(I5='CT à Transf'!$K$16,"Oui",""),"") | J3: =IF(J2="Oui",IF(J5='CT à Transf'!$K$16,"Oui",""),"") | ... OG3: =IF(OG2="Oui",IF(OG5='CT à Transf'!$K$16,"Oui",""),"")
B4: Compagnie | C4: UMR | D4: UMR | E4: UMR | F4: UMR | G4: UMR | H4: UFF | I4: UFF | J4: UFF | K4: UFF | L4: UFF | M4: SWISSLIFE | N4: SWISSLIFE | O4: SWISSLIFE | P4: SWISSLIFE | Q4: SWISSLIFE | R4: SWISSLIFE | S4: SWISSLIFE | T4: SWISSLIFE | U4: SWISSLIFE | V4: SWISSLIFE | W4: SWISSLIFE | X4: SWISSLIFE | Y4: SWISSLIFE | Z4: SWISSLIFE | AA4: SWISSLIFE | AB4: SOCIETE_GENERALE | AC4: SOCIETE_GENERALE | AD4: SOCIETE_GENERALE | AE4: SOCIETE_GENERALE | AF4: SOCIETE_GENERALE | AG4: SMA | AH4: PRO_BTP | AI4: PRO_BTP | AJ4: PRO_BTP | AK4: PRIMONIAL | AL4: PRIMONIAL | AM4: PRIMONIAL | AN4: PREVOIR | AO4: PREVOIR | AP4: PREVOIR | AQ4: PREFON | AR4: PREFON | AS4: ORADEA | AT4: ORADEA | AU4: NORTIA | AV4: NORTIA | AW4: NORTIA | AX4: NORTIA | AY4: NORTIA | AZ4: MNRA | BA4: MMA | BB4: MMA | BC4: MMA | BD4: MMA | BE4: MMA | BF4: MMA | BG4: MMA | BH4: MMA | BI4: MMA | BJ4: MMA | BK4: MMA | BL4: MMA | BM4: MMA | BN4: MMA | BO4: MMA | BP4: MEDICIS | BQ4: MEDICIS | BR4: MEDICIS | BS4: MEDICIS | BT4: MEDICIS | BU4: MATMUT | BV4: MAPA | BW4: MAPA | BX4: MALAKOFF_HUMANIS | BY4: MALAKOFF_HUMANIS | BZ4: MAIF | CA4: MAIF | CB4: MACSF | CC4: MACSF | CD4: MACSF | CE4: MACIF | CF4: MACIF | CG4: MACIF | CH4: MACIF | CI4: MACIF | CJ4: MACIF | CK4: MAAF | CL4: MAAF | CM4: MAAF | CN4: MAAF | CO4: MAAF | CP4: MAAF | CQ4: MAAF | CR4: LPA | CS4: LCL | CT4: LCL | CU4: LCL | CV4: LCL | CW4: LCL | CX4: LCL | CY4: LCL | CZ4: LCL | DA4: LA_MEDICALE | DB4: LA_MEDICALE | DC4: LA_MEDICALE | DD4: LA_MEDICALE | DE4: LA_MEDICALE | DF4: LA_BANQUE_POSTALE | DG4: LA_BANQUE_POSTALE | DH4: LA_BANQUE_POSTALE | DI4: LA_BANQUE_POSTALE | DJ4: LA_BANQUE_POSTALE | DK4: HSBC | DL4: HSBC | DM4: HSBC | DN4: HSBC | DO4: HSBC | DP4: HARMONIE_MUTUELLE | DQ4: HARMONIE_MUTUELLE | DR4: GROUPAMA | DS4: GROUPAMA | DT4: GROUPAMA | DU4: GROUPAMA | DV4: GROUPAMA | DW4: GROUPAMA | DX4: GROUPAMA | DY4: GROUPAMA | DZ4: GROUPAMA | EA4: GROUPAMA | EB4: GO_EPARGNE | EC4: GENERALI | ED4: GENERALI | EE4: GENERALI | EF4: GENERALI | EG4: GENERALI | EH4: GENERALI | EI4: GENERALI | EJ4: GENERALI | EK4: GENERALI | EL4: GENERALI | EM4: GENERALI | EN4: GENERALI | EO4: GENERALI | EP4: GENERALI | EQ4: GENERALI | ER4: GENERALI | ES4: GENERALI | ET4: GENERALI | EU4: GENERALI | EV4: GENERALI | EW4: GENERALI | EX4: GENERALI | EY4: GENERALI | EZ4: GENERALI | FA4: GENERALI | FB4: GENERALI | FC4: GENERALI | FD4: GENERALI | FE4: GENERALI | FF4: GENERALI | FG4: GENERALI | FH4: GENERALI | FI4: GENERALI | FJ4: GENERALI | FK4: GARANCE | FL4: GARANCE | FM4: GARANCE | FN4: GAN | FO4: GAN | FP4: GAN | FQ4: GAN | FR4: GAN | FS4: GAN | FT4: GAN | FU4: GAN | FV4: GAN | FW4: GAN | FX4: GAN | FY4: GAN | FZ4: GAN | GA4: GAN | GB4: GAN | GC4: GAN | GD4: GAN | GE4: GAN | GF4: GAN | GG4: GAN | GH4: GAN | GI4: GAN | GJ4: GAN | GK4: GAN | GL4: GAN | GM4: GAN | GN4: ERES | GO4: ERES | GP4: ERES | GQ4: ERES | GR4: ERES | GS4: ERES | GT4: ERES | GU4: EPSOR | GV4: EPSENS | GW4: CREDIT_MUTUEL | GX4: CREDIT_MUTUEL | GY4: CREDIT_MUTUEL | GZ4: CREDIT_MUTUEL | HA4: CREDIT_MUTUEL | HB4: CREDIT_MUTUEL | HC4: CREDIT_MUTUEL | HD4: CREDIT_MUTUEL | HE4: CREDIT_MUTUEL | HF4: CREDIT_MUTUEL | HG4: CREDIT_MUTUEL | HH4: CREDIT_MUTUEL | HI4: CREDIT_MUTUEL | HJ4: CREDIT_MUTUEL | HK4: CREDIT_MUTUEL | HL4: CREDIT_MUTUEL | HM4: CREDIT_MUTUEL | HN4: CREDIT_MUTUEL | HO4: CREDIT_MUTUEL | HP4: CREDIT_MUTUEL | HQ4: CREDIT_MUTUEL | HR4: CREDIT_MUTUEL | HS4: CREDIT_MUTUEL | HT4: CREDIT_MUTUEL | HU4: CREDIT_MUTUEL | HV4: CREDIT_MUTUEL | HW4: CREDIT_DU_NORD | HX4: CREDIT_DU_NORD | HY4: CREDIT_DU_NORD | HZ4: CREDIT_AGRICOLE | IA4: CREDIT_AGRICOLE | IB4: CREDIT_AGRICOLE | IC4: CREDIT_AGRICOLE | ID4: CREDIT_AGRICOLE | IE4: CREDIT_AGRICOLE | IF4: CREDIT_AGRICOLE | IG4: CREDIT_AGRICOLE | IH4: CREDIT_AGRICOLE | II4: CREDIT_AGRICOLE | IJ4: CREDIT_AGRICOLE | IK4: CREDIT_AGRICOLE | IL4: CREDIT_AGRICOLE | IM4: CREDIT_AGRICOLE | IN4: CREDIT_AGRICOLE | IO4: CREDIT_AGRICOLE | IP4: CARDIF | IQ4: CARDIF | IR4: CARDIF | IS4: CARDIF | IT4: CARDIF | IU4: CARDIF | IV4: CARDIF | IW4: CARDIF | IX4: CAISSE_D_EPARGNE | IY4: CAISSE_D_EPARGNE | IZ4: CAISSE_D_EPARGNE | JA4: CAISSE_D_EPARGNE | JB4: CAISSE_D_EPARGNE | JC4: CAISSE_D_EPARGNE | JD4: CAISSE_D_EPARGNE | JE4: BNP | JF4: BNP | JG4: BNP | JH4: BNP | JI4: BNP | JJ4: BNP | JK4: BNP | JL4: BNP | JM4: BNP | JN4: BNP | JO4: BNP | JP4: BNP | JQ4: BANQUE_POPULAIRE | JR4: BANQUE_POPULAIRE | JS4: BANQUE_POPULAIRE | JT4: BANQUE_POPULAIRE | JU4: BANQUE_POPULAIRE | JV4: BANQUE_POPULAIRE | JW4: BANQUE_POPULAIRE | JX4: BANQUE_POPULAIRE | JY4: BANQUE_POPULAIRE | JZ4: BANQUE_POPULAIRE | KA4: BANQUE_POPULAIRE | KB4: BANQUE_POPULAIRE | KC4: BANQUE_POPULAIRE | KD4: BANQUE_POPULAIRE | KE4: BANQUE_POPULAIRE | KF4: BANQUE_POPULAIRE | KG4: AXA | KH4: AXA | KI4: AXA | KJ4: AXA | KK4: AXA | KL4: AXA | KM4: AXA | KN4: AXA | KO4: AXA | KP4: AXA | KQ4: AXA | KR4: AXA | KS4: AXA | KT4: AXA | KU4: AXA | KV4: AXA | KW4: AXA | KX4: AXA | KY4: AXA | KZ4: AXA | LA4: AXA | LB4: AXA | LC4: AXA | LD4: AXA | LE4: AXA | LF4: AREAS | LG4: AREAS | LH4: AREAS | LI4: AREAS | LJ4: AREAS | LK4: AREAS | LL4: APRIL | LM4: APRIL | LN4: APRIL | LO4: APRIL | LP4: APRIL | LQ4: APRIL | LR4: APRIL | LS4: APICIL | LT4: APICIL | LU4: APICIL | LV4: APICIL | LW4: APICIL | LX4: APICIL | LY4: APICIL | LZ4: APICIL | MA4: APICIL | MB4: APICIL | MC4: ALPTIS | MD4: ALLIANZ | ME4: ALLIANZ | MF4: ALLIANZ | MG4: ALLIANZ | MH4: ALLIANZ | MI4: ALLIANZ | MJ4: ALLIANZ | MK4: ALLIANZ | ML4: ALLIANZ | MM4: ALLIANZ | MN4: ALLIANZ | MO4: ALLIANZ | MP4: ALLIANZ | MQ4: ALLIANZ | MR4: ALLIANZ | MS4: ALLIANZ | MT4: ALLIANZ | MU4: AGIPI | MV4: AGIPI | MW4: AGIPI | MX4: AGEAS | MY4: AG2R_LA_MONDIALE | MZ4: AG2R_LA_MONDIALE | NA4: AG2R_LA_MONDIALE | NB4: AG2R_LA_MONDIALE | NC4: AG2R_LA_MONDIALE | ND4: AG2R_LA_MONDIALE | NE4: AG2R_LA_MONDIALE | NF4: AG2R_LA_MONDIALE | NG4: AG2R_LA_MONDIALE | NH4: AG2R_LA_MONDIALE | NI4: AG2R_LA_MONDIALE | NJ4: AG2R_LA_MONDIALE | NK4: AG2R_LA_MONDIALE | NL4: AG2R_LA_MONDIALE | NM4: AG2R_LA_MONDIALE | NN4: AG2R_LA_MONDIALE | NO4: AG2R_LA_MONDIALE | NP4: AG2R_LA_MONDIALE | NQ4: AG2R_LA_MONDIALE | NR4: AFER | NS4: AFER | NT4: AFER | NU4: ABEILLE | NV4: ABEILLE | NW4: ABEILLE | NX4: ABEILLE | NY4: ABEILLE | NZ4: ABEILLE | OA4: ABEILLE | OB4: ABEILLE | OC4: ABEILLE | OD4: ABEILLE | OE4: ABEILLE | OF4: ABEILLE | OG4: ABEILLE
B5: Contrat | C5: ART83- COREM CO | D5: PERIN- ORIGINEO BY CRYSTAL | E5: PERIN-COREM | F5: PERIN- PERIVIE | G5: PERIN- PLACEMENT-DIRECT RETRAITE ISR | H5: ART83- UFF 83 | I5: ART83- UFF RETRAITE ENTREPRISE | J5: ART83- UFF RETRAITE ENTREPRISE PLUS | K5: MADELIN- UFF RETRAITE MADELIN | L5: MADELIN-UFF RETRAITE INDEPENDANT | M5: ART83- GARANTIE RETRAITE ENTREPRISE 2000 | N5: ART83- GARANTIE RETRAITE ENTREPRISES | O5: ART83- SWISSLIFE PLAN D'EPARGNE RETRAITE ENTREPRISES | P5: ART83- SWISSLIFE PREPARATION RETRAITE | Q5: ART83- SWISSLIFE RETRAITE ARTICLE 83 | R5: ART83- SWISSLIFE RETRAITE ENTREPRISES | S5: PERP- SWISSLIFE PERP | T5: MADELIN- GARANTIE RETRAITE INDEPENDANTS | U5: MADELIN- SWISSLIFE RETRAITE AGRICOLE | V5: MADELIN- SWISSLIFE RETRAITE INDEPENDANTS | W5: MADELIN- SWISSLIFE RETRAITE MADELIN | X5: MADELIN- SWISSLIFE RETRAITE SELECTION | Y5: PERIN- PER EXPERT | Z5: PERIN- SWISSLIFE PER INDIVIDUEL | AA5: PERCO- SWISSLIFE PER COLLECTIF | AB5: ART83- PALISSANDRE ENTREPRISES | AC5: PERP- PERP EPICEA | AD5: MADELIN- PALISSANDRE | AE5: PERIN- PER ACACIA | AF5: PERCO- EPARGNE SALARIALE ARCANCIA V | AG5: PERIN- PER INDIVIDUEL SMAVIE | AH5: PERP- PERP CONFIANCE BTP | AI5: MADELIN- RETRAITE SUPPLEMENTAIRE DES ARTISANS | AJ5: PERIN- PER INDIVIDUEL CONFIANCE | AK5: MADELIN- GESTION PRIVEE PROMADELIN | AL5: MADELIN- CARDIF RETRAITE PROFESSIONNELS ( PATRIMOINE MANAGEMENT ET ASSOCIES) | AM5: PERIN- PRIMOPER | AN5: PERP- PERP LIGNAGE | AO5: MADELIN- PREVOIR PRO RETRAITE | AP5: PERIN- SOLUTION PLAN EPARGNE RETRAITE | AQ5: PERP- PREFON-RETRAITE | AR5: PERIN- PER PREFON RETRAITE | AS5: PERP- PERP LIGNAGE | AT5: PERIN- PER LIGNAGE | AU5: PERP- COMPLEMENT EPARGNE RETRAITE | AV5: MADELIN- QUADRANCE | AW5: PERIN- PER PANTHEA | AX5: PERIN- PER ENEDIA | AY5: PERIN- PER PRIVATE | AZ5: MADELIN- ARIA GROUPE / ARIA EVOLUTION | BA5: ART83- MMA RETRAITE 83 (ancien MDM RETRAITE 83) | BB5: PERP- MULTISUPPORTS PERP | BC5: MADELIN- MMA MULTISUPPORTS RETRAITE INDEPENDANTS | BD5: MADELIN- MMA RETRAITE PRO | BE5: MADELIN- MMA SOLUTIONS RETRAITE AGRI | BF5: MADELIN- MMA SOLUTIONS RETRAITE AGRI + | BG5: MADELIN- MMA SOLUTIONS RETRAITE PRO | BH5: MADELIN- MMA SOLUTIONS RETRAITE PRO + | BI5: MADELIN- MULTISTRATEGIES RETRAITE AGRI | BJ5: MADELIN- MULTISTRATEGIES RETRAITE PRO | BK5: MADELIN- PLAN MDM RETRAITE INDEPENDANTS | BL5: MADELIN- SIGNATURE RETRAITE AGRI | BM5: MADELIN- SIGNATURE RETRAITE PRO | BN5: PERIN- SIGNATURE PER | BO5: PERIN- MMA PER AVENIR | BP5: PERP- PERP MEDICIS | BQ5: MADELIN- MEDICIS RETRAITE MADELIN | BR5: PERIN- PER MEDICIS MULTISUPPORT | BS5: PERIN- PER MEDICIS PATRIMONIAL | BT5: PERIN- PER MEDICIS PRODUIT EN POINTS | BU5: PERIN- COMPLICE RETRAITE | BV5: MADELIN- ACTIFONDS RETRAITE | BW5: MADELIN- MEDICIS RETRAITE MADELIN | BX5: MADELIN- RADIANCE HUMANIS RETRAITE PRO | BY5: PERIN- PER OBLIGATOIRE PATRIMONIAL | BZ5: PERP- PERP MAIF | CA5: PERIN- PER RESPONSABLE ET SOLIDAIRE | CB5: PERP- PERP'S (Plan d'Epargne Retraite des Professions de Santé) | CC5: MADELIN- RFPA RETRAITE MADELIN (RES FONDS DE PENSION AVENIR) | CD5: PERIN- RES RETRAITE | CE5: ART83- ACTIPLUS RETRAITE ENTREPRISE | CF5: PERP- MULTI PERP | CG5: MADELIN- MEDICIS RETRAITE MADELIN | CH5: MADELIN- ACTIFONDS RETRAITE | CI5: MADELIN- ACTIPLUS RETRAITE | CJ5: PERIN- MULTI HORIZON RETRAITE - MUTAVIE | CK5: ART83- MAAF 83 | CL5: PERP- WINNEO RETRAITE | CM5: MADELIN- DYNALTO PRO | CN5: MADELIN- MAAF 41 | CO5: MADELIN- WINALTO PRO | CP5: MADELIN- WINNEO PRO | CQ5: PERIN- PER WINALTO RETRAITE | CR5: MADELIN- AVOCAPI | CS5: ART83- LCL RETRAITE 83 | CT5: ART83- LCL RETRAITE MAITRISEE | CU5: ART83- LCL RETRAITE VOLONTAIRE | CV5: PERP- VELOURS | CW5: MADELIN- PRO LIGNES DE VIE | CX5: PERIN- LCL RETRAITE PER | CY5: PERCO- ALIM 'ÉPARGNE | CZ5: PERCO- ES - PL | DA5: MADELIN- MEDICALE HORIZON MADELIN 2 | DB5: MADELIN- MEDICALE RETRAITE | DC5: MADELIN- MEDICALE HORIZON MADELIN | DD5: MADELIN- LA MEDICALE SERENITE | DE5: PERIN- LA MEDICALE PERENNITE | DF5: ART83- PERE MULTISUPPORTS | DG5: ART83- RETRAITE 83 | DH5: PERP- SOLESIO PERP EVOLUTION | DI5: PERP- SOLESIO PERP HORIZON | DJ5: PERIN- CACHEMIRE PER | DK5: ART83- ELYS RETRAITE 83 | DL5: ART83- HSBC RETRAITE 83 | DM5: PERP- PLAN ELYSEES RETRAITE PATRIMOINE | DN5: MADELIN- ELYSEES RETRAITE INDEPENDANTS | DO5: PERIN- HSBC STRATEGIE RETRAITE | DP5: PERIN- PER INDIVIDUEL SOLUTION GROUPE VYV | DQ5: PERIN- PER ENTREPRISE OBLIGATOIRE | DR5: ART83- GROUPAMA DIMENSION RETRAITE ENTREPRISES | DS5: ART83- GROUPAMA RETRAITE PERFORMANCE | DT5: ART83- SYNERGIE RETRAITE ENTREPRISE | DU5: ART83- SYNERGIE RETRAITE LIBERTE | DV5: ART83- SYNERGIE RETRAITE SERENITE | DW5: PERP- GROUPAMA RETRAITE ACTIVE | DX5: MADELIN- AGRI RETRAITE ACTIVE | DY5: MADELIN- ENERGIE RETRAITE ACTIVE | DZ5: MADELIN- GROUPAMA AGRI-RETRAITE POINTS | EA5: PERIN- GROUPAMA NOUVELLE VIE | EB5: PERCO- JUST GO | EC5: ART83- FRANCE PROFIL RETRAITE | ED5: ART83- FRANCE PROFIL RETRAITE MULTISUPPORTS 2008 | EE5: ART83- LA RETRAITE 15 | EF5: ART83- LA RETRAITE 94 - ARTICLE 83 | EG5: ART83- LEADER SUPPLEMENT RETRAITE | EH5: ART83- SCENARIO RETRAITE | EI5: ART83- SERENIDAD RETRAITE ARTICLE 83 | EJ5: ART83- XAELIDIA RETRAITE ENTREPRISE | EK5: PERP- ANTHOLOGIE | EL5: PERP- GPA PERP | EM5: PERP- GRAFIC | EN5: PERP- SERENIDAD PERP | EO5: PERP- LE PERP GENERALI PATRIMOINE | EP5: MADELIN- ESPACE INVEST MADELIN | EQ5: MADELIN- GPA RETRAITE PRO | ER5: MADELIN- GPA RETRAITE PRO DUO | ES5: MADELIN- GPA RETRAITE PRO HORIZON | ET5: MADELIN- LEADER PROTECTION RETRAITE INDEPENDANTS | EU5: MADELIN- PRISM MULTISUPPORTS | EV5: MADELIN- SCENARIO RETRAITE - MADELIN | EW5: MADELIN- SERENIDAD RETRAITE MADELIN | EX5: MADELIN- XAELIDIA RETRAITE INDIVIDUELLE | EY5: MADELIN- La retraite 94 | EZ5: MADELIN- La retraite 08 | FA5: MADELIN- La retraite 08 - V2010 | FB5: MADELIN-La retraite 13 | FC5: MADELIN- La retraite 15 | FD5: PERIN- La retraite 20 | FE5: PERIN- PER Générali Patrimoine | FF5: PERCO- ESSENZIO | FG5: PERCO- ESSENZIO 2 | FH5: PERCO- ESSENZIO 3 PLUS | FI5: PERCO- GAELIA - PERCOI | FJ5: PERCO- GENERALI EPARGNE SALARIALE | FK5: PERP- GARANCE RETRAITE PERP | FL5: MADELIN- ARIA GROUPE / ARIA EVOLUTION | FM5: PERIN- GARANCE SÉRÉNITÉ | FN5: ART83- DIMENSION RETRAITE ACTIF | FO5: ART83- DIMENSION RETRAITE ENERGIE | FP5: ART83- DIMENSION RETRAITE ENTREPRISES | FQ5: ART83- EXCELLENCE RETRAITE ENTREPRISE | FR5: ART83- GALYA RETRAITE ENTREPRISE | FS5: ART83- GALYA RETRAITE GARANTIE | FT5: ART83- GAN RETRAITE ENTREPRISE | FU5: ART83- GAN RETRAITE PERFORMANCE ENTREPRISE TPE | FV5: ART83- GROUPAMA DIMENSION RETRAITE ENTREPRISES | FW5: ART83- RECORD-VERSION B | FX5: ART83- GAN RETRAITE PERFORMANCE ENTREPRISE | FY5: PERP- GAN INITIATIVE RETRAITE | FZ5: PERP- GAN RETRAITE GARANTIE | GA5: PERP- GAN RETRAITE PERP | GB5: MADELIN- DIMENSION AVENIR AGRICULTEUR II | GC5: MADELIN- DIMENSION AVENIR PROFESSIONNELS II | GD5: MADELIN- GALYA RETRAITE MADELIN | GE5: MADELIN- GAN PATRIMOINE INDEPENDANTS | GF5: MADELIN- GAN PATRIMOINE MADELIN RETRAITE | GG5: MADELIN- GAN PERFORMANCE RETRAITE PRO | GH5: MADELIN- GAN PREVOYANCE RETRAITE INDEPENDANT | GI5: MADELIN- GAN PREVOYANCE RETRAITE MADELIN | GJ5: MADELIN- GAN RETRAITE INDEPENDANT | GK5: PERIN- GAN ASSURANCE NOUVELLE VIE | GL5: PERIN- GAN PATRIMOINE NOUVELLE VIE | GM5: PERIN- GAN PREVOYANCE NOUVELLE VIE | GN5: ART83- ERES RETRAITE 83 | GO5: PERP- LE PERP ERES 163X | GP5: PERIN- LE PER | GQ5: PERIN- LE PER ERES BY SPIRICA | GR5: PERCO- ERES SELECTION 2 - PEI / PERCOI | GS5: PERCO- ERES SELECTION 7 | GT5: PERCO- PEI PERCOI ERES SELECTION 4 | GU5: PERCO- PEI-PERCOI EPSOR - EPSOR | GV5: PERCO- OFFRE SUR MESURE EPSENS | GW5: ART83- RETRAITE ENTREPRISE MONOSUPPORT | GX5: ART83- RETRAITE ENTREPRISE MULTISUPPORT | GY5: ART83- RETRAITE ENTREPRISE P.E.R.E. | GZ5: ART83- RETRAITE ENTREPRISE UC P.E.R.E. | HA5: ART83- RETRAITE SUPPLEMENTAIRE 83 | HB5: ART83- RETRAITE SUPPLEMENTAIRE 83 EN EUROS (ex Prévi Retraite Entreprises) | HC5: ART83- TRIADYS RETRAITE 83 | HD5: ART83- GAN RETRAITE PERFORMANCE ENTREPRISE | HE5: PERP- LE PERP INDEPENDANT | HF5: PERP- PLAN RETRAITE REVENUS | HG5: PERP- MYRIALIS PERP | HH5: PERP- PREVI - HORIZONS | HI5: MADELIN- PERENIAL PENSION HORIZONS | HJ5: MADELIN- PERENIAL PENSION RETRAITE | HK5: MADELIN- PLAN ASSUR HORIZONS PRO | HL5: MADELIN- PLAN ASSURANCE VIE PRO | HM5: MADELIN- PREVI-RETRAITE INDEPENDANTS | HN5: MADELIN- PREVI-RETRAITE INDEPENDANTS AGRI | HO5: MADELIN- PREVI-RETRAITE INDEPENDANTS PROS | HP5: PERIN- PER ASSURANCE RETRAITE | HQ5: PERIN- PER ASSURANCE RETRAITE CORPORATE | HR5: PERIN- PER ASSURANCE RETRAITE ENTREPRISE | HS5: PERIN- PROJECTION RETRAITE | HT5: PERIN- PERTINENCE RETRAITE | HU5: PERIN- SURAVENIR PER | HV5: PERCO- ACTIVEPARGNE RETRAITE - PERCOI | HW5: PERP- ANTARIUS PERP | HX5: MADELIN- ANTARIUS RETRAITE « MADELIN » | HY5: PERIN- ANTARIUS PERin | HZ5: ART83- EXTENSION RETRAITE MAITRISEE | IA5: ART83- EXTENSION RETRAITE SUPPLEMENTAIRE EURO | IB5: ART83- EXTENSION RETRAITE SUPPLÉMENTAIRE MULTISUPPORT | IC5: ART83- EXTENSION RETRAITE VOLONTAIRE | ID5: PERP- PLAN VERT AVENIR | IE5: PERP- PLAN VERT VITALITE | IF5: MADELIN- ACCORDANCE | IG5: MADELIN- ACCORDANCE MULTISUPPORTS | IH5: MADELIN- PREDIAGRI POINTS RETRAITE | II5: MADELIN- PREDIAGRI RETRAITE | IJ5: PERIN- EXTENSION RETRAITE MAÎTRISÉE PACTE 2019 ERM PACTE 2019 | IK5: PERIN- PER ASSURANCE PERSPECTIVE | IL5: PERCO- ALIM 'ÉPARGNE | IM5: PERCO- FAST'AMUNDI | IN5: PERCO- L'EPARGNE SALARIALE | IO5: PERCO- PER CONVERGENCE | IP5: ART83- CARDIF RETRAITE 83 | IQ5: PERP- CARDIF MULTIPLUS PERP | IR5: MADELIN- CARDIF AMBITION RETRAITE PROFESSIONNELS | IS5: MADELIN- CARDIF RETRAITE MADELIN | IT5: MADELIN- CARDIF RETRAITE PROFESSIONNELS | IU5: MADELIN- INITIATIVE RETRAITE | IV5: PERIN- CARDIF ELITE RETRAITE | IW5: PERIN- CARDIF ESSENTIEL RETRAITE | IX5: PERP- ASSYLIO | IY5: PERP- PERP CAISSE D'EPARGNE | IZ5: PERP- SOLUTION PERP | JA5: MADELIN- ECUREUIL RETRAITE PRO | JB5: PERIN- MILLEVIE PER | JC5: PERIN- PER CE | JD5: PERCO- BOX OFFICE PERCOI | JE5: ART83- PARTENAIRE PER ENTREPRISES | JF5: ART83- PREFERENCE PER ENTREPRISES | JG5: ART83- PRÉFÉRENCE RETRAITE | JH5: PERP- PLAN D'EPARGNE RETRAITE DES PARTICULIERS (PERP) | JI5: MADELIN- NATIO VIE MULTIHORIZONS PROFESSIONNEL | JJ5: MADELIN- PLAN D'EPARGNE RETRAITE LOI MADELIN | JK5: PERIN- BNP PARIBAS MULTIPLACEMENTS PER | JL5: PERIN- PRÉFÉRENCE PER OBLIGATOIRE | JM5: PERIN- BNP PARIBAS MULTIPLACEMENTS PRIVILÈGE PER | JN5: PERCO- AMPLISSIM EPARGNE SALARIALE | JO5: PERCO- PARTENAIRE EPARGNE SALARIALE | JP5: PERCO- PERCOI EFFIGIE | JQ5: ART83- CAPI RESSOURCES | JR5: ART83- RESSOURCES SÉLECTION VIE | JS5: ART83- RESSOURCES SELECTION VIE II | JT5: PERP- PER BP | JU5: PERP- PERP CM | JV5: PERP- PERP DUETTO RETRAITE | JW5: PERP- SOLUTION PERP | JX5: MADELIN- FRUCTI - AGRI | JY5: MADELIN- FRUCTI-PROFESSIONNEL | JZ5: MADELIN- PREPAR PRO | KA5: MADELIN- PREPAR'SERENITE - GARANTIE RETRAITE | KB5: PERIN- PERI BRED | KC5: PERIN- PLAN EPARGNE RETRAITE | KD5: PERCO-ES - PL | KE5: PERCO- FRUCTI DUO - FRUCTI EPARGNE PLUS | KF5: PERCO- FRUCTI OPTIMUM | KG5: ART83- 4G STRATEGIE RETRAITE | KH5: ART83- QUANTILE RETRAITE SECURITE | KI5: ART83- RETRAITE 4 G | KJ5: ART83- RETRAITE ENTREPRISE A ADHÉSION OBLIGATOIRE | KK5: ART83- RETRAITE ENTREPRISE GESTION PROGRAMMEE | KL5: ART83- RETRAITE ENTREPRISE PÈRE | KM5: ART83- SOLERE 83 | KN5: PERP- PERP CONFORT | KO5: PERP- PERP REFERENCE | KP5: MADELIN- AGRISSIAL | KQ5: MADELIN- COLIADE RETRAITE INDEPENDANT | KR5: MADELIN- CORALIS INDEPENDANTS | KS5: MADELIN- CORETIS | KT5: MADELIN- GERANT MAJORITAIRE RETRAITE | KU5: MADELIN- NOVIAL AVENIR | KV5: MADELIN- ORIAL | KW5: MADELIN- PLANISSIM | KX5: MADELIN- REGULARITE RETRAITE PRO / EURACTIEL DES PROFESSIONNELS | KY5: MADELIN- RETRAITE DES PROFESSIONNELS - AGRICOLES | KZ5: MADELIN- RETRAITE DES PROFESSIONNELS - NON AGRICOLES | LA5: PERIN- AXA MA RETRAITE | LB5: PERIN- PER AMADEO | LC5: PERIN- PER CORALIS | LD5: PERCO- EPARGNE SALARIALE PEI / PERCO-I | LE5: PERCO- PEE - PERCO AXA | LF5: ART83- RETRAITE COLLECTIVE ENTREPRISE | LG5: ART83- PERI | LH5: PERP- PERP MULTISUPPORT | LI5: MADELIN- ARELIA MULTISUPPORT | LJ5: MADELIN- ARELIA RETRAITE COMPLEMENTAIRE DES INDEPENDANTS | LK5: PERIN- PER INDIVIDUEL AREAS | LL5: ART83- AFFLUANCE RETRAITE ARTICLE 83 | LM5: ART83- APRIL RETRAITE ARTICLE 83 | LN5: PERP- APRIL PERP MULTISUPPORT | LO5: MADELIN- AFFLUANCE RETRAITE MADELIN | LP5: MADELIN- APRIL RETRAITE MADELIN | LQ5: MADELIN- CARDIF RETRAITE PROFESSIONNELS (APRIL) | LR5: MADELIN- RETRAITE MADELIN APRIL | LS5: ART83- APICIL CAP' XL (ancien Apicil Retraite entreprise) | LT5: ART83- APICIL CAP'XL & CO (ancien APICIL PERENNITE ENTREPRISE) | LU5: PERP- APICIL PERSPECTIVES GENERATION | LV5: PERP- PERSPECTIVE GENERATION PLUS | LW5: MADELIN- APICIL PROFORMANCE | LX5: MADELIN- APICIL PROFORMANCE PLUS | LY5: PERIN- APICIL AVENIR PER-OB | LZ5: PERIN- APICIL CONNECT PER | MA5: PERIN- INTENCIAL LIBERALYS RETRAITE | MB5: PERIN- CONCORDANCES PERIN | MC5: MADELIN- IMPERATIF RETRAITE MADELIN | MD5: ART83- AGF PLANEO 2 ENTREPRISE | ME5: ART83- AGF PLANEO 3 ENTREPRISE | MF5: ART83- AGF PLANEO 4 ENTREPRISE | MG5: ART83- AGF PLANEO EUROPEAN PENSION | MH5: ART83- AGF SOLEO RETRAITE | MI5: ART83- ALLIANZ PLANEO 5 ENTREPRISE | MJ5: ART83- ALLIANZ RENTEO | MK5: ART83- ALLIANZ RETRAITE ENTREPRISE | ML5: PERP- PERP ALLIANZ PLEINE RETRAITE | MM5: MADELIN- ALLIANZ ITINERAIRES RETRAITE MADELIN / AGRICOLE | MN5: MADELIN- ALLIANZ RETRAITE TNS / AGRI | MO5: MADELIN- OPTI'RETRAITE | MP5: MADELIN- PLATINIA RETRAITE MADELIN | MQ5: MADELIN- TELLUS AVENIR TNS / AGRI | MR5: MADELIN- TELLUS TNS | MS5: PERIN- ALLIANZ PER ENTREPRISE | MT5: PERIN- ALLIANZ PER HORIZON | MU5: PERP- PAIR | MV5: MADELIN- FAR | MW5: PERIN- FAR PER | MX5: PERIN- PER ZEN | MY5: ART83- EQUATION 83 MULTISUPPORTS | MZ5: ART83- MONDIALE PERSPECTIVES ENTREPRISE | NA5: ART83- MONDIALE RETRAITE PLUS | NB5: ART83- PER ENTREPRISES | NC5: ART83- RETRAITE SUPPLEMENTAIRE | ND5: ART83- RETRAITE SUPPLÉMENTAIRE II | NE5: ART83- RETRAITE SUPPLEMENTAIRE LIBRE | NF5: ART83- RETRAITE SUPPLEMENTAIRE LIBRE II | NG5: PERP- COMPLEMENT EPARGNE RETRAITE (EX -MONDIALE STRATEGIE RETRAITE) | NH5: PERP- MONDIALE SOLUTIONS RETRAITE | NI5: MADELIN- MONDIALE PRIVILEGE ACTIONS | NJ5: MADELIN- MONDIALE RETRAITE PROFESSIONNELS | NK5: MADELIN- RETRAITE AGRICOLE | NL5: MADELIN- RETRAITE PROFESSIONNELS | NM5: PERIN- AMBITION RETRAITE ENTREPRISE | NN5: PERIN- AMBITION RETRAITE INDIVIDUELLE | NO5: PERIN- AMBITION RETRAITE PRO | NP5: PERIN- EXCELLIE RETRAITE | NQ5: PERIN- UNIVERS RETRAITE ENTREPRISE LIBRE | NR5: ART83- CONTRAT COLLECTIF DE RETRAITE SUPPLÉMENTAIRE MULTISUPPORT AFER | NS5: ART83- RETRAITE SUPPLEMENTAIRE AFER | NT5: PERIN- AFER RETRAITE INDIVIDUELLE | NU5: ART83- ABEILLE RETRAITE ENTREPRISE ARTICLE 83 | NV5: ART83- NORWICH STRATEGIE RETRAITE - Article 83 | NW5: PERP- ABEILLE RETRAITE PERP | NX5: MADELIN- ABEILLE RETRAITE MADELIN | NY5: MADELIN- ABEILLE RETRAITE PLURIELLE MADELIN | NZ5: MADELIN- ATTITUDE STRATEGIE RETRAITE "LOI MADELIN" | OA5: MADELIN- ATTITUDE STRATEGIE RETRAITE AGRICOLE | OB5: MADELIN- NORWICH HORIZON LOI MADELIN | OC5: MADELIN- NORWICH STRATEGIE RETRAITE LOI MADELIN | OD5: MADELIN- NORWICH UNION OPTION AVENIR LOI MADELIN | OE5: MADELIN- VICTOIRE INVESTISSEMENT RETRAITE 2 | OF5: PERIN- ABEILLE RETRAITE PLURIELLE | OG5: PERIN- ABEILLE RETRAITE PLURIELLE ENTREPRISE
B6: Versement annuel
B7: Date d’effet
B8: Date de commercialisation du contrat par la cie | C8: De 2006 à NC | D8: De 2021 à … | E8: De 2021 à … | F8: De 2020 à … | G8: De 2023 à … | H8: De NC à 2005 | I8: De 2005 à 2013 | J8: De 2013 à NC | K8: De 2007 à NC | L8: De NC à 2007 | M8: De 2000 à 2002 | N8: De 1987 à 2008 | O8: De 2016 à NC | P8: De 2011 à 2013 | Q8: De 2013 à NC | R8: De 2009 à 2013 | S8: De 2004 à NC | T8: De 1995 à 2006 | U8: De 2006 à 2009 | V8: De 2006 à 2009 | W8: De 2013 à NC | X8: De 2006 à 2013 | Y8: De 2020 à … | Z8: De 2019 à … | AA8: De 2020 à … | AB8: De 2001 à NC | AC8: De 2004 à NC | AD8: De 1999 à NC | AE8: De 2019 à … | AF8: De 2059 à … | AG8: De 2020 à … | AH8: De 2005 à NC | AI8: De 1994 à NC | AJ8: De 2020 à … | AK8: De 2020 à NC | AL8: De 2009 à 2011 | AM8: De 2020 à … | AN8: De 2004 à NC | AO8: De 2006 à NC | AP8: De 2020 à … | AQ8: De 1968 à … | AR8: De 2019 à … | AS8: De 2004 à NC | AT8: De 2019 à … | AU8: De 2004 à NC | AV8: De 1998 à NC | AW8: De 2021 à … | AX8: De 2021 à … | AY8: De 2021 à … | AZ8: De 1994 à … | BA8: De 1994 à … | BB8: De 1994 à NC | BC8: De 2001 à NC | BD8: De 2001 à 2012 | BE8: De 2012 à 2015 | BF8: De 2015 à NC | BG8: De 2012 à 2015 | BH8: De 2015 à NC | BI8: De 2004 à 2015 | BJ8: De 2004 à 2015 | BK8: De 1994 à NC | BL8: De 2015 à NC | BM8: De 2015 à NC | BN8: De 2020 à … | BO8: De 2020 à … | BP8: De 2005 à NC | BQ8: De 2004 à NC | BR8: De 2023 à … | BS8: De 2023 à … | BT8: De 2020 à … | BU8: De 2021 à … | BV8: De 2002 à NC | BW8: De 2004 à NC | BX8: De 2013 à NC | BY8: NC | BZ8: De 2004 à NC | CA8: De 2020 à … | CG8: De 2004 à NC | CH8: De 2002 à NC | DA8: De 2003 à NC | DB8: De 1999 à 2002 | DC8: De 2000 à NC | DD8: De 2012 à NC | DE8: De 2020 à … | DW8: De 2004 à NC | DY8: De 2002 à NC | EA8: De 2019 à .. | EB8: NC | EC8: NC | ED8: De 2004 à NC | EE8: De 2008 à NC | EF8: De 1980 à 2008 | EG8: De 1993 à NC | EH8: De 2001 à NC | EI8: De 2005 à NC | EJ8: De NC à NC | EK8: De 2004 à NC | EL8: De NC à NC | EM8: De 2004 à NC | EN8: De 2004 à 2012 | EO8: De 2015 à NC | EP8: De 2007 à 2011 | EQ8: De 2005 à NC | ER8: De 1994 à NC | ES8: De 2002 à NC | ET8: De 1994 à NC | EU8: 1999-2009 | EV8: De 2001 à 2008 | EW8: De 2005 à NC | EX8: De 1999 à 2008 | EY8: De 1986 à 2008 | EZ8: De 2008 à 2010 | FA8: Du 01/07/10 à 2013 | FB8: Du 01/01/13 à 2015 | FC8: Du 01/01/2015 à NC | FD8: De 2019 à … | FE8: De 2019 à … | FY8: De 2004 à 2014 | GA8: De 2004 à 2011 | GC8: De 1998 à 2014 | GD8: De 2009 à NC | GJ8: De 2000 à 2007 | GK8: De 2019 à .. | HH8: De 2004 à NC | HT8: De 2019 à … | IG8: De 2007 à NC | II8: De 1997 à NC | IK8: De 2019 à … | IQ8: De 2004 à NC | IR8: De 2004 à 2007 | IS8: De 2011 à NC | IT8: De 2007 à 2011 | IU8: De 1995 à NC | IV8: De 2021 à … | IW8: De 2019 à 2022 | KN8: De 2004 à NC | KO8: De 2004 à NC | KR8: De 1998 à NC | KX8: De 2001 à NC | LA8: De 2019 à … | LC8: De 2021 à … | LQ8: De 2008 à 2011 | MA8: De 2019 à … | ML8: De 2004 à NC | MR8: De 1994 à 2005 | MT8: De 2020 à … | MU8: De 2004 à NC | MV8: De 1994 à NC | MW8: De 2019 à … | MX8: De 2019 à … | NA8: De 1990 à 1997 | NG8: De 2004 à NC | NI8: De 2000 à 2007 | NJ8: De 2007 à 2016 | NL8: De 2016 à NC | NN8: De 2020 à … | NO8: De 2019 à … | NP8: De 2020 à … | NV8: De 2002 à 2013 | NX8: De 2010 à 2017 | OF8: De 2019 à …
B9: Provision mathématique
B10: Dont intérets
B11: Nombre de fonds accessibles | C11: 1 | D11: 74 | E11: 1 | F11: 9 | G11: 99 | H11: 7 | I11: 9 | J11: 24 | K11: 22 | L11: 6 | M11: 1 | N11: 1 | O11: 564 | P11: 39 | Q11: 62 | R11: 24 | S11: 568 | T11: 1 | U11: 1 | V11: 1 | W11: 569 | X11: 48 | Y11: 727 | Z11: 2251 | AA11: 8 | AB11: 8 | AC11: 92 | AD11: 53 | AE11: 79 | AF11: 15 | AG11: 15 | AH11: 1 | AI11: 1 | AJ11: 9 | AK11: 140 | AL11: 262 | AM11: 225 | AN11: 281 | AO11: 1 | AP11: 16 | AQ11: 1 | AR11: 1 | AS11: 281 | AT11: 240 | AU11: 479 | AV11: 469 | AW11: 912 | AX11: 319 | AY11: 759 | AZ11: 1 | BA11: 1 | BB11: 59 | BC11: 13 | BD11: 32 | BE11: 35 | BF11: 36 | BG11: 35 | BH11: 36 | BI11: 83 | BJ11: 83 | BK11: 1 | BL11: 90 | BM11: 90 | BN11: 22 | BO11: 26 | BP11: 1 | BQ11: 1 | BR11: 9 | BS11: 15 | BT11: 1 | BU11: 48 | BV11: 7 | BW11: 1 | BX11: 5 | BY11: 23 | BZ11: 2 | CA11: 11 | CG11: 1 | CH11: 7 | DA11: 19 | DB11: 1 | DC11: 4 | DD11: 47 | DE11: 582 | DW11: 30 | DY11: 32 | EA11: 34 | EB11: 3 | EC11: 3 | ED11: 17 | EE11: 103 | EF11: 1 | EG11: 1 | EH11: 5 | EI11: 29 | EJ11: 16 | EK11: 118 | EL11: 5 | EM11: 1 | EN11: 15 | EO11: 473 | EP11: 154 | EQ11: 13 | ER11: 1 | ES11: 10 | ET11: 1 | EU11: 16 | EV11: 5 | EW11: 22 | EX11: 64 | EY11: 1 | EZ11: 191 | FA11: 191 | FB11: 191 | FC11: 104 | FD11: 104 | FE11: 329 | FY11: 1 | GA11: 1 | GC11: 1 | GD11: 46 | GJ11: 1 | GK11: 34 | HH11: 109 | HT11: 1260 | IG11: 26 | II11: 1 | IK11: 104 | IQ11: 252 | IR11: 245 | IS11: 612 | IT11: 262 | IU11: 30 | IV11: 2435 | IW11: 802 | KN11: 48 | KO11: 7 | KR11: 443 | KX11: 4 | LA11: 23 | LC11: NC | LQ11: 262 | MA11: 300 | ML11: 47 | MR11: 16 | MT11: 94 | MU11: 24 | MV11: 26 | MW11: 57 | MX11: 471 | NA11: 1 | NG11: 479 | NI11: 4 | NJ11: 12 | NL11: 19 | NN11: 18 | NO11: 18 | NP11: 180 | NV11: 44 | NX11: 50 | OF11: 153
B12: Répartition UC/€ | C12: - | E12: - | M12: - | N12: - | T12: - | U12: - | V12: - | AH12: - | AI12: - | AO12: - | AQ12: -
B13: Rendement fonds € | C13: Système par points | D13: 2023 : UC < 60% : 3% - UC ≤ 70% : 3,4 % - UC ≤ 80% : 3,6% - UC ≤ 90% : 3,80% - UC > 90% : 4% | E13: Système par points | F13: NC | G13: NC | H13: NC | I13: NC | J13: NC | K13: NC | L13: NC | M13: NC | N13: NC | O13: NC | P13: NC | Q13: NC | R13: NC | S13: NC | T13: NC TMG 2% | U13: NC TMG 2% | V13: NC TMG 2% | W13: NC | X13: NC | Y13: 2022 : UC < 35% : 1,50% - UC < 55% : 2,20% - UC >55% : 2,85% | Z13: 2022 : UC < 35% : 1,50% - UC < 55% : 2,20% - UC >55% : 2,85% | AA13: - | AB13: NC | AC13: NC | AD13: NC | AE13: NC | AF13: - | AG13: NC | AH13: Système par points | AI13: Système par points | AJ13: NC | AK13: NC | AL13: NC | AM13: NC | AN13: NC | AO13: NC TMG 1,5% | AP13: NC | AQ13: NC | AR13: NC | AS13: NC | AT13: NC | AU13: NC | AV13: NC | AW13: NC | AX13: NC | AY13: NC | AZ13: Système par points | BA13: NC | BB13: NC | BC13: NC | BD13: NC | BE13: NC | BF13: NC | BG13: NC | BH13: NC | BI13: NC | BJ13: NC | BK13: NC | BL13: NC | BM13: NC | BN13: NC | BO13: NC | BP13: Système par points | BQ13: Système par points | BR13: NC (25% max fonds €) | BS13: NC (25% max fonds €) | BT13: Système par points | BU13: NC (100% max fonds €) | BV13: NC | BW13: Système par points | BX13: NC | BY13: NC | BZ13: NC | CA13: NC (100% max fonds €) | CG13: Système par points | CH13: NC | DA13: NC | DB13: NC TMG 2% | DC13: NC | DD13: NC | DE13: NC | DW13: NC | DY13: NC | EA13: NC | EB13: Pas de fonds € | EC13: NC | ED13: NC | EE13: NC | EF13: NC TMG 2% | EG13: NC TMG 2,75% | EH13: NC | EI13: NC | EJ13: NC TMG 2,5% | EK13: NC | EL13: NC | EM13: NC | EN13: NC | EO13: NC | EP13: NC | EQ13: NC | ER13: NC TMG 2,5% | ES13: NC | ET13: NC TMG 2,5% | EU13: NC | EV13: NC | EW13: NC | EX13: NC | EY13: NC (TMG à 2% bruts 31/12/16) | EZ13: NC (TMG 1,85% bruts 31/12/16) | FA13: NC (TMG 1,85% bruts 31/12/16) | FB13: NC (TMG 1% bruts 31/12/16) | FC13: NC | FD13: NC | FE13: NC | FY13: NC | GA13: NC | GC13: NC | GD13: NC | GJ13: NC TMG 2% | GK13: NC | HH13: NC | IG13: NC | II13: NC | IK13: NC | IQ13: NC | IR13: NC | IS13: NC | IT13: NC | IU13: NC | IV13: NC | IW13: NC | KN13: NC | KO13: NC | KR13: NC | KX13: NC | LA13: NC | LC13: NC | LQ13: NC | MA13: NC | ML13: NC | MR13: NC | MT13: NC | MU13: NC Points | MV13: NC | MW13: NC | MX13: NC | NA13: NC TMG 3,5% | NG13: NC | NI13: NC | NJ13: NC (TMG sur vst<28/07/18) | NL13: NC | NN13: NC | NO13: NC | NP13: NC | NV13: NC | NX13: NC | OF13: NC
B14: Frais sur versements | C14: 0.035 | D14: 0.045 | E14: 0.02 | F14: 0.025 | G14: 0 | H14: 0.048 | I14: 0.048 | J14: 0.048 | K14: 4,80% puis 4% à partir de 3000€ | L14: 4,80% puis 4% à partir de 5000€ | M14: 0.0475 | N14: 0.0475 | O14: 0.0475 | P14: 0.0475 | Q14: 0.0475 | R14: 0.0475 | S14: 0.045 | T14: 0.0475 | U14: 0.0475 | V14: 0.0475 | W14: 0.0475 | X14: 0.0475 | Y14: 0.0495 | Z14: 0.0475 | AA14: 0.0475 | AB14: 0.036 | AC14: 4% puis 3% à partir de 3750€ puis 2,5% à partir de 15000€ | AD14: 4% puis 3% à partir de 3500€ puis 2,5% à partir de 15000€ | AE14: 0.025 | AF14: 0.03 | AG14: 0.025 | AH14: 2,50% VP 3,50% VL | AI14: 0.04 | AJ14: 0.04 | AK14: 0.05 | AL14: 0.0475 | AM14: 0.04 | AN14: 0.0465 | AO14: 0.0495 | AP14: 0.045 | AQ14: 0.0205 | AR14: 0.0205 | AS14: 0.0465 | AT14: 0.045 | AU14: 0.05 | AV14: 0.048 | AW14: 0.045 | AX14: 0.045 | AY14: 0.045 | AZ14: 0.03 | BA14: 0.05 | BB14: 0.04 | BC14: 0.048 | BD14: 0.048 | BE14: 0.04 | BF14: 0.04 | BG14: 0.04 | BH14: 0.04 | BI14: 0.049 | BJ14: 0.049 | BK14: NC | BL14: 0.049 | BM14: 0.049 | BN14: 0.049 | BO14: 0.04 | BP14: 0.02 | BQ14: 2% dégressif à 1,5% | BR14: 0.029 | BS14: 0.029 | BT14: 2% dégressif à 1,5% | BU14: 0.03 | BV14: 0.025 | BW14: 2% dégressif à 1,5% | BX14: 0.049 | BY14: 0.04 | BZ14: 2,4% dégressif à 1% | CA14: 2,4% dégressif à 1% | CG14: 2% dégressif à 1,5% | CH14: 0.025 | DA14: 4% dégressif à 3% | DB14: 5% dégressif à 4% | DC14: 4% dégressif à 2,25% | DD14: 0.04 | DE14: 0.025 | DW14: 0.045 | DY14: 0.045 | EA14: 0.045 | EB14: 0.045 | EC14: 0.045 | ED14: 0.045 | EE14: 0.0495 | EF14: 0.05 | EG14: 0.065 | EH14: 0.03 | EI14: 0.045 | EJ14: 0.045 | EK14: 0.05 | EL14: 0.05 | EM14: 0.0485 | EN14: 0.045 | EO14: 0.045 | EP14: 0.045 | EQ14: 0.045 | ER14: 0.065 | ES14: 5% dégressif à 4% | ET14: 0.065 | EU14: 0.045 | EV14: 0.03 | EW14: 0.045 | EX14: 0.045 | EY14: 0.05 | EZ14: 0.0495 | FA14: 0.0495 | FB14: 0.0495 | FC14: 0.0495 | FD14: 0.0495 | FE14: 0.045 | FY14: 0.045 | GA14: 0.045 | GC14: 0.03 | GD14: 0.045 | GJ14: 0.049 | GK14: 0.045 | HH14: 0.039 | HT14: 0.045 | IG14: 0.0375 | II14: 0.03 | IK14: 0.025 | IQ14: 4,75% dégressif à 3,25% | IR14: 0.0475 | IS14: 0.0475 | IT14: 0.0475 | IU14: 0.049 | IV14: 0.0475 | IW14: 0.0475 | KN14: 0.05 | KO14: 0.0485 | KR14: 0.045 | KX14: 0.0485 | LA14: 0.0485 | LC14: 0.045 | LQ14: 0.0475 | MA14: 0.045 | ML14: 0.048 | MR14: 0.065 | MT14: 0.048 | MU14: 0.05 | MV14: 0.05 | MW14: 0.05 | MX14: 0.045 | NA14: 0.05 | NG14: 0.05 | NI14: 0.045 | NJ14: 0.045 | NL14: 0.039 | NN14: 0.039 | NO14: 0.039 | NP14: 0.045 | NV14: 0.05 | NX14: 0.05 | OF14: 0.05
B15: Frais de gestion | C15: 0.003 | D15: 0,90% fonds € 1% UC 1,20% SCPI/pilotée/horizon | E15: 0.0037 | F15: 0.006 | G15: 0,60% fonds € 0,5% UC | H15: NC | I15: 0.009 | J15: 0.0095 | K15: 0.0095 | L15: 0.012 | M15: 0.00475 | N15: 0.00475 | O15: 0,65%€ 0,96%UC | P15: 0,65%€ 0,96%UC | Q15: 0,65%€ 0,96%UC | R15: 0,65%€ 0,96%UC | S15: 0.0096 | T15: 0.00475 | U15: 0,65%€ | V15: 0,65%€ | W15: 0,65%€ 0,96%UC | X15: 0,65%€ 0,96%UC | Y15: 0,75%€ 1%UC 0,5%Horizon | Z15: 0,65%€ 0,96%UC | AA15: 0.0065 | AB15: 0.006 | AC15: 0.0096 | AD15: 0.0096 | AE15: 0.0084 | AF15: Variable en fonction des UC | AG15: 0,84%€ 1%UC | AH15: 0.0075 | AI15: 0.005 | AJ15: 0.01 | AK15: 0,54%€ 1%UC | AL15: 0,7%€ 0,96%UC | AM15: 0,80%€ 0,98%UC | AN15: 1%UC 1,80% Mandat 1,193% SCPI | AO15: 0.008 | AP15: 0.01 | AQ15: 0.006 | AR15: 0.006 | AS15: 1%UC 1,80% Mandat 1,193% SCPI | AT15: 0,84%UC 0,96% Mandat 1,193% SCPI | AU15: 0.0096 | AV15: 0.008 | AW15: 1%UC et € 2%Pilotée | AX15: 0.01 | AY15: 2,30%€ 1%UC et horizon 1,90%Pilotée | AZ15: 0.009 | BA15: 0.006 | BB15: 0.008 | BC15: 0.008 | BD15: 0.008 | BE15: 0.008 | BF15: 0.008 | BG15: 0.008 | BH15: 0.008 | BI15: 0.01 | BJ15: 0.01 | BK15: 0.007 | BL15: 1% € et 1,1% UC | BM15: 1% € et 1,1% UC | BN15: 1% € et 1,1% UC | BO15: 0.008 | BP15: 0.007 | BQ15: 0.007 | BR15: 0.009 | BS15: 0.009 | BT15: 0.005 | BU15: 0,8% 1,30% en gestion profilée | BV15: 0,3% € et 1,8% UC | BW15: 0.007 | BX15: 0.0095 | BY15: 0.009 | BZ15: 0.006 | CA15: 0.006 | CG15: 0.007 | CH15: 0,3% € et 1,8% UC | DA15: Fonds € 0,06% - UC 0,80% | DB15: 0.005 | DC15: Fonds € 0,06% - UC 0,75% | DD15: Fonds € 0,70% - UC 1% | DE15: Fonds € 2% - UC 1% - Pilotée 0,6% | DW15: 0,70% (€) – 096% (UC) | DY15: 0,70% (€) – 096% (UC) | EA15: 0,70% (€) – 096% (UC) | EB15: NC | EC15: 0.0096 | ED15: 0.0096 | EE15: 0,60% (€) – 0,96% (UC) | EF15: 0.006 | EG15: NC | EH15: 0.0096 | EI15: 0,80% (€) – 1% (UC) | EJ15: 0.006 | EK15: 0.0096 | EL15: 0.008 | EM15: 0.009 | EN15: 0,80% (€) – 1% (UC) | EO15: 1% (€) – 1,1% (UC) - 0,5% (Gestion Pilotée) | EP15: 0,80% (€) – 1% (UC) | EQ15: 0.0096 | ER15: NC | ES15: 0.0096 | ET15: 0.005 | EU15: 0.009 | EV15: 0.0096 | EW15: 0,80% (€) – 1% (UC) | EX15: 0.006 | EY15: 0.006 | EZ15: 0,60%(€) et 0,96%(UC) | FA15: 0,60%(€) et 0,96%(UC) | FB15: 0,60%(€) et 0,96%(UC) | FC15: 0,60%(€) et 0,96%(UC) | FD15: 0,70%(€) et 0,96%(UC) | FE15: 0,90%(€) et 1%(UC) | FY15: 0.006 | GA15: 0.006 | GC15: 0.009 | GD15: 0,80%(€) et 0,96%(UC) | GJ15: NC | GK15: 0,70% (€) – 096% (UC) | HH15: 0,68% (€) – 0,96% (UC) | HT15: 1% (1.50%Gestion sous mandat) | IG15: 0,70%(€) et 0,95%(UC) | II15: 0.005 | IK15: 0,8%(€) et 0,96%(UC) | IQ15: 0,70% (€) – 0,96% (UC) | IR15: 0,70% (€) – 0,96% (UC) | IS15: 0,70% (€) – 0,96% (UC) | IT15: 0,7%€ 0,96%UC | IU15: 0.0078 | IV15: Libre ou Horizon : 0,80% (€) / 0,85% (UC) / 1,05 (FIA) Gestion déléguée 1,85% | IW15: 0,80% (€) – 0,85% (UC) | KN15: 0.0096 | KO15: 0.012 | KR15: 0.01 | KX15: 0.012 | LA15: 0,8%(€) et 0,96%(UC) | LC15: 1%, (GM : 2,50%) | LQ15: 0,7%€ 0,96%UC | MA15: 0.01 | ML15: 0,7-0,6%(€) et 0,45-0,85%(UC) | MR15: 1% 1,60% Pilotée 1,50% Immo | MT15: 0.0085 | MU15: 0.01 | MV15: 0,75% (€) – 1% (UC) 1,60% gestion pilotée | MW15: 0,75% (€) – 1% (UC) 1,46% gestion pilotée | MX15: 0,80% (€) – 1% (UC) | NA15: 0.0075 | NG15: 0.0096 | NI15: 0.008 | NJ15: 0.008 | NL15: 0.009 | NN15: 0.007 | NO15: 0.007 | NP15: 0.01 | NV15: 0.0095 | NX15: 1% (€) - 1,50% (UC) | OF15: 1% (GM 1,5%)
B16: Frais arbitrage | C16: - | D16: 1er gratuit puis 0,50% (mini 30 € à 200€ maxi) | E16: - | F16: 1er gratuit puis 0,50% (30€ maxi) | G16: 0 | H16: 0.006 | I16: 0.006 | J16: 0.006 | K16: 0.006 | L16: 0.006 | M16: - | N16: - | O16: 1er gratuit puis 0,20% (Mini 30€) | P16: 1er gratuit puis 0,20% (Mini 30€) | Q16: 1er gratuit puis 0,20% (Mini 30€) | R16: 1er gratuit puis 0,20% (Mini 30€) | S16: 1er gratuit puis 0,20% (Mini 30€) | T16: - | U16: - | V16: - | W16: 1er gratuit puis 0,20% (Mini 30€) | X16: 1er gratuit puis 0,20% (Mini 30€) | Y16: 1er gratuit puis 0,20% (Mini 30€) | Z16: 1er gratuit puis 0,20% (Mini 30€) | AA16: 1er gratuit puis 0,20% (Mini 30€) | AB16: NC | AC16: 0,50% plafonné à 75€ | AD16: 0,50% plafonné à 75€ | AE16: 0,50% plafonné à 75€ | AF16: gratuit | AG16: 1er gratuit puis 0,50% gratuit en ligne | AH16: - | AI16: - | AJ16: 1er gratuit puis 0,50% | AK16: 1er gratuit puis 1%+15€ | AL16: 0.01 | AM16: 0,50% plafonné à 75€ | AN16: 0,50% plafonné à 75€ | AO16: - | AP16: 0.005 | AQ16: - | AR16: - | AS16: 0,50% plafonné à 75€ | AT16: 0,50% plafonné à 75€ | AU16: 0.006 | AV16: 0.005 | AW16: 0,50% (Mini 45€) | AX16: 0.006 | AY16: 1% (Mini 45€) | AZ16: - | BA16: - | BB16: 1er gratuit puis 0,50% | BC16: 0.005 | BD16: 0.005 | BE16: 1er gratuit puis 0,50% | BF16: 1er gratuit puis 0,50% | BG16: 1er gratuit puis 0,50% | BH16: 1er gratuit puis 0,50% | BI16: 1er gratuit puis 0,50% | BJ16: 1er gratuit puis 0,50% | BK16: - | BL16: 0.008 | BM16: 0.008 | BN16: 0.008 | BO16: 1er gratuit puis 0,50% | BP16: - | BQ16: - | BR16: 5 gratuits puis 0,5% maxi 150€ | BS16: 5 gratuits puis 0,5% maxi 150€ | BT16: - | BU16: 1 gratuit puis 0,5% maxi 150€ | BV16: 0,1% maxi 30 € | BW16: - | BX16: 1 gratuit puis 1% maxi 150€ | BY16: 5 gratuits puis 0,5% maxi 150€ | BZ16: 1 gratuit puis 0,6% | CA16: 1 gratuit puis 15€ | CG16: - | CH16: 0,1% maxi 30 € | DA16: 0.01 | DB16: - | DC16: 0.01 | DD16: 1 gratuit puis 0,8% maxi 300€ | DE16: 1 gratuit puis 0,6% maxi 300€ | DW16: 0 | DY16: 0 | EA16: 0 | EB16: 0 | EC16: 1 gratuit puis 1% maxi 150€ | ED16: 1 gratuit puis 1% maxi 150€ | EE16: 2 gratuits puis 0,3% maxi 50€ | EF16: - | EG16: - | EH16: 0,5% (maxi 50€) | EI16: 1 gratuit puis 0,5% maxi 150€ | EJ16: 0,5% (maxi 150€) | EK16: 0.006 | EL16: 0.008 | EM16: - | EN16: 0.005 | EO16: 0,5% (15€ en ligne) | EP16: 1 gratuit puis 0,5% maxi 150€ | EQ16: 0.008 | ER16: - | ES16: 1 gratuit puis 1% | ET16: - | EU16: 1 gratuit puis 1% | EV16: 0,5% (maxi 50€) | EW16: 1 gratuit puis 0,5% maxi 150€ | EX16: 1 gratuit puis 0,5% maxi 150€ | EY16: - | EZ16: 2 gratuits puis 0,3% maxi 50€ | FA16: 2 gratuits puis 0,3% maxi 50€ | FB16: 2 gratuits puis 0,3% maxi 50€ | FC16: 3 gratuits puis 0,3% maxi 50€ | FD16: 0,3% (2gratuits) | FE16: 0,5% (15 € en ligne) | FY16: - | GA16: - | GC16: - | GD16: 2 gratuits puis 0,5% maxi 200€ | GJ16: - | GK16: 0 | HH16: 0.005 | HT16: 0 | IG16: 0.005 | II16: - | IK16: 0,5%, 0% en cas de changement de formule | IQ16: 0.01 | IR16: 0.01 | IS16: 0.01 | IT16: 0.01 | IU16: 0.01 | IV16: 0.01 | IW16: 0.01 | KN16: 0.01 | KO16: 1 gratuit puis 1% | KR16: 1 gratuit puis 1% | KX16: - | LA16: 1 gratuit puis 1% | LC16: 0.01 | LQ16: 0.01 | MA16: 1er gratuit puis 0,8% | ML16: 1 gratuit puis 1% | MR16: 0.0095 | MT16: 1 gratuit puis 0,5% | MU16: 1 gratuit puis 0,8% | MV16: 1 gratuit puis 0,8% | MW16: 1 gratuit puis 0,8% | MX16: 1gratuit puis 0,5% (max75€) | NA16: - | NG16: 0.006 | NI16: 1 gratuit puis 15€ | NJ16: 1 gratuit puis 15€ | NL16: 4 gratuits puis 15€ | NN16: 4 gratuits puis 15 | NO16: 4 gratuits puis 15 | NP16: 0.006 | NV16: 0.0055 | NX16: 0,5% (max 300€) | OF16: 0
B17: Frais transfert sortant | C17: 5% (0 après 10 ans) | D17: 1% (0 après 5 ans) | E17: 1% (0 après 5 ans) | F17: 1% (0 après 5 ans) | G17: 0 | H17: 0.04 | I17: 0.04 | J17: 0.04 | K17: 1% 0% après 10ans | L17: 4% 0% après 10ans | M17: NC | N17: NC | O17: 1% 0% après 10ans | P17: 1% 0% après 10ans | Q17: 1% 0% après 10ans | R17: 1% 0% après 10ans | S17: 5% avant 10 ans sinon 0 | T17: 0 | U17: 5% avant 10 ans sinon 0 | V17: 5% avant 10 ans sinon 0 | W17: 1% avant 10 ans sinon 0% | X17: 1% avant 10 ans sinon 0% | Y17: 1% avant 5 ans sinon 0% | Z17: 1% avant 5 ans sinon 0% | AA17: 1% avant 5 ans sinon 0% | AB17: NC | AC17: 0 | AD17: 0 | AE17: 1% avant 5 ans sinon 0% | AF17: NC | AG17: 1% avant 5 ans sinon 0% | AH17: 5% avant 10 ans sinon 0% | AI17: 5% avant 10 ans sinon 0% | AJ17: 1% avant 5 ans sinon 0% | AK17: 3% avant 10 ans sinon 0% | AL17: 2% avant 10 ans sinon 0% | AM17: 1% avant 5 ans sinon 0% | AN17: 2% avant 10 ans sinon 0% | AO17: 5% avant 10 ans sinon 0% | AP17: 1% avant 5 ans sinon 0% | AQ17: 1% avant 5 ans sinon 0% | AR17: 1% avant 5 ans sinon 0% | AS17: 2% avant 10 ans sinon 0% | AT17: 1% avant 5 ans sinon 0% | AU17: 5% avant 10 ans sinon 1 | AV17: 1% avant 10 ans sinon 0% | AW17: 1% avant 5 ans sinon 0% | AX17: 1% avant 5 ans sinon 0% | AY17: 1% avant 5 ans sinon 0% | AZ17: 1% avant 10 ans sinon 0% | BA17: 0.01 | BB17: 0 | BC17: 1% avant 10 ans sinon 0% | BD17: 0 | BE17: 0 | BF17: 0 | BG17: 0 | BH17: 0 | BI17: 0 | BJ17: 0 | BK17: 1,8% avant 10 ans sinon 0% | BL17: 0 | BM17: 0 | BN17: 1% avant 5 ans sinon 0% | BO17: 1% avant 5 ans sinon 0% | BP17: 1% avant 10 ans sinon 0% | BQ17: 1% avant 10 ans sinon 0% | BR17: 1% avant 5 ans sinon 0% | BS17: 1% avant 5 ans sinon 0% | BT17: 1% avant 5 ans sinon 0% | BU17: 1% avant 5 ans sinon 0% | BV17: 0 | BW17: 1% avant 10 ans sinon 0% | BX17: 1% avant 10 ans sinon 0% | BY17: 1% avant 5 ans sinon 0% | BZ17: 0.006 | CA17: 0 | CG17: 1% avant 10 ans sinon 0% | CH17: 0 | DA17: 1% avant 10 ans sinon 0 | DB17: 0 | DC17: 1% avant 10 ans sinon 0 | DD17: 2% avant 10 ans sinon 0 | DE17: 1% avant 5 ans sinon 0 | DW17: 5% avant 10 ans sinon 0 | DY17: 1% avant 10 ans sinon 0 | EA17: 1% avant 5 ans sinon 0% | EB17: 1% avant 5 ans sinon 0% | EC17: NC | ED17: 1% avant 10 ans sinon 0 | EE17: 1% avant 10 ans sinon 0 | EF17: 1% avant 10 ans sinon 0 | EG17: NC | EH17: 1% avant 10 ans sinon 0 | EI17: 1% avant 10 ans sinon 0 | EJ17: 1% avant 10 ans sinon 0 | EK17: 5% avant 10 ans sinon 0 | EL17: 5% avant 10 ans sinon 0 | EM17: 5% avant 10 ans sinon 0 | EN17: 3% avant 10 ans sinon 0 | EO17: 5% avant 10 ans sinon 0% | EP17: 1% avant 10 ans sinon 0% | EQ17: 5% avant 10 ans sinon 0% | ER17: 5% avant 10 ans sinon 0% | ES17: 5% avant 10 ans sinon 0% | ET17: 5% avant 10 ans sinon 0% | EU17: 1% avant 10 ans sinon 0 | EV17: 1% avant 10 ans sinon 0 | EW17: 1% avant 10 ans sinon 0 | EX17: 1% avant 10 ans sinon 0% | EY17: 1% + 5% décroissant avant 10 ans sinon 0% | EZ17: 1% avant 10 ans sinon 0% | FA17: 1% avant 10 ans sinon 0% | FB17: 1% avant 10 ans sinon 0% | FC17: 1% avant 10 ans sinon 0% | FD17: 1% avant 5 ans sinon 0% | FE17: 1% avant 5 ans sinon 0% | FY17: NC | GA17: 5% avant 10 ans sinon 0 | GC17: 0 | GD17: 1% avant 10 ans sinon 0 | GJ17: 0 | GK17: 1% avant 5 ans sinon 0% | HH17: 2% avant 10 ans sinon 0% | HT17: 1% avant 5 ans sinon 0% | IG17: 1% moins de 10 ans sinon 0% | II17: 0 | IK17: 1% avant 5 ans sinon 0% | IQ17: 2% avant 10 ans sinon 0% | IR17: 2% avant 10 ans sinon 0% | IS17: 2% avant 10 ans sinon 0% | IT17: 2% avant 10 ans sinon 0% | IU17: 0 | IV17: 1% avant 5 ans sinon 0% | IW17: 1% avant 5 ans sinon 0% | KN17: 5% avant 10 ans sinon 0 | KO17: 2% avant 10 ans sinon 0 | KR17: 1% avant 10 ans sinon 0 | KX17: 2% avant 10 ans sinon 0 | LA17: 1% avant 5 ans sinon 0 | LC17: 1% avant 5 ans sinon 0 | LQ17: 2% avant 10 ans sinon 0% | MA17: 1% avant 5 ans sinon 0% | ML17: 1% avant 10 ans sinon 0 | MR17: 5% avant 10 ans sinon 0 | MT17: 1% avant 5 ans sinon 0% | MU17: 5% avant 10 ans sinon 0 | MV17: NC | MW17: NC | MX17: 1% avant 5 ans sinon 0% | NA17: 0 | NG17: 5% avant 10 ans sinon 1 | NI17: 1% avant 10 ans sinon 0 | NJ17: 1% avant 10 ans sinon 0 | NL17: 1% avant 10 ans sinon 0 | NN17: 1% avant 5 ans sinon 0% | NO17: 1% avant 5 ans sinon 0% | NP17: 1% avant 5 ans sinon 0% | NV17: 0 | NX17: 0 | OF17: 1% avant 5 ans sinon 0%
B18: Clause bénéficiaire | C18: Standard (Rente viagère conjoint à partir de 55 ans) | D18: Standard (Capital) | E18: Standard (Capital) | F18: Standard (Capital) | G18: Standard (Capital) | H18: Standard (Capital avant retraite sinon rente) | I18: Standard (Capital avant retraite sinon rente) | J18: Standard (Capital avant retraite sinon rente) | K18: Standard (Rente temporaire) | L18: Standard (Rente) | M18: Standard (Capital) | N18: Standard (Capital si option garantie décès) | O18: Standard (Capital ou rente) | P18: Standard (Capital ou rente) | Q18: Standard (Capital ou rente) | R18: Standard (Capital ou rente) | S18: Standard (Rente temporaite ou viagère) | T18: Standard (Rente viagère) | U18: Standard (Rente viagère) | V18: Standard (Rente viagère) | W18: Standard (Rente viagère) | X18: Standard (Rente viagère) | Y18: Standard (Capital) | Z18: Standard (Capital) | AA18: Standard (Capital) | AB18: Standard (Capital) | AC18: Standard (Rente viagère conjoint ou temporaire enfants) | AD18: Standard (Rente viagère) | AE18: Standard (Capital) | AF18: NC | AG18: Standard (Capital) | AH18: Non | AI18: Standard (Rente viagère à hauteur de 60%) | AJ18: Standard (Capital) | AK18: Standard (Rente viagère ou rente temporaire) | AL18: Standard (Rente viagère) | AM18: Standard (Capital) | AN18: Standard (Rente viagère) | AO18: Standard (Rente viagère) | AP18: Standard (Capital) | AQ18: En cas de décès de l’Affilié avant la liquidation de ses droits, et pour le cas où cette option est choisie, les points acquis au moment du décès sont réversibles à hauteur de 60%. | AR18: Pour les nouvelles adéhsions depuis le 01/01/2022 :Standard (Capital) Sinon, si l’Affilié n’avait pas choisi la réversion, il ne bénéficie pas de la garantie décès. | AS18: Standard (Rente viagère) | AT18: Standard (Capital) | AU18: Standard (Rente viagère) | AV18: Standard (Rente viagère) | AW18: Standard (Capital) | AX18: Standard (Capital) | AY18: Standard (Capital) | AZ18: Standard (En cas de décès avant la liquidation, choix au moment de la souscription (rente, capital, rente éducation) | BA18: Standard (En cas de décès avant la liquidation, rente conjoint à 60 ans (mais possiblité d'anticpation)) | BB18: Standard (Rente viagère) | BC18: Standard (Rente viagère) | BD18: Standard (En cas de décès avant liquidation, rente viagère si décès avant 65 ans sinon rien) | BE18: Standard (Rente viagère) | BF18: Standard (Rente viagère) | BG18: Standard (Rente viagère) | BH18: Standard (Rente viagère) | BI18: Standard (Rente viagère) | BJ18: Standard (Rente viagère) | BK18: Standard (En cas de décès avant liquidation, rente viagère si décès avant 65 ans sinon rien) | BL18: Standard (Rente viagère) | BM18: Standard (Rente viagère) | BN18: Standard (Capital) | BO18: Standard (Capital) | BP18: Standard (Rente égale à 60 % des points acquis) | BQ18: Standard (Rente égale à 60 % des points acquis) | BR18: Standard (Capital) | BS18: Standard (Capital) | BT18: Standard (Capital 60% de la valeur en compte) | BU18: Standard (Capital) | BV18: Standard (rente temporaire 10 ans) | BW18: Standard (Rente égale à 60 % des points acquis) | BX18: Standard (Rente viagère) | BY18: Standard (Capital) | BZ18: Standard (Rente viagère) | CA18: Standard (Capital) | CG18: Standard (Rente égale à 60 % des points acquis) | CH18: Standard (rente temporaire 10 ans) | DA18: Standard (Rente viagère) | DB18: Standard (Rente viagère) | DC18: Défaut (rente conjoint) | DD18: Standard (Rente temporaire) | DE18: Standard (Capital) | DW18: Standard (Rente temporaite ou viagère) | DY18: Standard (Rente temporaite ou viagère) | EA18: Standard (Capital) | EB18: Non, compte titre | EC18: Standard Rente temporaire | ED18: Standard (Rente temporaire ou capital) | EE18: Standard (Option 1 : rente temporaire 10 ans)(Option 2T ou 2P : rente viagère majorée bonne fin) | EF18: Standard (Option 1 : rente temporaire 10 ans)(Option 1A et 2 : rente viagère majorée bonne fin) | EG18: Standard (Capital) | EH18: Standard (Rente temporaire) | EI18: Standard (Capital ou Rente temporaire) | EJ18: Standard (Rente temporaire) | EK18: Standard (Rente viagère) | EL18: Standard (Rente viagère) | EM18: Standard (Rente viagère) | EN18: Standard (Rente viagère) | EO18: Standard (Rente viagère) | EP18: Standard (Rente temporaire) | EQ18: Standard (Rente viagère) | ER18: Standard (Rente viagère) | ES18: Standard (Rente viagère) | ET18: Standard (Rente viagère) | EU18: Standard (Rente viagère) | EV18: Standard (Rente viagère) | EW18: Standard (Capital ou Rente temporaire) | EX18: Standard (Capital ou Rente temporaire) | EY18: Standard (Rente temporaire) | EZ18: Standard (Rente temporaire) | FA18: Standard (Rente temporaire) | FB18: Standard (Rente temporaire) | FC18: Standard (Rente temporaire) | FD18: Standard (Capital) | FE18: Standard (Capital) | FY18: Standard (Rente viagère) | GA18: Standard (Rente viagère) | GC18: Standard (Rente viagère option A1) | GD18: Standard (Rente viagère) | GJ18: Standard (Rente viagère) | GK18: Standard (Capital) | HH18: Standard (Rente viagère) | HT18: Standard (Capital) | IG18: Standard (Rente viagère) | II18: Standard (Rente viagère) | IK18: Standard (Capital) | IQ18: Standard (Rente temporaire ou viagère) | IR18: Standard (Rente viagère) | IS18: Standard (Rente temporaire ou viagère) | IT18: Standard (Rente viagère) | IU18: Standard (Rente viagère) | IV18: Standard (Capital) | IW18: Standard (Capital) | KN18: Standard (Rente viagère) | KO18: Standard (Rente viagère) | KR18: Standard (Rente viagère) | KX18: Standard (Rente viagère) | LA18: Standard (Capital) | LC18: Standard (Capital) | LQ18: Standard (Rente viagère) | MA18: Standard (Capital) | ML18: Standard (Rente viagère) | MR18: Standard (Rente viagère) | MT18: Standard (Capital) | MU18: Standard (Rente viagère) | MV18: Standard (Rente viagère) | MW18: Standard (Capital) | MX18: Standard (Capital) | NA18: Capial ou rente | NG18: Standard (Rente viagère) | NI18: Standard (Rente viagère) | NJ18: Standard (Rente viagère) | NL18: Standard (Rente viagère) | NN18: Standard (Capital) | NO18: Standard (Capital) | NP18: Standard (Capital) | NV18: Standard (Capital) | NX18: Standard (Rente viagère) | OF18: Standard (Capital)
B19: Garanties complémentaires | C19: Non | D19: Sur option Plancher Décès Exo cotisations | E19: Non | F19: Sur option Plancher Décès | G19: Sur option Plancher Décès | H19: Inclus : Plancher Décès Sur option : Exo cotisations Rente immédiate | I19: Inclus : Plancher Décès Sur option : Exo cotisations Rente immédiate | J19: Inclus : Plancher Décès Sur option : Exo cotisations Rente immédiate | K19: Sur option Plancher Décès Exo cotisations | L19: Inclus : Plancher Décès | M19: Sur option Rente conjoint viagère Exo cotisations Rente invalidité | N19: Sur option Rente conjoint viagère Exo cotisations Rente invalidité | O19: Inclus : Plancher Décès Sur option : Exo cotisations Bonne fin | P19: Inclus : Plancher Décès Sur option : Exo cotisations Bonne fin | Q19: Inclus : Plancher Décès Sur option : Exo cotisations Bonne fin | R19: Inclus : Plancher Décès Sur option : Exo cotisations Bonne fin | S19: Inclus : Plancher Décès | T19: Non | U19: Sur option : Exo cotisations Bonne fin option1 ou option2 | V19: Sur option : Exo cotisations Bonne fin option1 ou option2 | W19: Inclus : Plancher Décès Sur option : Exo cotisations Bonne fin | X19: Inclus : Plancher Décès Sur option : Exo cotisations Bonne fin | Y19: Inclus : Plancher décès Sur option : Exo cotisations | Z19: Inclus : Plancher décès Sur option : Exo cotisations | AA19: Inclus : Plancher décès | AB19: Inclus : Plancher décès | AC19: Sur option : Exo cotisations | AD19: Inclus : Plancher décès Sur option : Exo cotisations | AE19: Inclus : Plancher décès | AF19: NC | AG19: Inclus : Plancher décès | AH19: Sur option : En cas de décès avant la liquidation, rente viagère calculée sur 60% | AI19: - | AJ19: Inclus : Plancher décès Sur option : Table de mortalité | AK19: Sur option : Plancher décès Exo cotisations Bonne fin Table de mortalité | AL19: Inclus : Plancher décès Sur option : Table garantie | AM19: Inclus : Plancher décès | AN19: Non | AO19: Sur option : Exo cotisations | AP19: Sur option : Plancher décès | AQ19: Sur option : Capital décès avant liquidation | AR19: - | AS19: Non | AT19: Plancher décès (inclus) | AU19: Sur option : Exo cotisations Plancher décès | AV19: Non | AW19: Inclus : Plancher décès Sur option : Exo cotisations | AX19: Sur option : Plancher décès | AY19: Sur option : Exo cotisations Plancher décès | AZ19: Sur option : Exo cotisations Bonne fin | BA19: Sur option : Exo cotisations Dépendance | BB19: Non | BC19: Inclus : Plancher décès | BD19: Inclus : Plancher décès | BE19: Inclus : Plancher décès Sur option : Exo cotisations Bonne fin Table garantie | BF19: Inclus : Plancher décès Exo cotisations Option : Bonne fin | BG19: Inclus : Plancher décès Sur option : Exo cotisations Bonne fin Table garantie | BH19: Inclus : Plancher décès Exo cotisations Option : Bonne fin | BI19: Inclus : Plancher décès Sur option : Exo cotisations Bonne fin Table garantie | BJ19: Inclus : Plancher décès Sur option : Exo cotisations Bonne fin Table garantie | BK19: Non | BL19: Inclus : Plancher décès Exo cotisations Option : Bonne fin | BM19: Inclus : Plancher décès Exo cotisations Option : Bonne fin | BN19: Inclus : Plancher décès Sur option : Exo cotisations Bonne fin | BO19: Inclus : Plancher décès Sur option : Exo cotisations Bonne fin | BP19: Non | BQ19: Option : Bonne fin Exo cotisations Dépendance | BR19: Option : Plancher décès | BS19: Option : Plancher décès | BT19: Non | BU19: Inclus : Plancher décès Sur option : Exo cotisations Table garantie | BV19: Inclus : Plancher décès | BW19: Option : Bonne fin Exo cotisations Dépendance | BX19: Option : Plancher décès Exo cotisations | BY19: Option : Plancher décès Bonne fin | BZ19: Non | CA19: Inclus : Plancher décès | CG19: Option : Bonne fin Exo cotisations Dépendance | CH19: Inclus : Plancher décès | DA19: Option : Plancher décès | DB19: Non | DC19: Option : Plancher décès | DD19: Option : Plancher décès Exo cotisations Table garantie | DE19: Option : Plancher décès | DW19: Sur option : Plancher décès Table garantie | DY19: Sur option : Plancher décès (0,24) Exo des cotisations (+3%) et bonne fin (+12%) Table garantie (+0,48%FG) | EA19: Sur option : Plancher décès (0,24) Exo des cotisations (+3%) et bonne fin (+12%) | EB19: - | EC19: Sur option Bonne fin (5%) Exo des cotisations (2%) Décès 150% (0,5%) | ED19: Sur option Bonne fin (5%) Exo des cotisations (2%) Décès 150% (0,5%) | EE19: Option 1 : rente individuelle Option 2T : rente réversible 100% conjoint Option 2P : rente réversible 60% conjoint Inclus : Bonne fin et exo des cotisations | EF19: Option 1 : rente individuelle Option 1A : rente réversible 60% conjoint Option 2 : rente réversible 100% conjoint Inclus : Bonne fin en 1A et 2 et exo des cotisations (pour toutes) | EG19: Sur option : Exo des cotisations | EH19: Sur option : Exo des cotisations | EI19: Sur option Bonne fin Exo des cotisations Décès 150% | EJ19: Sur option Bonne fin Exo des cotisations Décès 150% | EK19: Sur option Exo des cotisations (3%) | EL19: Non | EM19: Sur option Bonne fin | EN19: Non | EO19: Sur option : Exo des cotisation et plancher décès | EP19: Sur option Bonne fin Exo des cotisations | EQ19: Inclus : Plancher décès Sur option : Bonne fin Exo des cotisations Table garantie | ER19: Inclus : Bonne fin Exo des cotisations | ES19: Sur option : Exo des cotisations | ET19: Inclus : Bonne fin Exo des cotisations | EU19: Sur option : Exo des cotisation (+3%) | EV19: Inclus : Exo des cotisations | EW19: Sur option : Exo des cotisations | EX19: Sur option Bonne fin Exo des cotisations | EY19: Option 1 : rente individuelle Option 1A : rente réversible 60% conjoint Option 2 : rente réversible 100% conjoint Inclus : Bonne fin en 1A et 2 et exo des cotisations (pour toutes) | EZ19: Option 1 : rente individuelle Option 2T : rente réversible 100% conjoint Option 2P : rente réversible 60% conjoint Inclus : Bonne fin et exo des cotisations | FA19: Option 1 : rente individuelle Option 2T : rente réversible 100% conjoint Option 2P : rente réversible 60% conjoint Inclus : Bonne fin et exo des cotisations | FB19: Option 1 : rente individuelle Option 2T : rente réversible 100% conjoint Option 2P : rente réversible 60% conjoint Inclus : Bonne fin et exo des cotisations | FC19: Exo des cotisations et Bonne fin Attention : rente 1(non réversible) rente 2T (100%réversible) ou 2 P (60% réversible) | FD19: Option SR : rente individuelle Option RT : rente réversible 100% conjoint Option RP : rente réversible 60% conjoint Inclus : Bonne fin et exo des cotisations | FE19: Sur option Plancher décès | FY19: Sur option : Transmission, Exo des cotisation et bonne fin | GA19: Sur option : Exo des cotisation | GC19: Sur option : Garantie de bonne fin (option B ) Exo des cotisation (option A2) | GD19: Sur option : Plancher décès, Exo des cotisation (+3%) et bonne fin Table garantie | GJ19: Sur option : Exo des cotisation (+3%) et bonne fin | GK19: Sur option : Plancher décès (0,24) Exo des cotisation (+3%) et bonne fin (+12%) | HH19: Non | HT19: Sur option : Plancher Décès Exo cotisations Décès accidentel | IG19: Non | II19: Sur option : Garantie de rente | IK19: Non | IQ19: Non | IR19: Inclus : Plancher décès | IS19: Inclus : Plancher Décès Sur option : Exo cotisations, Bonne fin | IT19: Inclus : Plancher décès | IU19: Non | IV19: Inclus : Plancher Décès Sur option : Exo cotisations | IW19: Inclus : Plancher Décès | KN19: Option : Plancher décès | KO19: Non | KR19: Option : Plancher décès | KX19: Inclus : Plancher décès | LA19: Inclus : Plancher décès | LC19: Option : Plancher décès | LQ19: Plancher décès (inclus) | MA19: Sur option : plancher décès | ML19: Option : Plancher décès | MR19: Inclus : Plancher décès | MT19: Inclus : Plancher décès | MU19: Non | MV19: Inclus : Plancher décès Sur option : Exo des cotisation (+3%) et bonne fin (+6%) | MW19: Inclus : Plancher décès Option : exo des cotisations (3%) et bonne fin (6%) | MX19: Option : Plancher décès | NA19: Sur option : Exo cotisations | NG19: Sur option : Exo des cotisation (+3%) Plancher décès | NI19: Inclus : Plancher décès Option : Exo des cotisation (+3%) | NJ19: Inclus : Plancher décès Option : Exo des cotisation (+3%) bonne fin (8%) | NL19: Inclus : Plancher décès Option : Exo des cotisation Bonne fin | NN19: Inclus : Plancher décès | NO19: Inclus : Plancher décès Option : Exo des cotisation Table de mortalité | NP19: Option : Plancher décès | NV19: Inclus : Plancher Décès Option : Exo des cotisations | NX19: Inclus : Plancher décès Option : Exo des cotisation (+3%) et bonne fin (+8,75%) | OF19: Inclus : Plancher décès
B20: Age limite liquidation | C20: Non | D20: Non mais versement max jusqu'à 75ans (70ans si retraite) | E20: 75 ans | F20: 75 ans | G20: Non mais versement max jusqu'à 75ans (70ans si retraite) | H20: Non | I20: Non | J20: Non | K20: Non | L20: Non | M20: Non | N20: Non | O20: Non | P20: Non | Q20: Non | R20: Non | S20: Non | T20: Non | U20: Non | V20: Non | W20: Non | X20: Non | Y20: Non | Z20: Non | AA20: Non | AB20: Non | AC20: Non maxi 73 ans | AD20: 85 ans | AE20: Non | AF20: Non | AG20: Oui 80 ans, les prestations devront être liquidées en totalité | AH20: 70 ans | AI20: 70 ans | AJ20: Oui 80 ans, les prestations devront être liquidées en totalité | AK20: 70 ans | AL20: 75 ans | AM20: Non sauf si rente | AN20: Non | AO20: 69 ans | AP20: Non | AQ20: NC | AR20: NC | AS20: Non | AT20: Non | AU20: Non | AV20: Non | AW20: Non | AX20: Non | AY20: Non | AZ20: 70 ans | BA20: 70 ans | BB20: 80 ans | BC20: Non | BD20: 80 ans | BE20: 80 ans | BF20: 80 ans | BG20: 80 ans | BH20: 80 ans | BI20: 80 ans | BJ20: 80 ans | BK20: NC | BL20: 80 ans | BM20: 80 ans | BN20: 80 ans | BO20: 80 ans | BP20: NC | BQ20: NC | BR20: NC | BS20: NC | BT20: NC | BU20: Non | BV20: 75 | BW20: NC | BX20: NC | BY20: NC | BZ20: 70 | CA20: 75 | CG20: NC | CH20: 75 | DA20: Non | DB20: Non | DC20: Non | DD20: 75 ans | DE20: Non | DW20: Espérance de vie -15 ans | DY20: 75 ans | EA20: 75 ans | EB20: NC | EC20: NC | ED20: Terme + 10 ans | EE20: 75 ans | EF20: NC | EG20: NC | EH20: 75 ans | EI20: 70 ans | EJ20: NC | EK20: NC | EL20: NC | EM20: 75 ans | EN20: Espérance de vie -15 ans | EO20: Espérance de vie -15 ans | EP20: 70 ans | EQ20: NC | ER20: NC | ES20: NC | ET20: NC | EU20: NC | EV20: 75 ans | EW20: 70 ans | EX20: NC | EY20: NC | EZ20: 75 ans | FA20: 75 ans | FB20: 75 ans | FC20: 75 ans | FD20: 80 ans | FE20: Non | FY20: NC | GA20: NC | GC20: NC | GD20: NC | GJ20: NC | GK20: 75 ans | HH20: Espérance de vie -15 ans | HT20: Non | IG20: NC | II20: NC | IK20: Non | IQ20: 73 ans | IR20: NC | IS20: 74 ans | IT20: 75 ans | IU20: NC | IV20: Non | IW20: Non | KN20: Espérance de vie - 15 ans | KO20: Espérance de vie - 15 ans | KR20: NC | KX20: 70 ans | LA20: Non | LC20: Non | LQ20: 75 ans | MA20: Non | ML20: Espérance de vie - 15 ans | MR20: NC | MT20: Non | MU20: 75 ans | MV20: 75 ans | MW20: Non | MX20: Non | NA20: NC | NG20: Non | NI20: NC | NJ20: NC | NL20: NC | NN20: Non | NO20: Non | NP20: Non | NV20: NC | NX20: NC | OF20: Non
B21: Sortie capital possible à la retraite | C21: Non | D21: Oui C1;C2 | E21: Oui C1;C2 | F21: Oui C1;C2 | G21: Oui C1;C2 | H21: Non | I21: Non | J21: Non | K21: Non | L21: Non | M21: Non | N21: Non | O21: Non | P21: Non | Q21: Non | R21: Non | S21: Jusqu'à 20% | T21: Non | U21: Non | V21: Non | W21: Non | X21: Non | Y21: Oui C1;C2 | Z21: Oui C1;C2 | AA21: Oui C1;C2 | AB21: Non | AC21: Jusqu'à 20% | AD21: Non | AE21: Oui C1;C2 | AF21: Oui C1;C2 | AG21: Oui C1;C2 | AH21: Jusqu'à 20% | AI21: Non | AJ21: Oui C1;C2 | AK21: Non | AL21: Non | AM21: Oui C1;C2 | AN21: Jusqu'à 20% | AO21: Non | AP21: Oui C1;C2 | AQ21: Jusqu'à 20% C0 | AR21: Oui C1;C2 | AS21: Jusqu'à 20% | AT21: Oui C1;C2 | AU21: Jusqu'à 20% | AV21: Non | AW21: Oui C1;C2 | AX21: Oui C1;C2 | AY21: Oui C1;C2 | AZ21: Non | BA21: Non | BB21: Jusqu'à 20% | BC21: Non | BD21: Non | BE21: Non | BF21: Non | BG21: Non | BH21: Non | BI21: Non | BJ21: Non | BK21: Non | BL21: Non | BM21: Non | BN21: Oui C1;C2 | BO21: Oui C1;C2 | BP21: Jusqu'à 20% | BQ21: Non | BR21: Oui C1;C2 | BS21: Oui C1;C2 | BT21: Oui C1;C2 | BU21: Oui C1;C2 | BV21: Non | BW21: Non | BX21: Non | BY21: Oui C1;C2 | BZ21: Jusqu'à 20% | CA21: Oui C1;C2 | CG21: Non | CH21: Non | DA21: Non | DB21: Non | DC21: Non | DD21: Non | DE21: Oui C1;C2 | DW21: Jusqu'à 20% | DY21: Oui C1;C2 | EA21: Oui C1;C2 | EB21: Oui C1;C2 | EC21: Non | ED21: Non | EE21: Non | EF21: Non | EG21: Non | EH21: Non | EI21: Non | EJ21: Non | EK21: Jusqu'à 20% | EL21: Jusqu'à 20% | EM21: Jusqu'à 20% | EN21: Jusqu'à 20% | EO21: Jusqu'à 20% | EP21: Non | EQ21: Non | ER21: Non | ES21: Non | ET21: Non | EU21: Non | EV21: Non | EW21: Non | EX21: Non | EY21: Non | EZ21: Non | FA21: Non | FB21: Non | FC21: Non | FD21: Oui C1;C2 | FE21: Oui C1;C2 | FY21: Jusqu'à 20% | GA21: Jusqu'à 20% | GC21: Non | GD21: Non | GJ21: Non | GK21: Oui C1;C2 | HH21: Jusqu'à 20% | HT21: Oui C1;C2 | IG21: Non | II21: Non | IK21: Oui C1;C2 | IQ21: Jusqu'à 20% | IR21: Non | IS21: Non | IT21: Non | IU21: Non | IV21: Oui C1;C2 | IW21: Oui C1;C2 | KN21: Jusqu'à 20% | KO21: Jusqu'à 20% | KR21: Non | KX21: Non | LA21: Oui C1;C2 | LC21: Oui C1;C2 | LQ21: Non | MA21: Oui C1;C2 | ML21: Jusqu'à 20% | MR21: Non | MT21: Oui C1;C2 | MU21: Jusqu'à 20% | MV21: Non | MW21: Oui C1;C2 | MX21: Oui C1;C2 | NA21: Non | NG21: Jusqu'à 20% | NI21: Non | NJ21: Non | NL21: Non | NN21: Oui C1;C2 | NO21: Oui C1;C2 | NP21: Oui C1;C2 | NV21: Non | NX21: Non | OF21: Oui C1;C2
B22: Fractionnement du capital | C22: Non | D22: Oui | E22: Oui 2,4,6,10 ans | F22: Oui 2,4,6,10 ans | G22: Oui | H22: Non | I22: Non | J22: Non | K22: Non | L22: Non | M22: Non | N22: Non | O22: Non | P22: Non | Q22: Non | R22: Non | S22: Non | T22: Non | U22: Non | V22: Non | W22: Non | X22: Non | Y22: Oui | Z22: Oui | AA22: Oui | AB22: Non | AC22: Non | AD22: Non | AE22: Oui | AF22: Oui | AG22: Oui | AH22: Non | AI22: Non | AJ22: Oui | AK22: Non | AL22: Non | AM22: Oui | AN22: Non | AO22: Non | AP22: Oui | AQ22: Non | AR22: C1 en 1, 5 ou 10 fois | AS22: Non | AT22: Oui | AU22: Non | AV22: Non | AW22: Oui | AX22: Oui | AY22: Oui | AZ22: Non | BA22: Non | BB22: Non | BC22: Non | BD22: Non | BE22: Non | BF22: Non | BG22: Non | BH22: Non | BI22: Non | BJ22: Non | BK22: Non | BL22: Non | BM22: Non | BN22: Oui | BO22: Oui | BP22: Non | BQ22: Non | BR22: Oui (2 à 6 fois) | BS22: Oui (2 à 6 fois) | BT22: Oui (2 à 4 fois) | BU22: Oui | BV22: Non | BW22: Non | BX22: Non | BY22: Oui (2 à 4 fois) | BZ22: Non | CA22: Oui | CG22: Non | CH22: Non | DA22: Non | DB22: - | DC22: - | DD22: - | DE22: Oui | DW22: Non | DY22: Oui sans limite | EA22: Oui | EB22: NC | EC22: Non | ED22: Non | EE22: Non | EF22: Non | EG22: Non | EH22: Non | EI22: Non | EJ22: Non | EK22: Non | EL22: Non | EM22: Non | EN22: Non | EO22: Non | EP22: Non | EQ22: Non | ER22: Non | ES22: Non | ET22: Non | EU22: Non | EV22: Non | EW22: Non | EX22: Non | EY22: Non | EZ22: Non | FA22: Non | FB22: Non | FC22: Non | FD22: Oui | FE22: Oui | FY22: Non | GA22: Non | GC22: Non | GD22: Non | GJ22: - | GK22: Oui | HH22: Non | HT22: Oui | IG22: Non | II22: Non | IK22: Oui 10 ans maxi | IQ22: Non | IR22: Non | IS22: Non | IT22: Non | IU22: Non | IV22: Oui | IW22: Oui | KN22: Non | KO22: Non | KR22: Non | KX22: Non | LA22: Oui | LC22: Oui | LQ22: Non | MA22: Oui | ML22: Non | MR22: Non | MT22: Oui (25 ans maxi) | MU22: Non | MV22: Non | MW22: Oui | MX22: Oui | NA22: Non | NG22: Non | NI22: Non | NJ22: Non | NL22: Non | NN22: Oui | NO22: Oui | NP22: Oui | NV22: Non | NX22: Non | OF22: Oui
B23: Rachat libre | C23: Non | D23: Oui | E23: Non | F23: Non | G23: Oui | H23: Non | I23: Non | J23: Non | K23: Non | L23: Non | M23: Non | N23: Non | O23: Non | P23: Non | Q23: Non | R23: Non | S23: Non | T23: Non | U23: Non | V23: Non | W23: Non | X23: Non | Y23: NC | Z23: Oui | AA23: Oui | AB23: Non | AC23: Non | AD23: Non | AE23: NC | AF23: NC | AG23: Oui | AH23: Non | AI23: Non | AJ23: Oui | AK23: Non | AL23: Non | AM23: NC | AN23: Non | AO23: Non | AP23: Oui | AQ23: Non | AR23: Non | AS23: Non | AT23: NC | AU23: Non | AV23: Non | AW23: Oui | AX23: NC | AY23: Oui | AZ23: Non | BA23: Non | BB23: Non | BC23: Non | BD23: Non | BE23: Non | BF23: Non | BG23: Non | BH23: Non | BI23: Non | BJ23: Non | BK23: Non | BL23: Non | BM23: Non | BN23: NC | BO23: Oui | BP23: Non | BQ23: Non | BR23: Non | BS23: Non | BT23: Non | BU23: Oui | BV23: Non | BW23: Non | BX23: Non | BY23: Non | BZ23: Non | CA23: Oui | CG23: Non | CH23: Non | DA23: Non | DB23: Non | DC23: Non | DD23: Non | DE23: Oui | DW23: Non | DY23: Non | EA23: NC | EB23: NC | EC23: Non | ED23: Non | EE23: Non | EF23: Non | EG23: Non | EH23: Non | EI23: Non | EJ23: Non | EK23: Non | EL23: Non | EM23: Non | EN23: Non | EO23: Non | EP23: Non | EQ23: Non | ER23: Non | ES23: Non | ET23: Non | EU23: Non | EV23: Non | EW23: Non | EX23: Non | EY23: Non | EZ23: Non | FA23: Non | FB23: Non | FC23: Non | FD23: Non | FE23: Oui | FY23: Non | GA23: Non | GC23: Non | GD23: Non | GJ23: Non | GK23: NC | HH23: Non | HT23: Non | IG23: Non | II23: Non | IK23: Non | IQ23: Non | IR23: Non | IS23: Non | IT23: Non | IU23: Non | IV23: Oui | IW23: Oui | KN23: Non | KO23: Non | KR23: Non | KX23: Non | LA23: Oui | LC23: Oui | LQ23: Non | MA23: Oui | ML23: Non | MR23: Non | MT23: Oui | MU23: Non | MV23: Non | MW23: Oui | MX23: Oui | NA23: Non | NG23: Non | NI23: Non | NJ23: Non | NL23: Non | NN23: Oui | NO23: Oui | NP23: Non | NV23: Non | NX23: Non | OF23: Oui
B24: Table utilisée pour la conversion en rente | C24: Celle du vst Système par points | D24: En vigueur (TGF05) | E24: Celle du vst Système par points | F24: En vigueur (TGF05) | G24: En vigueur (TGF05) | H24: En vigueur (TGF05) | I24: En vigueur (TGF05) | J24: En vigueur (TGF05) | K24: TGF05 | L24: En vigueur (TGF05) | M24: NC | N24: NC | O24: TGF-TGH05 | P24: TGF-TGH05 | Q24: TGF-TGH05 | R24: TGF-TGH05 | S24: En vigueur (TGF05) | T24: TPRV93 | U24: TGF-TGH05 | V24: TGF-TGH05 | W24: TGF05 | X24: TGH05 ou TGF05 | Y24: TGF05 | Z24: TGF05 | AA24: En vigueur (TGF05) | AB24: En vigueur (TGF05) | AC24: En vigueur (TGF05) | AD24: En vigueur (TGF05) | AE24: En vigueur (TGF05) | AF24: En vigueur (TGF05) | AG24: En vigueur (TGF05) | AH24: Celle du vst Système par points | AI24: Celle du vst Système par points | AJ24: En vigueur (TGF05) | AK24: En vigueur (TGF05) | AL24: TGH05 ou TGF05 | AM24: En vigueur (TGF05) | AN24: En vigueur (TGF05) | AO24: En vigueur (TGF05) | AP24: En vigueur (TGF05) | AQ24: Celle du vst Système par points | AR24: Celle du vst Système par points | AS24: En vigueur (TGF05) | AT24: En vigueur (TGF05) | AU24: TGF05 | AV24: En vigueur (TGF05) | AW24: En vigueur (TGF05) | AX24: En vigueur (TGF05) | AY24: En vigueur (TGF05) | AZ24: Celle du vst Système par points | BA24: Celle lors du versement | BB24: En vigueur (TGF05) | BC24: En vigueur (TGF05) | BD24: Celle lors du versement | BE24: Celle lors du versement | BF24: TGF05 | BG24: Celle lors du versement | BH24: TGF05 | BI24: NC | BJ24: NC | BK24: NC | BL24: TGF05 | BM24: TGF05 | BN24: TGF05 | BO24: TGF05 | BP24: Celle du vst Système par points | BQ24: Celle du vst Système par points | BR24: En vigueur (TGF05) | BS24: En vigueur (TGF05) | BT24: Celle du vst Système par points | BU24: En vigueur (TGF05) | BV24: En vigueur (TGF05) | BW24: Celle du vst Système par points | BX24: TGH05 ou TGF05 | BY24: En vigueur (TGF05) | BZ24: En vigueur (TGF05) | CA24: En vigueur (TGF05) | CG24: Celle du vst Système par points | CH24: En vigueur (TGF05) | DA24: En vigueur (TGF05) | DB24: En vigueur (TGF05) | DC24: En vigueur (TGF05) | DD24: En vigueur (TGF05) | DE24: En vigueur (TGF05) | DW24: En vigueur (TGF05) | DY24: En vigueur (TGF05) | EA24: En vigueur (TGF05) | EB24: NC | EC24: NC | ED24: NC | EE24: TGF-TH05 | EF24: TPRV93 ou TGH ou TGF05 | EG24: En vigueur (TGF05) | EH24: TPRV93 ou TGH ou TGF05 | EI24: TGH ou TGF05 | EJ24: TPRV93 | EK24: En vigueur (TGF05) | EL24: En vigueur (TGF05) | EM24: TPRV93 ou TGH ou TGF05 | EN24: En vigueur (TGF05) | EO24: En vigueur (TGF05) | EP24: TPRV93 ou en vigueur | EQ24: En vigueur (TGF05) | ER24: En vigueur (TGF05) | ES24: En vigueur (TGF05) | ET24: NC | EU24: TPG93 | EV24: TPRV93 | EW24: TGH - TGF05 | EX24: TPRV93 | EY24: TPRV93 | EZ24: TGH07/TGF07 avant 31/12/16 puis TGUNI12 | FA24: TGH07/TGF09 avant 31/12/16 puis TGUNI12 | FB24: TGUNI12 | FC24: TGUNI15 | FD24: NC | FE24: En vigueur (TGF05) | FY24: En vigueur (TGF05) | GA24: En vigueur (TGF05) | GC24: Celle du versement | GD24: TGF05 | GJ24: Celle du versement | GK24: En vigueur (TGF05) | HH24: En vigueur (TGF05) | HT24: En vigueur (TGF05) | IG24: En vigueur (TGF05) | II24: En vigueur (TGF05) | IK24: En vigueur (TGF05) | IQ24: En vigueur (TGF05) | IR24: En vigueur (TGF05) | IS24: En vigueur (TGF05) | IT24: TGH05 ou TGF05 | IU24: En vigueur (TGF05) | IV24: En vigueur (TGF05) | IW24: En vigueur (TGF05) | KN24: En vigueur (TGF05) | KO24: En vigueur (TGF05) | KR24: En vigueur (TGF05) | KX24: En vigueur (TGF05) | LA24: En vigueur (TGF05) | LC24: En vigueur (TGF05) | LQ24: TGH05 ou TGF05 | MA24: En vigueur (TGF05) | ML24: En vigueur (TGF05) | MR24: TPRV93 | MT24: En vigueur (TGF05) | MU24: NC (Sytème points) | MV24: NC | MW24: En vigueur (TGF05) | MX24: En vigueur (TGF05) | NA24: Plusieurs | NG24: TGF05 | NI24: TPRV93 | NJ24: TGH05/TGF05 (fonction année) | NL24: TGF05 | NN24: En vigueur (TGF05) | NO24: En vigueur (TGF05) | NP24: En vigueur (TGF05) | NV24: TPRV93 ou TGH-F 05 | NX24: TGH05 ou TGF05 | OF24: En vigueur (TGF05)
B25: Table garantie à l’adhésion | C25: Celle du vst Système par points | D25: Non | E25: Celle du vst Système par points | F25: Non | G25: Non | H25: Non | I25: Non | J25: Non | K25: Oui | L25: Non | M25: NC | N25: NC | O25: Oui | P25: Oui | Q25: Oui uniquement pour les cotisations entreprise | R25: Oui | S25: Non | T25: Oui | U25: Oui | V25: Oui | W25: Oui | X25: Oui | Y25: Oui | Z25: Oui | AA25: Oui | AB25: Non | AC25: Non | AD25: Non | AE25: Non | AF25: Non | AG25: Oui | AH25: Celle du vst Système par points | AI25: Celle du vst Système par points | AJ25: Oui | AK25: En option | AL25: En option | AM25: Non | AN25: Non | AO25: Non | AP25: Non | AQ25: Celle du vst Système par points | AR25: Celle du vst Système par points | AS25: Non | AT25: Non | AU25: Non | AV25: Non | AW25: Sur option (+0,28%FG) | AX25: Non | AY25: Non | AZ25: Celle du vst Système par points | BA25: Celle lors du versement | BB25: Non | BC25: Non | BD25: Celle lors du versement | BE25: Sur option | BF25: Oui | BG25: Sur option | BH25: Oui | BI25: Sur option 0,3% | BJ25: Sur option 0,3% | BK25: Oui | BL25: Oui | BM25: Oui | BN25: Oui | BO25: Oui | BP25: Celle du vst Système par points | BQ25: Celle du vst Système par points | BR25: Non | BS25: Non | BT25: Celle du vst Système par points | BU25: Sur option 0,28% | BV25: Non | BW25: Celle du vst Système par points | BX25: Oui | BY25: Non | BZ25: Non | CA25: Non | CG25: Celle du vst Système par points | CH25: Non | DA25: Non | DB25: Non | DC25: Non | DD25: Sur option 0,36% FG | DE25: Non | DW25: Sur option | DY25: Non | EA25: Non | EB25: NC | EC25: Oui | ED25: Oui | EE25: Oui | EF25: Oui à l'édhésion du salarié | EG25: Non | EH25: Oui à l'édhésion du salarié | EI25: A chaque versement | EJ25: Oui | EK25: Non | EL25: Non | EM25: Oui | EN25: Non | EO25: Non | EP25: Oui pour adhésion avant 31/12/07 | EQ25: Non | ER25: Non | ES25: Non | ET25: NC | EU25: Oui | EV25: Oui | EW25: A chaque versement | EX25: Oui | EY25: Oui | EZ25: Oui (mais avenant sur TGUNI12) | FA25: Oui (mais avenant sur TGUNI12) | FB25: Oui | FC25: Oui | FD25: Oui | FE25: Non | FY25: A chaque versement | GA25: Non | GC25: A chaque versement | GD25: Sur option 0,24%FG | GJ25: Celle du versement | GK25: Non | HH25: Non | HT25: Non | IG25: Oui | II25: Non | IK25: Non | IQ25: Non | IR25: Non | IS25: Sur option 0,31%de FG | IT25: En option | IU25: Non | IV25: Sur option 0,28%de FG | IW25: Non | KN25: Non | KO25: Non | KR25: Non | KX25: Non | LA25: Chaque versement | LC25: Chaque versement | LQ25: En option | MA25: Non | ML25: Non | MR25: Oui | MT25: Sur option 0,30%FG | MU25: Oui | MV25: A chaque versement ou vérifier CG avant 2036 | MW25: A chaque versement | MX25: Sur option (+0,15% de FG) | NA25: Non, à chaque versement | NG25: Non | NI25: Oui | NJ25: Oui | NL25: Oui | NN25: Sur option | NO25: Sur option | NP25: Non | NV25: Oui | NX25: Oui | OF25: Oui
B26: Taux technique | C26: NC | D26: En vigueur (0%) | E26: NC | F26: En vigueur (0%) | G26: En vigueur (0%) | H26: NC | I26: NC | J26: NC | K26: Au choix 0% ou celui de l'assureur | L26: NC | M26: NC | N26: NC | O26: Au choix 0% ou celui de l'assureur | P26: Au choix 0% ou celui de l'assureur | Q26: Au choix 0% ou celui de l'assureur | R26: Au choix 0% ou celui de l'assureur | S26: En vigueur (0%) | T26: Au choix 0% ou celui de l'assureur | U26: Au choix 0% ou celui de l'assureur | V26: Au choix 0% ou celui de l'assureur | W26: Au choix 0% ou celui de l'assureur | X26: Au choix 0% ou celui de l'assureur | Y26: En vigueur (0%) | Z26: En vigueur (0%) | AA26: En vigueur (0%) | AB26: En vigueur (0%) | AC26: En vigueur (0%) | AD26: En vigueur (0%) | AE26: En vigueur (0%) | AF26: En vigueur (0%) | AG26: En vigueur (0%) | AH26: NC | AI26: NC | AJ26: En vigueur (0%) | AK26: Au choix 0% ou celui de l'assureur | AL26: Celui de l'assureur | AM26: En vigueur (0%) | AN26: En vigueur (0%) | AO26: En vigueur (0%) | AP26: En vigueur (0%) | AQ26: 0 | AR26: 0 | AS26: En vigueur (0%) | AT26: En vigueur (0%) | AU26: 0 | AV26: Au choix 0% ou celui de l'assureur | AW26: 0 | AX26: NC | AY26: En vigueur (0%) | AZ26: NC | BA26: En vigueur (0%) | BB26: En vigueur (0%) | BC26: En vigueur (0%) | BD26: NC | BE26: Au moment du versement | BF26: Au moment du versement | BG26: Au moment du versement | BH26: Au moment du versement | BI26: Au moment du versement | BJ26: Au moment du versement | BK26: NC | BL26: Au moment du versement | BM26: Au moment du versement | BN26: En vigueur (0%) | BO26: En vigueur (0%) | BP26: NC | BQ26: NC | BR26: Au choix 0% ou celui de l'assureur | BS26: Au choix 0% ou celui de l'assureur | BT26: NC | BU26: En vigueur (0%) | BV26: NC | BW26: NC | BX26: En vigueur (0%) | BY26: En vigueur (0%) | BZ26: En vigueur (0%) | CA26: En vigueur (0%) | CG26: NC | CH26: NC | DA26: NC | DB26: NC | DC26: NC | DD26: NC | DE26: En vigueur (0%) | DW26: En vigueur (0%) | DY26: En vigueur (0%) | EA26: En vigueur (0%) | EB26: NC | EC26: Sur option en vigueur ou assureur | ED26: Sur option en vigueur ou assureur | EE26: Celui de l'assureur | EF26: Celui de l'assureur (3,50%) | EG26: NC | EH26: 0 | EI26: En vigueur (0%) | EJ26: Sur option en vigueur ou assureur 2,5% | EK26: En vigueur (0%) | EL26: En vigueur (0%) | EM26: En vigueur (0%) | EN26: En vigueur (0%) | EO26: En vigueur (0%) | EP26: En vigueur (0%) | EQ26: En vigueur (0%) | ER26: NC | ES26: NC | ET26: NC | EU26: NC | EV26: 0 | EW26: Celui de l'assureur | EX26: Sur option en vigueur ou assureur 2,5% | EY26: 2,90% nets pour vst avant 31/12/16 puis 0% | EZ26: 1,25% nets pour vst avant 31/12/16 puis 0% | FA26: 1,25% nets pour vst avant 31/12/16 puis 0% | FB26: 1% nets pour vst avant 31/12/16 puis 0% | FC26: 0 | FD26: 0 | FE26: 0 | FY26: Celui de l'assureur | GA26: NC | GC26: Celui de l'assureur | GD26: 0% ou celui de l'assureur | GJ26: NC | GK26: En vigueur (0%) | HH26: 0 | HT26: En vigueur (0%) | IG26: Au choix 0% ou celui de l'assureur | II26: NC | IK26: 0 | IQ26: 0 | IR26: NC | IS26: NC | IT26: Celui de l'assureur | IU26: NC | IV26: En vigueur (0%) | IW26: En vigueur (0%) | KN26: NC | KO26: NC | KR26: NC | KX26: NC | LA26: En vigueur (0%) | LC26: En vigueur (0%) | LQ26: Celui de l'assureur | MA26: 0 | ML26: 0 | MR26: En vigueur (0%) | MT26: 0 | MU26: NC | MV26: NC | MW26: NC | MX26: 0 | NA26: Celui de l'assureur (=TMG) | NG26: 0 | NI26: 0.02 | NJ26: NC | NL26: NC | NN26: 0 | NO26: 0 | NP26: 0 | NV26: 0 | NX26: NC | OF26: Au choix 0% ou celui de l'assureur
